Workbook

Sheet Ficha Contractual
B4: FICHA CONTRACTUAL
B5: Completar al inicio y actualizar ante cualquier modificación
B7: A. DATOS GENERALES DEL CRÉDITO
B8: Acreditado | C8: Red Girasol | D8: ID del Contrato | E8: 2025LP0007
B9: Razón Social | C9: RED GIRASOL SAPI DE CV | D9: Fecha de Firma | E9: 45715
B10: RFC | C10: RGI160414TR9 | D10: Fecha de 1ª disposición | E10: 45723
B11: Tipo de crédito | C11: Simple | D11: Fecha Vencimiento | E11: =EDATE(E10,C13) -> 46819
B12: Monto original (MXN) | C12: 50000000 | D12: Sindicado (si aplica) | E12: No
B13: Plazo (meses) | C13: 36 | D13: Periodicidad de pago capital | E13: Mensual, Despues de 6 meses calendario a partir de la fecha de la primera Disposición
B14: Tasa base | C14: 0.205 | D14: Administrador Maestro | E14: CXC
B15: Tipo de tasa | C15: FIJA | D15: Número de fideicomiso | E15: Fideicomiso - 1403
B17: B. COVENANTS — LÍMITES Y NIVELES DE INCUMPLIMIENTO
B18: Nivel I: Ajustes generales en covenants |Nivel II: Ajuste de tasa +1% y aforo sube a 1.50x | Nivel III: Evento de aceleración
B19: Covenant | C19: Fórmula Modelo Monitoreo | D19: Base | E19: Post-ajuste Nivel I | F19: Post-ajuste Nivel II
B20: COVENANTS ESTÁNDAR (aplican a todos los créditos)
B21: Rentabilidad Operativa | C21: (Gtos venta + Gtos admin + Gtos operación) / (Intereses cobrados + Comisiones cobradas) | D21: 0.29 | E21: 0.25 | F21: 0.29
B22: Cobertura de Deuda | C22: Activos productivos / Pasivos totales [Activos prod. = Bancos + Inversiones + Cartera] | D22: 1 | E22: 1.15 | F22: 1.07
B23: Cartera Vencida Neta | C23: (Cartera Vencida − Reservas) / (Cartera Vigente + Cartera Vencida) | D23: 0.05 | E23: 0.05 | F23: 0.1
B24: Capitalización | C24: (Cartera crédito neta) / Capital Contable Elegible | D24: 0.11 | E24: 0.25 | F24: 0.2
B25: Estimación preventiva de riesgos | C25: Reservas / Cartera vencida | D25: 1 | E25: 1 | F25: 0.8
B26: Coeficiente de liquidez | C26: (Efectivo + Inversiones disponibles + Cobranza programada) / Vencimientos deuda programados | D26: 1.1x | E26: 1.1x | F26: 1.0x
B27: COVENANTS ESPECÍFICOS DEL CONTRATO
B28: IMOR 16 | C28: Cartera vencida 16m / Portafolio 16m | D28: ≤ 7.5% | E28: ≤ 7.5% | F28: TBA
B29: Índice de apalancamiento | C29: Pasivo Total/ Capital Contable Ajustado | D29: ≤ 6.0 | E29: ≤ 5.0 | F29: TBA
B30: Índice de apalancamiento ajustado | C30: Pasivo Total / Derechos de Cobro sobre Participaciones | D30: ≤ 90% | E30: ≤ 85% | F30: TBA
B31: Índice de capitalización | C31: Capital Contable Ajustado / Activo Total | D31: ≥ 13% | E31: ≥ 15% | F31: TBA
B32: Índice de cartera atrasada | C32: Cartera Atrasada / Valor del Portafolio | D32: ≤ 11% | E32: ≤ 11% | F32: TBA
B33: Índice de cartera vencida | C33: Cartera Vencida/ Valor del Portafolio | D33: ≤ 14% | E33: ≤ 14% | F33: TBA
B34: Índice de rendimiento | C34: Ingresos Agregados / Valor del Portafolio | D34: ≥ 28% | E34: ≥ 30% | F34: TBA
B35: Índice de rentabilidad | C35: Utilidad Neta / Valor del Portafolio | D35: ≥ -2% | E35: ≥ 0% | F35: TBA
B36: Aforo mínimo | C36: Ver fórmula completa en pestaña EEFF — CTO A | D36: ≥ 1.35x | E36: ≥ 1.50x* | F36: TBA
B37: * El aforo aplicable cambia a 1.50x ante incumplimiento del escenario base de IMOR 16 (IMOR 16 > 7.5%)
B39: C. EVENTOS DE INCUMPLIMIENTO — CONSECUENCIAS POR NIVEL
B40: Nivel | C40: Descripción | D40: Consecuencias contractuales | G40: Fecha de activación
B41: Nivel I | C41: Incumplimiento de Niveles I de los covenants | D41: Ajustes en las condiciones generales de los covenants base | G41: 45870
B42: Nivel II | C42: Incumplimiento de Niveles II de los covenants | D42: Ajuste de tasa de interés +1% sobre la tasa vigente. Aforo mínimo requerido sube a 1.50x. | G42: [Fecha]
B43: [Otro evento] | C43: [Describir el evento de incumplimiento adicional según el contrato] | D43: Se considera Evento de Aceleración. El acreditante puede exigir el pago anticipado de la totalidad del crédito. | G43: [Fecha]
B45: D. DEFINICIONES CONTRACTUALES CLAVE
B46: Concepto | C46: Definición resumida
B47: Cartera Vigente | C47: Créditos al corriente sin días de atraso.
B48: Cartera Atrasada | C48: >30 y <90 días de atraso; o adeudo equiv. a pagos entre 30 y 90 días previos.
B49: Cartera Vencida | C49: En concurso mercantil; ≥90 días de atraso; o adeudo equiv. a 90 días previos.
B50: Reservas para futuras pérdidas | C50: Estimación preventiva de riesgos constituida conforme a criterios contables aplicables.
B51: Capital Contable Ajustado / Elegible | C51: Cap. social suscrito + utilidades ejercicios anteriores + utilidades año corriente − CxC neto.
B52: Valor del Portafolio | C52: Saldo D/C Participaciones − créditos >36 meses que califican como cartera vencida.
B53: Activos Productivos | C53: Bancos + Inversiones (disponibles y no comprometidas) + Cartera de crédito.
B54: Ingresos Agregados | C54: Ingresos por comisiones + intereses cobrados. [Verificar definición contractual exacta]
B55: Cobranza Programada | C55: Pagos de capital e intereses programados para los próximos [n] meses. [Definir según contrato]
B56: Vencimientos de Deuda Programados | C56: Pagos de capital e intereses de pasivos exigibles en los próximos [n] meses.
B57: Valor Presente Neto | C57: Flujos futuros descontados a Tasa Interés / 12. Suma de (flujo ÷ (1+Tasa Mensual)^n).
... B60: [Concepto adicional 3] | C60: [Definir según contrato]
B62: E. CALENDARIO DE DOCUMENTOS REQUERIDOS
B63: Documento | C63: Frecuencia | D63: Día límite | E63: Notas
B64: Loan Tape | C64: Mensual | D64: Día 10 | E64: Cálculo de IMOR, cartera, aforo
B65: Estados Financieros (BG + ER) | C65: Mensual | D65: Día 15
B66: Certificado de cumplimiento | C66: Mensual | D66: 15 días post-cierre | E66: Adjuntar pestaña Obligaciones
B67: Desglose de Pasivos | C67: Trimestral | D67: 15 días post-cierre
B68: Reporte de Buró de Crédito | C68: Mensual | D68: Día 5 | E68: Verificar autorización vigente
B69: Reporte Syntage | C69: Mensual | D69: Día 5
B70: Reporte mensual Fideicomiso | C70: Mensual | D70: Día 10 | E70: Solo si aplica
B71: Declaraciones fiscales anuales | C71: Anual | D71: 30 días post-presentación
B72: [Documento adicional]

Sheet Obligaciones
B4: OBLIGACIONES DE HACER Y NO HACER
B5: Documento informativo · Adjuntar al correo de solicitud del certificado de cumplimiento trimestral
B7: Este documento es un resumen ejecutivo sobre las obligaciones contractuales. Las obligaciones completas, sus definiciones y consecuencias de incumplimiento constan en el Contrato de Crédito respectivo.
B9: I. OBLIGACIONES DE HACER
B10: # | C10: Obligación | D10: Frecuencia / Plazo
B11: 1 | C11: Entregar balances y estados de resultados internos mensuales dentro de los 15 días posteriores al cierre de cada mes. | D11: Mensual — día 15
B12: 2 | C12: Proporcionar estados financieros auditados por un contador independiente dentro de los 120 días siguientes al cierre del ejercicio fiscal. | D12: Anual — Hasta 120 días
B13: 3 | C13: Entregar, junto con la información financiera, un certificado que acredite el cumplimiento de las obligaciones financieras y la inexistencia de incumplimientos. | D13: Mensual — día 15
B14: 4 | C14: Mantener una conexión en tiempo real entre sus sistemas contables y de cobranza con el Agente Administrativo y el Administrador Maestro. Que permitan al agente administrativo el acceso en todo momento a la información relacionada con los Derecho de Cobro Transmitidos | D14: Continua
B15: 5 | C15: Informar al Agente Administrativo sobre cualquier "Efecto Adverso de Importancia" o incumplimiento en un plazo máximo de 5 días hábiles. | D15: Inmediato al evento
B16: 6 | C16: Notificar sobre litigios cuya cuantía exceda los $5,000,000.00 MXN o multas impuestas por autoridades que superen dicho umbral. | D16: Inmediato al evento
B17: 7 | C17: Observar todas las leyes aplicables (especialmente LRITF, LTOSF y LPDUSF), así como presentar y pagar impuestos de manera oportuna. | D17: Continua
B18: 8 | C18: Realizar todos los actos necesarios para transmitir los Derechos de Cobro al Patrimonio del Fideicomiso y mantener vigente el Contrato de Factoraje. | D18: Continua
B19: 9 | C19: Mantener covenants financieros dentro de los límites del contrato. | D19: Mensual
B20: 10 | C20: Permitir al Agente Administrativo auditar sus bienes y libros con un aviso previo de 5 días. | D20: A Solicitud
B21: 11 | C21: Mantener en el fideicomiso el monto necesario para cubrir capital e intereses de la siguiente fecha de pago. | D21: Continua
B23: II. OBLIGACIONES DE NO HACER
B24: # | C24: Restricción | D24: Condiciones / Excepciones
B25: 1 | C25: No contratar nueva deuda, salvo la ya existente o aquella que no cause incumplimiento en sus obligaciones financieras. | D25: Con autorización escrita previa
B26: 2 | C26: No otorgar garantías a favor de terceros o constituir gravámenes sobre sus activos (especialmente sobre los que forman parte del patrimonio del fideicomiso). | D26: Ver covenants de capitalización y cobertura
B27: 3 | C27: No realizar fusiones, escisiones, disoluciones o ventas de activos sustanciales, ni cambiar la naturaleza de su negocio. | D27: Ver condiciones específicas del contrato
B28: 4 | C28: No distribuir dividendos si esto resulta en un incumplimiento de sus obligaciones bajo los Documentos del Crédito. | D28: Ver condiciones específicas del contrato
B29: 5 | C29: No realizar pagos extraordinarios de salarios o bonos a accionistas o funcionarios fuera de términos de mercado o que afecten los límites financieros. | D29: Ver condiciones específicas del contrato
B30: 6 | C30: No realizar un "Cambio de Control" (perder el control o bajar del 50% de los valores representativos de capital). | D30: Ver condiciones específicas del contrato
B31: 7 | C31: No modificar sus políticas de otorgamiento de crédito o los formatos de contratos con sus clientes (Contratos de Crédito Red Girasol) sin autorización. | D31: Ver condiciones específicas del contrato
B32: 8 | C32: No Participar en actividades ilícitas, producción de armas, tabaco, juegos de azar o aquellas que dañen el medio ambiente.
B33: 9 | C33: No permitir que otras obligaciones quirografarias tengan mayor preferencia de pago que el crédito presente.

Sheet Supuestos
A1: MODELO
A2: Inicio Crédito Syscap | B2: Dic-24 | C2: Cuentas por cobrar, neto | D2: 0
A3: Disp. Inicial | B3: 5000000 | C3: Pagos anticipados y otros activos, neto | D3: 1500000
A4: Cobranza | B4: 0.9 | C4: Propiedades, mobiliario y equipo, neto | D4: 200000
A5: Crecimiento Cartera | B5: 0.0075 | C5: CAPITALIZACIÓN | D5: 20000000
A6: Crecimiento Gastos | B6: 0.06 | C6: Castigo Tasa Activa | D6: 0.015
A8: CARTERA
A9: # de Registros | B9: =COUNT(#REF!) -> 0 | C9: Días de Atraso Vencimientos | D9: 90
A10: Primer Crédito | B10: =MIN(#REF!)-DAY(MIN(#REF!))+1 -> #REF! | C10: Participación Histórica | D10: 0.01
A11: Tasa Activa Ponderada | B11: =SUMPRODUCT(#REF!,#REF!) -> #REF! | C11: Inicio Com. Apertura | D11: 44986
A12: Fecha LT | B12: 45657
A13: COMISIONES
A14: Tipo Producto | B14: Preoriginación | C14: Contratación | D14: Administración | E14: Notas
A15: Verde | B15: 0.02 | C15: 0.06 | D15: 0 | E15: Antes del 1 de Enero 2023
A16: Verde+ | B16: 0.02 | C16: 0 | D16: 0.01 | E16: Entre 01/01/23 y 01/01/24 - SOBRE EL SALDO INSOLUTO
A17: Crédito Automotriz | B17: 0.02 | C17: 0.015 | D17: 0.011 | E17: A partir del 2024
A18: Crédito Personal | B18: 0.02 | C18: 0.02 | D18: 0.0135 | E18: A partir del 2024
A19: Crédito PYME | B19: 0.02 | C19: 0.015 | D19: 0.011 | E19: A partir del 2024
A20: Crédito Solar | B20: 0.02 | C20: 0.01 | D20: 0.0085 | E20: A partir del 2024
A21: Comisión Éxito Vieja | B21: 0.02 | E21: Sobre cobranza total (intereses y amortizaciones)
A22: Comisión Éxito Nueva | B22: 0.1 | C22: Desde | D22: 45536 | E22: Sobre intereses a partir de Sep. 2024

Sheet Crédito Syscap
A1: Mes | B1: Saldo Inicial | C1: Disposiciones | D1: Pago | E1: Interés | F1: Amortización | G1: Saldo Final | H1: Comisión Estr | I1: Comisión Admin | J1: Total Comisiones
A2: 0 | B2: 0 | C2: 20000000
A3: 1 | B3: =C2 -> 20000000 | C3: 15000000 | D3: =IF(A3<=$B$45, E3, IF(B3>0, B3*(($B$40/12)/(1-(1+($B$40/12))^(-($B$44-A3+1)))), 0)) -> 350000 | E3: =B3*$B$40/12 -> 350000 | F3: =IF(A3<=$B$45, 0, D3-E3) -> 0 | G3: =B3-F3 -> 20000000 | H3: =C2*$B$47 -> 400000 | I3: =($B$42*$B$48/12) -> 20833.333 | J3: =H3+I3 -> 420833.33
A4: 2 | B4: =G3+C3 -> 35000000 | C4: 15000000 | D4: =IF(A4<=$B$45, E4, IF(B4>0, B4*(($B$40/12)/(1-(1+($B$40/12))^(-($B$44-A4+1)))), 0)) -> 612500 | E4: =B4*$B$40/12 -> 612500 | F4: =IF(A4<=$B$45, 0, D4-E4) -> 0 | G4: =B4-F4 -> 35000000 | H4: =C3*$B$47 -> 300000 | I4: =($B$42*$B$48/12) -> 20833.333 | J4: =H4+I4 -> 320833.33
A5: 3 | B5: =G4+C4 -> 50000000 | C5: 0 | D5: =IF(A5<=$B$45, E5, IF(B5>0, B5*(($B$40/12)/(1-(1+($B$40/12))^(-($B$44-A5+1)))), 0)) -> 875000 | E5: =B5*$B$40/12 -> 875000 | F5: =IF(A5<=$B$45, 0, D5-E5) -> 0 | G5: =B5-F5 -> 50000000 | H5: =C4*$B$47 -> 300000 | I5: =($B$42*$B$48/12) -> 20833.333 | J5: =H5+I5 -> 320833.33
A6: 4 | B6: =G5+C5 -> 50000000 | C6: 0 | D6: =IF(A6<=$B$45, E6, IF(B6>0, B6*(($B$40/12)/(1-(1+($B$40/12))^(-($B$44-A6+1)))), 0)) -> 875000 | E6: =B6*$B$40/12 -> 875000 | F6: =IF(A6<=$B$45, 0, D6-E6) -> 0 | G6: =B6-F6 -> 50000000 | H6: =C5*$B$47 -> 0 | I6: =($B$42*$B$48/12) -> 20833.333 | J6: =H6+I6 -> 20833.333
A7: 5 | B7: =G6+C6 -> 50000000 | C7: 0 | D7: =IF(A7<=$B$45, E7, IF(B7>0, B7*(($B$40/12)/(1-(1+($B$40/12))^(-($B$44-A7+1)))), 0)) -> 875000 | E7: =B7*$B$40/12 -> 875000 | F7: =IF(A7<=$B$45, 0, D7-E7) -> 0 | G7: =B7-F7 -> 50000000 | H7: =C6*$B$47 -> 0 | I7: =($B$42*$B$48/12) -> 20833.333 | J7: =H7+I7 -> 20833.333
A8: 6 | B8: =G7+C7 -> 50000000 | C8: 0 | D8: =IF(A8<=$B$45, E8, IF(B8>0, B8*(($B$40/12)/(1-(1+($B$40/12))^(-($B$44-A8+1)))), 0)) -> 875000 | E8: =B8*$B$40/12 -> 875000 | F8: =IF(A8<=$B$45, 0, D8-E8) -> 0 | G8: =B8-F8 -> 50000000 | H8: =C7*$B$47 -> 0 | I8: =($B$42*$B$48/12) -> 20833.333 | J8: =H8+I8 -> 20833.333
A9: 7 | B9: =G8+C8 -> 50000000 | C9: 0 | D9: =IF(A9<=$B$45, E9, IF(B9>0, B9*(($B$40/12)/(1-(1+($B$40/12))^(-($B$44-A9+1)))), 0)) -> 2156487.7 | E9: =B9*$B$40/12 -> 875000 | F9: =IF(A9<=$B$45, 0, D9-E9) -> 1281487.7 | G9: =B9-F9 -> 48718512 | H9: =C8*$B$47 -> 0 | I9: =($B$42*$B$48/12) -> 20833.333 | J9: =H9+I9 -> 20833.333
A10: 8 | B10: =G9+C9 -> 48718512 | C10: 0 | D10: =IF(A10<=$B$45, E10, IF(B10>0, B10*(($B$40/12)/(1-(1+($B$40/12))^(-($B$44-A10+1)))), 0)) -> 2156487.7 | E10: =B10*$B$40/12 -> 852573.96 | F10: =IF(A10<=$B$45, 0, D10-E10) -> 1303913.8 | G10: =B10-F10 -> 47414598 | H10: =C9*$B$47 -> 0 | I10: =($B$42*$B$48/12) -> 20833.333 | J10: =H10+I10 -> 20833.333
A11: 9 | B11: =G10+C10 -> 47414598 | C11: 0 | D11: =IF(A11<=$B$45, E11, IF(B11>0, B11*(($B$40/12)/(1-(1+($B$40/12))^(-($B$44-A11+1)))), 0)) -> 2156487.7 | E11: =B11*$B$40/12 -> 829755.47 | F11: =IF(A11<=$B$45, 0, D11-E11) -> 1326732.3 | G11: =B11-F11 -> 46087866 | H11: =C10*$B$47 -> 0 | I11: =($B$42*$B$48/12) -> 20833.333 | J11: =H11+I11 -> 20833.333
A12: 10 | B12: =G11+C11 -> 46087866 | D12: =IF(A12<=$B$45, E12, IF(B12>0, B12*(($B$40/12)/(1-(1+($B$40/12))^(-($B$44-A12+1)))), 0)) -> 2156487.7 | E12: =B12*$B$40/12 -> 806537.66 | F12: =IF(A12<=$B$45, 0, D12-E12) -> 1349950.1 | G12: =B12-F12 -> 44737916 | H12: =C11*$B$47 -> 0 | I12: =($B$42*$B$48/12) -> 20833.333 | J12: =H12+I12 -> 20833.333
A13: 11 | B13: =G12+C12 -> 44737916 | D13: =IF(A13<=$B$45, E13, IF(B13>0, B13*(($B$40/12)/(1-(1+($B$40/12))^(-($B$44-A13+1)))), 0)) -> 2156487.7 | E13: =B13*$B$40/12 -> 782913.53 | F13: =IF(A13<=$B$45, 0, D13-E13) -> 1373574.2 | G13: =B13-F13 -> 43364342 | H13: =C12*$B$47 -> 0 | I13: =($B$42*$B$48/12) -> 20833.333 | J13: =H13+I13 -> 20833.333
A14: 12 | B14: =G13+C13 -> 43364342 | D14: =IF(A14<=$B$45, E14, IF(B14>0, B14*(($B$40/12)/(1-(1+($B$40/12))^(-($B$44-A14+1)))), 0)) -> 2156487.7 | E14: =B14*$B$40/12 -> 758875.98 | F14: =IF(A14<=$B$45, 0, D14-E14) -> 1397611.8 | G14: =B14-F14 -> 41966730 | H14: =C13*$B$47 -> 0 | I14: =($B$42*$B$48/12) -> 20833.333 | J14: =H14+I14 -> 20833.333
A15: 13 | B15: =G14+C14 -> 41966730 | D15: =IF(A15<=$B$45, E15, IF(B15>0, B15*(($B$40/12)/(1-(1+($B$40/12))^(-($B$44-A15+1)))), 0)) -> 2156487.7 | E15: =B15*$B$40/12 -> 734417.78 | F15: =IF(A15<=$B$45, 0, D15-E15) -> 1422070 | G15: =B15-F15 -> 40544660 | H15: =C14*$B$47 -> 0 | I15: =($B$42*$B$48/12) -> 20833.333 | J15: =H15+I15 -> 20833.333
A16: 14 | B16: =G15+C15 -> 40544660 | D16: =IF(A16<=$B$45, E16, IF(B16>0, B16*(($B$40/12)/(1-(1+($B$40/12))^(-($B$44-A16+1)))), 0)) -> 2156487.7 | E16: =B16*$B$40/12 -> 709531.55 | F16: =IF(A16<=$B$45, 0, D16-E16) -> 1446956.2 | G16: =B16-F16 -> 39097704 | H16: =C15*$B$47 -> 0 | I16: =($B$42*$B$48/12) -> 20833.333 | J16: =H16+I16 -> 20833.333
A17: 15 | B17: =G16+C16 -> 39097704 | D17: =IF(A17<=$B$45, E17, IF(B17>0, B17*(($B$40/12)/(1-(1+($B$40/12))^(-($B$44-A17+1)))), 0)) -> 2156487.7 | E17: =B17*$B$40/12 -> 684209.82 | F17: =IF(A17<=$B$45, 0, D17-E17) -> 1472277.9 | G17: =B17-F17 -> 37625426 | H17: =C16*$B$47 -> 0 | I17: =($B$42*$B$48/12) -> 20833.333 | J17: =H17+I17 -> 20833.333
A18: 16 | B18: =G17+C17 -> 37625426 | D18: =IF(A18<=$B$45, E18, IF(B18>0, B18*(($B$40/12)/(1-(1+($B$40/12))^(-($B$44-A18+1)))), 0)) -> 2156487.7 | E18: =B18*$B$40/12 -> 658444.96 | F18: =IF(A18<=$B$45, 0, D18-E18) -> 1498042.8 | G18: =B18-F18 -> 36127383 | H18: =C17*$B$47 -> 0 | I18: =($B$42*$B$48/12) -> 20833.333 | J18: =H18+I18 -> 20833.333
A19: 17 | B19: =G18+C18 -> 36127383 | D19: =IF(A19<=$B$45, E19, IF(B19>0, B19*(($B$40/12)/(1-(1+($B$40/12))^(-($B$44-A19+1)))), 0)) -> 2156487.7 | E19: =B19*$B$40/12 -> 632229.21 | F19: =IF(A19<=$B$45, 0, D19-E19) -> 1524258.5 | G19: =B19-F19 -> 34603125 | H19: =C18*$B$47 -> 0 | I19: =($B$42*$B$48/12) -> 20833.333 | J19: =H19+I19 -> 20833.333
A20: 18 | B20: =G19+C19 -> 34603125 | D20: =IF(A20<=$B$45, E20, IF(B20>0, B20*(($B$40/12)/(1-(1+($B$40/12))^(-($B$44-A20+1)))), 0)) -> 2156487.7 | E20: =B20*$B$40/12 -> 605554.68 | F20: =IF(A20<=$B$45, 0, D20-E20) -> 1550933.1 | G20: =B20-F20 -> 33052192 | H20: =C19*$B$47 -> 0 | I20: =($B$42*$B$48/12) -> 20833.333 | J20: =H20+I20 -> 20833.333
A21: 19 | B21: =G20+C20 -> 33052192 | D21: =IF(A21<=$B$45, E21, IF(B21>0, B21*(($B$40/12)/(1-(1+($B$40/12))^(-($B$44-A21+1)))), 0)) -> 2156487.7 | E21: =B21*$B$40/12 -> 578413.35 | F21: =IF(A21<=$B$45, 0, D21-E21) -> 1578074.4 | G21: =B21-F21 -> 31474117 | H21: =C20*$B$47 -> 0 | I21: =($B$42*$B$48/12) -> 20833.333 | J21: =H21+I21 -> 20833.333
A22: 20 | B22: =G21+C21 -> 31474117 | D22: =IF(A22<=$B$45, E22, IF(B22>0, B22*(($B$40/12)/(1-(1+($B$40/12))^(-($B$44-A22+1)))), 0)) -> 2156487.7 | E22: =B22*$B$40/12 -> 550797.05 | F22: =IF(A22<=$B$45, 0, D22-E22) -> 1605690.7 | G22: =B22-F22 -> 29868427 | H22: =C21*$B$47 -> 0 | I22: =($B$42*$B$48/12) -> 20833.333 | J22: =H22+I22 -> 20833.333
A23: 21 | B23: =G22+C22 -> 29868427 | D23: =IF(A23<=$B$45, E23, IF(B23>0, B23*(($B$40/12)/(1-(1+($B$40/12))^(-($B$44-A23+1)))), 0)) -> 2156487.7 | E23: =B23*$B$40/12 -> 522697.46 | F23: =IF(A23<=$B$45, 0, D23-E23) -> 1633790.3 | G23: =B23-F23 -> 28234636 | H23: =C22*$B$47 -> 0 | I23: =($B$42*$B$48/12) -> 20833.333 | J23: =H23+I23 -> 20833.333
... A38: 36 | B38: =G37+C37 -> 2119398.3 | D38: =IF(A38<=$B$45, E38, IF(B38>0, B38*(($B$40/12)/(1-(1+($B$40/12))^(-($B$44-A38+1)))), 0)) -> 2156487.7 | E38: =B38*$B$40/12 -> 37089.47 | F38: =IF(A38<=$B$45, 0, D38-E38) -> 2119398.3 | G38: =B38-F38 -> 1.1175871e-08 | H38: =C37*$B$47 -> 0 | I38: =($B$42*$B$48/12) -> 20833.333 | J38: =H38+I38 -> 20833.333
A40: Tasa | B40: 0.21
A41: Monto Disposiciones | B41: 10000000
A42: Saldo Total Línea | B42: 50000000
A43: Cantidad de Disp. | B43: 2
A44: Plazo | B44: 36
A45: Gracia de Capital | B45: 6
A46: Gastos Notariales | B46: 550000
A47: Comisión Estr. | B47: 0.02
A48: Comisión Admin. | B48: 0.005

Sheet Monitoreo
B2: IMOR 16
B3: 45657 | C3: =EOMONTH(B3,1) -> 45688 | D3: =EOMONTH(C3,1) -> 45716 | E3: =EOMONTH(D3,1) -> 45747 | F3: =EOMONTH(E3,1) -> 45777 | G3: =EOMONTH(F3,1) -> 45808 | H3: =EOMONTH(G3,1) -> 45838 | I3: =EOMONTH(H3,1) -> 45869 | J3: =EOMONTH(I3,1) -> 45900 | ... BJ3: =EOMONTH(BI3,1) -> 47483
A4: RL | B4: ='Efs Real'!L69 -> 0.051749426 | D4: ='Efs Real'!N69 -> 0.038760461 | E4: ='Efs Real'!O69 -> 0.037997795 | F4: ='Efs Real'!P69 -> 0.02464623 | G4: ='Efs Real'!Q69 -> 0.071112877 | H4: ='Efs Real'!R69 -> 0.074020122 | I4: ='Efs Real'!S69 -> 0.098921489 | J4: ='Efs Real'!T69 -> 0.11188499 | K4: ='Efs Real'!U69 -> 0.13215844 | ... P4: ='Efs Real'!Z69 -> 0.067340333
A5: MAX | B5: 0.075 | C5: 0.075 | D5: 0.075 | E5: 0.075 | F5: 0.075 | G5: 0.075 | H5: 0.075 | I5: 0.075 | J5: 0.075 | K5: 0.075 | L5: 0.075 | M5: 0.075 | N5: 0.075 | O5: 0.075 | P5: 0.075 | Q5: 0.075 | R5: 0.075 | S5: 0.075 | T5: 0.075 | U5: 0.075 | V5: 0.075 | W5: 0.075 | X5: 0.075 | Y5: 0.075 | Z5: 0.075 | AA5: 0.075 | AB5: 0.075 | AC5: 0.075 | AD5: 0.075 | AE5: 0.075 | AF5: 0.075 | AG5: 0.075 | AH5: 0.075 | AI5: 0.075 | AJ5: 0.075 | AK5: 0.075 | AL5: 0.075 | AM5: 0.075 | AN5: 0.075 | AO5: 0.075 | AP5: 0.075 | AQ5: 0.075 | AR5: 0.075 | AS5: 0.075 | AT5: 0.075 | AU5: 0.075 | AV5: 0.075 | AW5: 0.075 | AX5: 0.075 | AY5: 0.075 | AZ5: 0.075 | BA5: 0.075 | BB5: 0.075 | BC5: 0.075 | BD5: 0.075 | BE5: 0.075 | BF5: 0.075 | BG5: 0.075 | BH5: 0.075 | BI5: 0.075 | BJ5: 0.075
B7: Indice de apalancamiento
B8: 45657 | C8: =EOMONTH(B8,1) -> 45688 | D8: =EOMONTH(C8,1) -> 45716 | E8: =EOMONTH(D8,1) -> 45747 | F8: =EOMONTH(E8,1) -> 45777 | G8: =EOMONTH(F8,1) -> 45808 | H8: =EOMONTH(G8,1) -> 45838 | I8: =EOMONTH(H8,1) -> 45869 | J8: =EOMONTH(I8,1) -> 45900 | ... BJ8: =EOMONTH(BI8,1) -> 47483
A9: OG | B9: ='Efs OG'!CS84 -> 0.79734677 | C9: ='Efs OG'!CT84 -> 0.79016044 | D9: ='Efs OG'!CU84 -> 2.058031 | E9: ='Efs OG'!CV84 -> 2.9822117 | F9: ='Efs OG'!CW84 -> 4.9712842 | G9: ='Efs OG'!CX84 -> 5.5084033 | H9: ='Efs OG'!CY84 -> 5.8675784 | I9: ='Efs OG'!CZ84 -> 5.4374108 | ... BJ9: ='Efs OG'!FA84 -> 0.040826053
A10: RL | B10: ='Efs Real'!L57 -> 1.0218305 | C10: ='Efs Real'!M57 -> 1.1200474 | D10: ='Efs Real'!N57 -> 1.5228594 | E10: ='Efs Real'!O57 -> 3.142638 | F10: ='Efs Real'!P57 -> 3.2542372 | G10: ='Efs Real'!Q57 -> 4.3216202 | H10: ='Efs Real'!R57 -> 4.0454956 | I10: ='Efs Real'!S57 -> 5.2496795 | ... P10: ='Efs Real'!Z57 -> 14.334917
A11: MAX | B11: 6 | C11: 6 | D11: 6 | E11: 6 | F11: 6 | G11: 6 | H11: 6 | I11: 6 | J11: 5 | K11: 5 | L11: 5 | M11: 5 | N11: 5 | O11: 5 | P11: 5 | Q11: 5 | R11: 5 | S11: 5 | T11: 5 | U11: 5 | V11: 5 | W11: 5 | X11: 5 | Y11: 5 | Z11: 5 | AA11: 5 | AB11: 5 | AC11: 5 | AD11: 5 | AE11: 5 | AF11: 5 | AG11: 5 | AH11: 5 | AI11: 5 | AJ11: 5 | AK11: 5 | AL11: 5 | AM11: 5 | AN11: 5 | AO11: 5 | AP11: 5 | AQ11: 5 | AR11: 5 | AS11: 5 | AT11: 5 | AU11: 5 | AV11: 5 | AW11: 5 | AX11: 5 | AY11: 5 | AZ11: 5 | BA11: 5 | BB11: 5 | BC11: 5 | BD11: 5 | BE11: 5 | BF11: 5 | BG11: 5 | BH11: 5 | BI11: 5 | BJ11: 5
A13: =IFERROR(__xludf.DUMMYFUNCTION("IMPORTRANGE(""https://docs.google.com/spreadsheets/d/1RNG9c9ku9IgXbqzh4Ng5a6f84xmyVPd-/edit?usp=sharing&ouid=116612639875179195240&rtpof=true&sd=true"",""Efs Real!B1"")"),"#REF!") -> #REF! | B13: Indice de apalancamiento ajustado
A14: =IFERROR(__xludf.DUMMYFUNCTION("IMPORTRANGE(""https://docs.google.com/spreadsheets/d/1RNG9c9ku9IgXbqzh4Ng5a6f84xmyVPd-/edit?gid=1965519997#gid=1965519997"",""Efs Real!B:B"")"),"#REF!") -> #REF! | B14: 45657 | C14: =EOMONTH(B14,1) -> 45688 | D14: =EOMONTH(C14,1) -> 45716 | E14: =EOMONTH(D14,1) -> 45747 | F14: =EOMONTH(E14,1) -> 45777 | G14: =EOMONTH(F14,1) -> 45808 | H14: =EOMONTH(G14,1) -> 45838 | I14: =EOMONTH(H14,1) -> 45869 | J14: =EOMONTH(I14,1) -> 45900 | ... BJ14: =EOMONTH(BI14,1) -> 47483
A15: OG | B15: ='Efs OG'!CS85 -> 0.47790809 | C15: ='Efs OG'!CT85 -> 0.47263307 | D15: ='Efs OG'!CU85 -> 0.69852675 | E15: ='Efs OG'!CV85 -> 0.77055709 | F15: ='Efs OG'!CW85 -> 0.85295858 | G15: ='Efs OG'!CX85 -> 0.87179625 | H15: ='Efs OG'!CY85 -> 0.8861586 | I15: ='Efs OG'!CZ85 -> 0.88527086 | ... BJ15: ='Efs OG'!FA85 -> 0.049411608
A16: RL | B16: ='Efs Real'!L58 -> 0.54297135 | C16: ='Efs Real'!M58 -> 0.58188453 | D16: ='Efs Real'!N58 -> 0.64550829 | E16: ='Efs Real'!O58 -> 0.79824949 | F16: ='Efs Real'!P58 -> 0.82088828 | G16: ='Efs Real'!Q58 -> 0.91499578 | H16: ='Efs Real'!R58 -> 0.86940431 | I16: ='Efs Real'!S58 -> 0.87028633 | ... P16: ='Efs Real'!Z58 -> 1.0810481
A17: MAX | B17: 0.9 | C17: 0.9 | D17: 0.9 | E17: 0.9 | F17: 0.9 | G17: 0.9 | H17: 0.9 | I17: 0.9 | J17: 0.85 | K17: 0.85 | L17: 0.85 | M17: 0.85 | N17: 0.85 | O17: 0.85 | P17: 0.85 | Q17: 0.85 | R17: 0.85 | S17: 0.85 | T17: 0.85 | U17: 0.85 | V17: 0.85 | W17: 0.85 | X17: 0.85 | Y17: 0.85 | Z17: 0.85 | AA17: 0.85 | AB17: 0.85 | AC17: 0.85 | AD17: 0.85 | AE17: 0.85 | AF17: 0.85 | AG17: 0.85 | AH17: 0.85 | AI17: 0.85 | AJ17: 0.85 | AK17: 0.85 | AL17: 0.85 | AM17: 0.85 | AN17: 0.85 | AO17: 0.85 | AP17: 0.85 | AQ17: 0.85 | AR17: 0.85 | AS17: 0.85 | AT17: 0.85 | AU17: 0.85 | AV17: 0.85 | AW17: 0.85 | AX17: 0.85 | AY17: 0.85 | AZ17: 0.85 | BA17: 0.85 | BB17: 0.85 | BC17: 0.85 | BD17: 0.85 | BE17: 0.85 | BF17: 0.85 | BG17: 0.85 | BH17: 0.85 | BI17: 0.85 | BJ17: 0.85
B19: Indice de capitalizacion
B20: 45657 | C20: =EOMONTH(B20,1) -> 45688 | D20: =EOMONTH(C20,1) -> 45716 | E20: =EOMONTH(D20,1) -> 45747 | F20: =EOMONTH(E20,1) -> 45777 | G20: =EOMONTH(F20,1) -> 45808 | H20: =EOMONTH(G20,1) -> 45838 | I20: =EOMONTH(H20,1) -> 45869 | J20: =EOMONTH(I20,1) -> 45900 | ... BJ20: =EOMONTH(BI20,1) -> 47483
A21: OG | B21: ='Efs OG'!CS83 -> 0.56988345 | C21: ='Efs OG'!CT83 -> 0.56780842 | D21: ='Efs OG'!CU83 -> 0.32915346 | E21: ='Efs OG'!CV83 -> 0.2522785 | F21: ='Efs OG'!CW83 -> 0.16890552 | G21: ='Efs OG'!CX83 -> 0.15607544 | H21: ='Efs OG'!CY83 -> 0.14913754 | I21: ='Efs OG'!CZ83 -> 0.16072783 | ... BJ21: ='Efs OG'!FA83 -> 1.0277649
A22: RL | B22: ='Efs Real'!L60 -> 0.4946013 | C22: ='Efs Real'!M60 -> 0.47168758 | D22: ='Efs Real'!N60 -> 0.39637564 | E22: ='Efs Real'!O60 -> 0.24139208 | F22: ='Efs Real'!P60 -> 0.23505976 | G22: ='Efs Real'!Q60 -> 0.1879127 | H22: ='Efs Real'!R60 -> 0.19819363 | I22: ='Efs Real'!S60 -> 0.16000821 | ... P22: ='Efs Real'!Z60 -> 0.065212493
A23: MIN | B23: 0.13 | C23: 0.13 | D23: 0.13 | E23: 0.13 | F23: 0.13 | G23: 0.13 | H23: 0.13 | I23: 0.13 | J23: 0.15 | K23: 0.15 | L23: 0.15 | M23: 0.15 | N23: 0.15 | O23: 0.15 | P23: 0.15 | Q23: 0.15 | R23: 0.15 | S23: 0.15 | T23: 0.15 | U23: 0.15 | V23: 0.15 | W23: 0.15 | X23: 0.15 | Y23: 0.15 | Z23: 0.15 | AA23: 0.15 | AB23: 0.15 | AC23: 0.15 | AD23: 0.15 | AE23: 0.15 | AF23: 0.15 | AG23: 0.15 | AH23: 0.15 | AI23: 0.15 | AJ23: 0.15 | AK23: 0.15 | AL23: 0.15 | AM23: 0.15 | AN23: 0.15 | AO23: 0.15 | AP23: 0.15 | AQ23: 0.15 | AR23: 0.15 | AS23: 0.15 | AT23: 0.15 | AU23: 0.15 | AV23: 0.15 | AW23: 0.15 | AX23: 0.15 | AY23: 0.15 | AZ23: 0.15 | BA23: 0.15 | BB23: 0.15 | BC23: 0.15 | BD23: 0.15 | BE23: 0.15 | BF23: 0.15 | BG23: 0.15 | BH23: 0.15 | BI23: 0.15 | BJ23: 0.15
B25: Indice de cartera atrasada
B26: 45657 | C26: =EOMONTH(B26,1) -> 45688 | D26: =EOMONTH(C26,1) -> 45716 | E26: =EOMONTH(D26,1) -> 45747 | F26: =EOMONTH(E26,1) -> 45777 | G26: =EOMONTH(F26,1) -> 45808 | H26: =EOMONTH(G26,1) -> 45838 | I26: =EOMONTH(H26,1) -> 45869 | J26: =EOMONTH(I26,1) -> 45900 | ... BJ26: =EOMONTH(BI26,1) -> 47483
A27: RL | B27: ='Efs Real'!L79 -> 0.034638809 | D27: ='Efs Real'!N79 -> 0.1212076 | E27: ='Efs Real'!O79 -> 0.13826239 | F27: ='Efs Real'!P79 -> 0.078829252 | G27: ='Efs Real'!Q79 -> 0.047487779 | H27: ='Efs Real'!R79 -> 0.1025311 | I27: ='Efs Real'!S79 -> 0.092024709 | J27: ='Efs Real'!T79 -> 0.058130551 | K27: ='Efs Real'!U79 -> 0.1458566 | ... P27: ='Efs Real'!Z79 -> 0.034578491
A28: MAX | B28: 0.11 | C28: 0.11 | D28: 0.11 | E28: 0.11 | F28: 0.11 | G28: 0.11 | H28: 0.11 | I28: 0.11 | J28: 0.11 | K28: 0.11 | L28: 0.11 | M28: 0.11 | N28: 0.11 | O28: 0.11 | P28: 0.11 | Q28: 0.11 | R28: 0.11 | S28: 0.11 | T28: 0.11 | U28: 0.11 | V28: 0.11 | W28: 0.11 | X28: 0.11 | Y28: 0.11 | Z28: 0.11 | AA28: 0.11 | AB28: 0.11 | AC28: 0.11 | AD28: 0.11 | AE28: 0.11 | AF28: 0.11 | AG28: 0.11 | AH28: 0.11 | AI28: 0.11 | AJ28: 0.11 | AK28: 0.11 | AL28: 0.11 | AM28: 0.11 | AN28: 0.11 | AO28: 0.11 | AP28: 0.11 | AQ28: 0.11 | AR28: 0.11 | AS28: 0.11 | AT28: 0.11 | AU28: 0.11 | AV28: 0.11 | AW28: 0.11 | AX28: 0.11 | AY28: 0.11 | AZ28: 0.11 | BA28: 0.11 | BB28: 0.11 | BC28: 0.11 | BD28: 0.11 | BE28: 0.11 | BF28: 0.11 | BG28: 0.11 | BH28: 0.11 | BI28: 0.11 | BJ28: 0.11
B30: Indice de cartera vencida
B31: 45657 | C31: =EOMONTH(B31,1) -> 45688 | D31: =EOMONTH(C31,1) -> 45716 | E31: =EOMONTH(D31,1) -> 45747 | F31: =EOMONTH(E31,1) -> 45777 | G31: =EOMONTH(F31,1) -> 45808 | H31: =EOMONTH(G31,1) -> 45838 | I31: =EOMONTH(H31,1) -> 45869 | J31: =EOMONTH(I31,1) -> 45900 | ... BJ31: =EOMONTH(BI31,1) -> 47483
A32: RL | B32: ='Efs Real'!L78 -> 0.093519918 | D32: ='Efs Real'!N78 -> 0.10098074 | E32: ='Efs Real'!O78 -> 0.11312762 | F32: ='Efs Real'!P78 -> 0.098726512 | G32: ='Efs Real'!Q78 -> 0.12932795 | H32: ='Efs Real'!R78 -> 0.13336209 | I32: ='Efs Real'!S78 -> 0.14904247 | J32: ='Efs Real'!T78 -> 0.15850606 | K32: ='Efs Real'!U78 -> 0.1717627 | ... P32: ='Efs Real'!Z78 -> 0.16224649
A33: MAX | B33: 0.14 | C33: 0.14 | D33: 0.14 | E33: 0.14 | F33: 0.14 | G33: 0.14 | H33: 0.14 | I33: 0.14 | J33: 0.14 | K33: 0.14 | L33: 0.14 | M33: 0.14 | N33: 0.14 | O33: 0.14 | P33: 0.14 | Q33: 0.14 | R33: 0.14 | S33: 0.14 | T33: 0.14 | U33: 0.14 | V33: 0.14 | W33: 0.14 | X33: 0.14 | Y33: 0.14 | Z33: 0.14 | AA33: 0.14 | AB33: 0.14 | AC33: 0.14 | AD33: 0.14 | AE33: 0.14 | AF33: 0.14 | AG33: 0.14 | AH33: 0.14 | AI33: 0.14 | AJ33: 0.14 | AK33: 0.14 | AL33: 0.14 | AM33: 0.14 | AN33: 0.14 | AO33: 0.14 | AP33: 0.14 | AQ33: 0.14 | AR33: 0.14 | AS33: 0.14 | AT33: 0.14 | AU33: 0.14 | AV33: 0.14 | AW33: 0.14 | AX33: 0.14 | AY33: 0.14 | AZ33: 0.14 | BA33: 0.14 | BB33: 0.14 | BC33: 0.14 | BD33: 0.14 | BE33: 0.14 | BF33: 0.14 | BG33: 0.14 | BH33: 0.14 | BI33: 0.14 | BJ33: 0.14
B35: Indice de rendimiento
B36: 45657 | C36: =EOMONTH(B36,1) -> 45688 | D36: =EOMONTH(C36,1) -> 45716 | E36: =EOMONTH(D36,1) -> 45747 | F36: =EOMONTH(E36,1) -> 45777 | G36: =EOMONTH(F36,1) -> 45808 | H36: =EOMONTH(G36,1) -> 45838 | I36: =EOMONTH(H36,1) -> 45869 | J36: =EOMONTH(I36,1) -> 45900 | ... BJ36: =EOMONTH(BI36,1) -> 47483
A37: OG | B37: ='Efs OG'!CS86 -> 0.32465717 | C37: ='Efs OG'!CT86 -> 0.29792175 | D37: ='Efs OG'!CU86 -> 0.32148484 | E37: ='Efs OG'!CV86 -> 0.31382425 | F37: ='Efs OG'!CW86 -> 0.30921444 | G37: ='Efs OG'!CX86 -> 0.29454936 | H37: ='Efs OG'!CY86 -> 0.29457407 | I37: ='Efs OG'!CZ86 -> 0.29565668 | ... BJ37: ='Efs OG'!FA86 -> 0.10914313
A38: RL | B38: ='Efs Real'!L61 -> 0.49128635 | D38: ='Efs Real'!N61 -> 0.46343952 | E38: ='Efs Real'!O61 -> 0.40301369 | F38: ='Efs Real'!P61 -> 0.34426087 | G38: ='Efs Real'!Q61 -> 0.33571751 | H38: ='Efs Real'!R61 -> 0.31486238 | I38: ='Efs Real'!S61 -> 0.28804192 | J38: ='Efs Real'!T61 -> 0.25722046 | K38: ='Efs Real'!U61 -> 0.25859564 | ... P38: ='Efs Real'!Z61 -> 0.16607488
A39: MIN | B39: 0.28 | C39: 0.28 | D39: 0.28 | E39: 0.28 | F39: 0.28 | G39: 0.28 | H39: 0.28 | I39: 0.28 | J39: 0.3 | K39: 0.3 | L39: 0.3 | M39: 0.3 | N39: 0.3 | O39: 0.3 | P39: 0.3 | Q39: 0.3 | R39: 0.3 | S39: 0.3 | T39: 0.3 | U39: 0.3 | V39: 0.3 | W39: 0.3 | X39: 0.3 | Y39: 0.3 | Z39: 0.3 | AA39: 0.3 | AB39: 0.3 | AC39: 0.3 | AD39: 0.3 | AE39: 0.3 | AF39: 0.3 | AG39: 0.3 | AH39: 0.3 | AI39: 0.3 | AJ39: 0.3 | AK39: 0.3 | AL39: 0.3 | AM39: 0.3 | AN39: 0.3 | AO39: 0.3 | AP39: 0.3 | AQ39: 0.3 | AR39: 0.3 | AS39: 0.3 | AT39: 0.3 | AU39: 0.3 | AV39: 0.3 | AW39: 0.3 | AX39: 0.3 | AY39: 0.3 | AZ39: 0.3 | BA39: 0.3 | BB39: 0.3 | BC39: 0.3 | BD39: 0.3 | BE39: 0.3 | BF39: 0.3 | BG39: 0.3 | BH39: 0.3 | BI39: 0.3 | BJ39: 0.3
B41: Indice rentabilidad
B42: 45657 | C42: =EOMONTH(B42,1) -> 45688 | D42: =EOMONTH(C42,1) -> 45716 | E42: =EOMONTH(D42,1) -> 45747 | F42: =EOMONTH(E42,1) -> 45777 | G42: =EOMONTH(F42,1) -> 45808 | H42: =EOMONTH(G42,1) -> 45838 | I42: =EOMONTH(H42,1) -> 45869 | J42: =EOMONTH(I42,1) -> 45900 | ... BJ42: =EOMONTH(BI42,1) -> 47483
A43: OG | B43: ='Efs OG'!CS87 -> 0.022206958 | C43: ='Efs OG'!CT87 -> -0.0044084217 | D43: ='Efs OG'!CU87 -> 0.00095752086 | E43: ='Efs OG'!CV87 -> 0.0081371964 | F43: ='Efs OG'!CW87 -> 0.036637043 | G43: ='Efs OG'!CX87 -> 0.053373452 | H43: ='Efs OG'!CY87 -> 0.06690704 | I43: ='Efs OG'!CZ87 -> 0.067598391 | ... BJ43: ='Efs OG'!FA87 -> 0.026149662
A44: RL | B44: ='Efs Real'!L62 -> -0.25730637 | D44: ='Efs Real'!N62 -> -0.25698136 | E44: ='Efs Real'!O62 -> -0.23983151 | F44: ='Efs Real'!P62 -> -0.19809747 | G44: ='Efs Real'!Q62 -> -0.19683796 | H44: ='Efs Real'!R62 -> -0.17527368 | I44: ='Efs Real'!S62 -> -0.14711211 | J44: ='Efs Real'!T62 -> -0.11570119 | K44: ='Efs Real'!U62 -> -0.10873788 | ... P44: ='Efs Real'!Z62 -> -0.013552794
A45: MIN | B45: -0.02 | C45: -0.02 | D45: -0.02 | E45: -0.02 | F45: -0.02 | G45: -0.02 | H45: -0.02 | I45: -0.02 | J45: 0 | K45: 0 | L45: 0 | M45: 0 | N45: 0 | O45: 0 | P45: 0 | Q45: 0 | R45: 0 | S45: 0 | T45: 0 | U45: 0 | V45: 0 | W45: 0 | X45: 0 | Y45: 0 | Z45: 0 | AA45: 0 | AB45: 0 | AC45: 0 | AD45: 0 | AE45: 0 | AF45: 0 | AG45: 0 | AH45: 0 | AI45: 0 | AJ45: 0 | AK45: 0 | AL45: 0 | AM45: 0 | AN45: 0 | AO45: 0 | AP45: 0 | AQ45: 0 | AR45: 0 | AS45: 0 | AT45: 0 | AU45: 0 | AV45: 0 | AW45: 0 | AX45: 0 | AY45: 0 | AZ45: 0 | BA45: 0 | BB45: 0 | BC45: 0 | BD45: 0 | BE45: 0 | BF45: 0 | BG45: 0 | BH45: 0 | BI45: 0 | BJ45: 0
B48: 45657 | C48: =EOMONTH(B48,1) -> 45688 | D48: =EOMONTH(C48,1) -> 45716 | E48: =EOMONTH(D48,1) -> 45747 | F48: =EOMONTH(E48,1) -> 45777 | G48: =EOMONTH(F48,1) -> 45808 | H48: =EOMONTH(G48,1) -> 45838 | I48: =EOMONTH(H48,1) -> 45869 | J48: =EOMONTH(I48,1) -> 45900 | ... BJ48: =EOMONTH(BI48,1) -> 47483
A49: Aforo mínimo | B49: =IF(B4>7.5%, 1.5, 1.35) -> 1.35 | C49: =IF(C4>7.5%, 1.5, 1.35) -> 1.35 | D49: =IF(D4>7.5%, 1.5, 1.35) -> 1.35 | E49: =IF(E4>7.5%, 1.5, 1.35) -> 1.35 | F49: =IF(F4>7.5%, 1.5, 1.35) -> 1.35 | G49: =IF(G4>7.5%, 1.5, 1.35) -> 1.35 | H49: =IF(H4>7.5%, 1.5, 1.35) -> 1.35 | I49: =IF(I4>7.5%, 1.5, 1.35) -> 1.5 | J49: =IF(J4>7.5%, 1.5, 1.35) -> 1.5 | K49: =IF(J4>7.5%, 1.5, 1.35) -> 1.5 | L49: =IF(L4>7.5%, 1.5, 1.35) -> 1.5 | M49: =IF(M4>7.5%, 1.5, 1.35) -> 1.5 | N49: =IF(N4>7.5%, 1.5, 1.35) -> 1.5 | O49: =IF(O4>7.5%, 1.5, 1.35) -> 1.35 | P49: =IF(P4>7.5%, 1.5, 1.35) -> 1.35 | Q49: =IF(Q4>7.5%, 1.5, 1.35) -> 1.35 | R49: =IF(R4>7.5%, 1.5, 1.35) -> 1.35 | S49: =IF(S4>7.5%, 1.5, 1.35) -> 1.35 | ... BJ49: =IF(BJ4>7.5%, 1.5, 1.35) -> 1.35
A50: Saldo Insoluto | F50: 30000000 | H50: 43000000 | I50: 46000000 | J50: 52000000 | K50: 52000000
A51: Monto cedido | E51: 30148888 | F51: 40824371 | H51: 57893037 | I51: 69131449 | J51: 76881537 | K51: 75229006
A52: Aforo cedido | E52: 1.43 | F52: =F51/F50 -> 1.3608124 | H52: 1.3543 | I52: =I51/I50 -> 1.5028576 | J52: =J51/J50 -> 1.4784911 | K52: =K51/K50 -> 1.4467117 | M52: 1.4324 | N52: 1.4256

Sheet Efs Real
A1: Estado de resultados | B1: 44713 | C1: 44805 | D1: 44896 | E1: 44986 | F1: 45078 | G1: 45170 | H1: 45261 | I1: 45352 | J1: 45444 | K1: 45536 | L1: 45627 | M1: 45658 | N1: 45689 | O1: 45717 | P1: 45748 | Q1: 45778 | R1: 45809 | S1: 45839 | T1: 45870 | U1: 45901 | V1: 45931 | W1: 45962 | X1: 45992 | Y1: 46023 | Z1: 46054 | AA1: feb-26 restado
A2: Comisiones cobradas | B2: 3031000 | C2: 5147000 | D2: 7230000 | E2: 2199000 | F2: 2974000 | G2: 4870000 | H2: 7076000 | I2: 2519000 | J2: 5696000 | K2: 8874000 | L2: 12252000 | M2: 998000 | N2: =1957000-M2 -> 959000 | O2: =3385000-SUM(M2:N2) -> 1428000 | P2: 1908286 | Q2: 1343719.5 | R2: =8202000-SUM($M2:Q2) -> 1564994.5 | S2: 1214533.8 | T2: 1552749 | U2: =12705000-SUM($M2:T2) -> 1735717.2 | V2: 2341515.2 | W2: 1066373.4 | X2: 1580714.3 | Y2: 1053000 | Z2: 2144000 | AA2: =Z2-Y2 -> 1091000
A3: Comisiones pagadas | B3: -112000 | C3: -247000 | D3: -322000 | E3: -111000 | F3: -194000 | G3: -346000 | H3: -515000 | I3: -612000 | J3: -1574000 | K3: -2635000 | L3: -3675000 | M3: -415000 | N3: =-725000-M3 -> -310000 | O3: =-1056000-SUM(M3:N3) -> -331000 | P3: -195731 | Q3: -254716.28 | R3: =-1627000-SUM(M3:Q3) -> -120552.72 | S3: -245747.17 | T3: -109983.18 | U3: =-(SUM($M3:T3)+2407000) -> -424269.65 | V3: -239566.18 | W3: -96599.85 | X3: -181499.01 | Y3: -208000 | Z3: -388000 | AA3: =Z3-Y3 -> -180000
A4: Pagadas vs Cobradas | B4: =-B3/B2 -> 0.036951501 | C4: =-C3/C2 -> 0.04798912 | D4: =-D3/D2 -> 0.044536653 | E4: =-E3/E2 -> 0.05047749 | F4: =-F3/F2 -> 0.065232011 | G4: =-G3/G2 -> 0.071047228 | H4: =-H3/H2 -> 0.072781232 | I4: =-I3/I2 -> 0.24295355 | ... Z4: =-Z3/Z2 -> 0.18097015 | AA4: =Z4-Y4 -> -0.016560715
A5: Resultado por Servicios | B5: 2919000 | C5: 4900000 | D5: 6908000 | E5: 2088000 | F5: 2780000 | G5: 4524000 | H5: 6561000 | I5: 1907000 | J5: 4122000 | K5: =SUM(K2:K3) -> 6239000 | L5: =SUM(L2:L3) -> 8577000 | M5: =SUM(M2:M3) -> 583000 | N5: =SUM(N2:N3) -> 649000 | O5: =SUM(O2:O3) -> 1097000 | P5: =SUM(P2:P3) -> 1712555 | Q5: =SUM(Q2:Q3) -> 1089003.2 | R5: =SUM(R2:R3) -> 1444441.8 | ... Z5: =SUM(Z2:Z3) -> 1756000 | AA5: =Z5-Y5 -> 911000
A6: Ingresos por intereses | B6: 357000 | C6: 656000 | D6: 880000 | E6: 262000 | F6: 699000 | G6: 874000 | H6: 1256000 | I6: 386000 | J6: 761000 | K6: 1093000 | L6: 1569000 | M6: 286000 | N6: =731000-M6 -> 445000 | O6: =1121000-SUM(M6:N6) -> 390000 | P6: 566720 | Q6: 733525.58 | R6: =3124000-SUM(M6:Q6) -> 702754.42 | S6: 806638.8 | T6: 855943.36 | U6: =5540000-SUM($M6:T6) -> 753417.84 | V6: 1288378.6 | W6: 865868.25 | X6: 1031707.3 | Y6: 713000 | Z6: 1437000 | AA6: =Z6-Y6 -> 724000
A7: Resultado por valuación a valor razonable | B7: 1000 | C7: 231000 | D7: 263000 | E7: 19000 | F7: 538000 | G7: 1252000 | H7: 1282000 | I7: 1000 | J7: 1000 | K7: 1000 | L7: 1000 | M7: 0 | N7: =0-M7 -> 0 | O7: 0 | P7: 0 | Q7: -724598.78 | R7: =-1706000-SUM(M7:Q7) -> -981401.22 | S7: 0 | T7: -990373.36 | U7: =SUM($M7:T7)+2696000 -> -373.36 | V7: 0 | W7: -476229.42 | X7: 0 | Y7: 0 | Z7: 0 | AA7: =Z7-Y7 -> 0
A8: Gastos por Intereses | B8: -144000 | C8: -245000 | D8: -245000 | E8: 0 | F8: 0 | G8: 0 | H8: 0 | I8: 0 | J8: 0 | K8: 0 | L8: -238000 | M8: 0 | N8: =-188000-M8 -> -188000 | O8: =-305000-SUM(M8:N8) -> -117000 | P8: 0 | Q8: -898013.89 | R8: =-1867000-SUM(M8:Q8) -> -663986.11 | S8: -844486.11 | T8: -917944.44 | U8: =-(SUM($M8:T8)+4517000) -> -887569.45 | V8: -917944.45 | W8: -858722.21 | X8: -962823.51 | Y8: -943000 | Z8: -1779000 | AA8: =Z8-Y8 -> -836000
A9: Margen Financiero por Intermediación | B9: 3133000 | C9: 5542000 | D9: 7806000 | E9: 2369000 | F9: 4017000 | G9: 6650000 | H9: 9099000 | I9: 2294000 | J9: 4884000 | K9: 7333000 | L9: =SUM(L6:L8)+L5 -> 9909000 | M9: =SUM(M6:M8)+M5 -> 869000 | N9: =SUM(N6:N8)+N5 -> 906000 | O9: =SUM(O6:O8)+O5 -> 1370000 | P9: =SUM(P6:P8)+P5 -> 2279275 | Q9: =SUM(Q6:Q8)+Q5 -> 199916.1 | R9: =R5+SUM(R6:R8) -> 501808.9 | S9: =S5+SUM(S6:S8) -> 930939.31 | T9: =T5+SUM(T6:T8) -> 390391.41 | U9: =U5+SUM(U6:U8) -> 1176922.6 | V9: =V5+SUM(V6:V8) -> 2472383.1 | W9: =W5+SUM(W6:W8) -> 500690.15 | X9: =X5+SUM(X6:X8) -> 1468099 | Y9: =Y5+SUM(Y6:Y8) -> 615000 | Z9: =Z5+Z6+Z8 -> 1414000 | AA9: =Z9-Y9 -> 799000
A10: Otros ingresos (egresos) de la operación | B10: 1886000 | C10: 1882000 | D10: 1597000 | E10: -401000 | F10: -512000 | G10: -565000 | H10: -602000 | I10: 67000 | J10: 65000 | K10: 171000 | L10: 144000 | M10: -4000 | N10: =-47000-M10 -> -43000 | O10: =-91000-SUM(M10:N10) -> -44000 | P10: -27793 | Q10: -155119.55 | R10: =-444000-SUM(M10:Q10) -> -170087.45 | S10: -159333.15 | T10: -258050.5 | U10: =-(SUM($M10:T10)+1098000) -> -236616.35 | V10: -462793.95 | W10: -466796.14 | X10: -156531.81 | Y10: -38000 | Z10: -84000 | AA10: =Z10-Y10 -> -46000
A11: Gastos de Administración y Promoción | B11: -4616000 | C11: -7689000 | D11: -13731000 | E11: -3446000 | F11: -7176000 | G11: -11329000 | H11: -15660000 | I11: -4272000 | J11: -8109000 | K11: -12211000 | L11: -16138000 | M11: -1622000 | N11: =-2677000-M11 -> -1055000 | O11: =-4358000-SUM(M11:N11) -> -1681000 | P11: -1590408 | Q11: -1955019.4 | R11: =-9500000-SUM(M11:Q11) -> -1596572.6 | S11: -1598596.9 | T11: -1622859 | U11: =-(SUM($M11:T11)+13964000) -> -1242544 | V11: -1908771.3 | W11: -1615578.5 | X11: -1791374.2 | Y11: -2031000 | Z11: -3703000 | AA11: =Z11-Y11 -> -1672000
A12: Impuestos a la utilidad y diferido | B12: 434000 | C12: 378000 | D12: 449000 | E12: 0 | F12: -154000 | G12: -174000 | H12: -332000 | I12: 0 | J12: 0 | K12: 0 | L12: 0 | M12: 0 | N12: =0-M12 -> 0 | O12: 0 | P12: 0 | Q12: 0 | R12: =0-SUM(M12:Q12) -> 0 | S12: =0-SUM(N12:R12) -> 0 | T12: =0-SUM(O12:S12) -> 0 | U12: =SUM($M12:T12)+0 -> 0 | V12: 0 | Y12: 0 | Z12: 0 | AA12: =Z12-Y12 -> 0
A13: Resultado Neto | B13: 837000 | C13: 113000 | D13: -3879000 | E13: -1478000 | F13: -3825000 | G13: -5418000 | H13: -7495000 | I13: -1911000 | J13: -3160000 | K13: -4707000 | L13: =SUM(L10:L12)+L9 -> -6085000 | M13: =SUM(M10:M12)+M9 -> -757000 | N13: =SUM(N10:N12)+N9 -> -192000 | O13: =SUM(O10:O12)+O9 -> -355000 | P13: =SUM(P10:P12)+P9 -> 661074 | Q13: =SUM(Q10:Q12)+Q9 -> -1910222.9 | R13: =SUM(R10:R12)+R9 -> -1264851.1 | S13: =SUM(S10:S12)+S9 -> -826990.79 | ... Y13: =SUM(Y10:Y12)+Y9 -> -1454000 | Z13: =Z9+Z10+Z11 -> -2373000 | AA13: =Z13-Y13 -> -919000
B14: 6 | C14: 9 | D14: 12 | E14: 3 | F14: 6 | G14: 9 | H14: 12 | I14: 3 | J14: 6 | K14: 9 | L14: 12 | M14: 1 | N14: 2 | V14: | | W14: | | X14: | | Y14: |
A15: Cuentas Bajo Administración | B15: 44713 | C15: 44805 | D15: 44896 | E15: 44986 | F15: 45078 | G15: 45170 | H15: 45261 | I15: 45352 | J15: 45444 | K15: 45536 | L15: 45627 | M15: 45658 | N15: 45689 | O15: 45717 | P15: 45748 | Q15: 45778 | R15: 45809 | S15: 45839 | T15: 45870 | U15: 45901 | V15: 45931 | W15: 45931 | X15: 45992 | Y15: 46023 | Z15: 46054
A16: Deuda cuentas corrientes | B16: 2339000 | C16: 3307000 | D16: 5406000 | E16: 4330000 | F16: 4512000 | G16: 4995000 | H16: 6718000 | I16: 5575000 | J16: 5215000 | K16: 6889000 | L16: 11052000 | M16: 10315000 | N16: 10349000 | O16: 10201000 | P16: 6418014 | R16: 3424000 | U16: 4130000 | Y16: 5222000 | Z16: 7042000
A17: Depósitos de inversionistas | B17: 4458000 | C17: 5356000 | D17: 4906000 | E17: 7587000 | F17: 7267000 | G17: 6142000 | H17: 6825000 | I17: 8451000 | J17: 9034000 | K17: 8643000 | L17: 7734000 | M17: 7538000 | N17: 7236000 | O17: 7543000 | P17: 10336837 | R17: 11544000 | U17: 7770000 | Y17: 7943000 | Z17: 10938000
A18: Otras cuentas corrientes | B18: 6524000 | C18: 8079000 | D18: 10063000 | E18: 11779000 | F18: 11608000 | G18: 10980000 | H18: 13791000 | I18: 13851000 | J18: 13566000 | K18: 15240000 | L18: 17276000 | M18: 13842000 | N18: 17655000 | O18: 18747000 | P18: 17709968 | R18: 0 | U18: 12210000 | Y18: 13241000 | Z18: 17906000
A19: Instrumentos financieros de clientes en administración | B19: 97373000 | C19: 100058000 | D19: 111072000 | E19: 116535000 | F19: 119344000 | G19: 130759000 | H19: 136571000 | I19: 152097000 | J19: 152920000 | K19: 160492000 | L19: 173957000 | M19: 175565000 | N19: 173917000 | O19: 184923000 | P19: 194537486 | R19: 202657000 | U19: 204013000 | Y19: 196293000 | Z19: 196245000
A20: Comisiones vs. Cartera | B20: =(B2/B14*12)/B19 -> 0.062255451 | C20: =(C2/C14*12)/C19 -> 0.068586886 | D20: =(D2/D14*12)/D19 -> 0.065092913 | E20: =(E2/E14*12)/E19 -> 0.07547947 | F20: =(F2/F14*12)/F19 -> 0.049839121 | G20: =(G2/G14*12)/G19 -> 0.049658787 | H20: =(H2/H14*12)/H19 -> 0.051811878 | I20: =(I2/I14*12)/I19 -> 0.066247198 | ... L20: =(L2/L14*12)/L19 -> 0.070431199 | M20: =(M2*12)/M19 -> 0.068214052 | N20: =(N2*12)/N19 -> 0.066169495 | O20: =(O2*12)/O19 -> 0.092665596 | P20: =(P2*12)/P19 -> 0.11771218 | Q20: =(Q2*12)/Q19 -> #DIV/0! | R20: =(R2*12)/R19 -> 0.09266857 | U20: =(U2*12)/U19 -> 0.1020945 | V20: =(V2*12)/V19 -> #DIV/0! | W20: =(W2*12)/W19 -> #DIV/0! | X20: =(X2*12)/X19 -> #DIV/0! | Y20: =(Y2*12)/Y19 -> 0.064373156 | Z20: =(Z2*12)/Z19 -> 0.13110143
A21: Colaterales recibidos en garanía por cuenta de solicitantes | B21: 117285000 | C21: 125400000 | D21: 134270000 | E21: 151502000 | F21: 166160000 | G21: 186115000 | H21: 203482000 | I21: 198647000 | J21: 208366000 | K21: 216152000 | L21: 231653000 | M21: 233750000 | N21: 242718000 | O21: 247111000 | P21: 253062289 | R21: 271081000 | U21: 270589000 | Y21: 252127000 | Z21: 252751000
A22: Total Operaciones de Administración | B22: 227979000 | C22: 242200000 | D22: 265717000 | E22: 291733000 | F22: 308891000 | G22: 338991000 | H22: 367387000 | I22: 378621000 | J22: 389101000 | K22: 407416000 | L22: =L21+L19+L18+L17+L16 -> 441672000 | M22: =M21+M19+M18+M17+M16 -> 441010000 | N22: =N21+N19+N18+N17+N16 -> 451875000 | O22: =O21+O19+O18+O17+O16 -> 468525000 | P22: =P21+P19+P18+P17+P16 -> 482064594 | Q22: =Q21+Q19+Q18+Q17+Q16 -> 0 | R22: =R21+R19+R18+R17+R16 -> 488706000 | U22: =U21+U19+U18+U17+U16 -> 498712000 | V22: =V21+V19+V18+V17+V16 -> 0 | W22: =W21+W19+W18+W17+W16 -> 0 | X22: =X21+X19+X18+X17+X16 -> 0 | Y22: =Y21+Y19+Y18+Y17+Y16 -> 474826000 | Z22: =Z21+Z19+Z18+Z17+Z16 -> 484882000
M23: 1 | N23: 2
A24: Balance General | B24: 44713 | C24: 44805 | D24: 44896 | E24: 44986 | F24: 45078 | G24: 45170 | H24: 45261 | I24: 45352 | J24: 45444 | K24: 45536 | L24: 45627 | M24: 45658 | N24: 45689 | O24: 45717 | P24: 45748 | Q24: 45778 | R24: 45809 | S24: 45839 | T24: 45870 | U24: 45901 | V24: 45931 | W24: 45931 | X24: 45992 | Y24: 46023 | Z24: 46054
A25: Efectivo y equivalentes de efectivo | B25: 544000 | C25: 6371000 | D25: 1962000 | E25: 3241000 | F25: 2397000 | G25: 3151000 | H25: 945000 | I25: 113000 | J25: 634000 | K25: 458000 | L25: 334000 | M25: 678000 | N25: 65000 | O25: 443000 | P25: 279981 | Q25: 1501430.3 | R25: 253000 | S25: 661157.8 | T25: 62726.5 | U25: 121000 | V25: 401123.31 | W25: 687768.41 | X25: 290091.8 | Y25: 160000 | Z25: 813000
A26: Inversiones en instrumentos financieros (cartera RG) | B26: 6209000 | C26: 6678000 | D26: 6905000 | E26: 6430000 | F26: 6187000 | G26: 1298000 | H26: 1996000 | I26: 1476000 | J26: 1516000 | K26: 6208000 | L26: 25517000 | M26: 24388000 | N26: 24356000 | O26: 38503000 | P26: 50875285 | Q26: 50875230 | R26: 61878000 | S26: 72564877 | T26: 72334955 | U26: 69199000 | V26: 77800817 | W26: 72500790 | X26: 64999893 | Y26: 63365000 | Z26: 61408000
A27: Estimación de pérdidas crediticias | B27: -1683000 | C27: -1495000 | D27: -1548000 | E27: -1550000 | F27: -1221000 | G27: -403000 | H27: -403000 | I27: -403000 | J27: -403000 | K27: -403000 | L27: -403000 | M27: -403000 | N27: -403000 | O27: -2503000 | P27: -2503265 | Q27: -3227863.7 | R27: -4209000 | S27: -4209174.6 | T27: -5199548 | U27: -5200000 | V27: -5199548 | W27: -5675777.4 | X27: -5675777.4 | Y27: -5676000 | Z27: -5676000
A28: Cuentas por cobrar, neto | B28: 325000 | C28: 1231000 | D28: 6980000 | E28: 7253000 | F28: 7160000 | G28: 11824000 | H28: 11779000 | I28: 11677000 | J28: 11821000 | K28: 11405000 | L28: 11266000 | M28: 11398000 | N28: 13552000 | O28: 12011000 | P28: 12321419 | Q28: 12473029 | R28: 11183000 | S28: 11623339 | T28: 12428384 | U28: 13152000 | V28: 13035761 | W28: 11717400 | X28: 12311004 | Y28: 12186000 | Z28: 12264000
A29: Pagos anticipados y otros activos, neto | B29: 1630000 | C29: 2000000 | D29: 2472000 | E29: 1696000 | F29: 1675000 | G29: 1529000 | H29: 1549000 | I29: 1511000 | J29: 1460000 | K29: 1419000 | L29: 1382000 | M29: 1617000 | N29: 1450000 | O29: 2747000 | P29: 4619536 | Q29: =2271537.47+3494711.12+1037057.22 -> 6803305.8 | R29: 7792000 | S29: 4781463.7 | T29: 5390587.6 | U29: 6322000 | V29: 7862889 | W29: 7908494.4 | X29: 10047810 | Y29: 11203000 | Z29: 12406000
A30: Propiedades, mobiliario y equipo, neto | B30: 132000 | C30: 114000 | D30: 96000 | E30: 109000 | F30: 180000 | G30: 174000 | H30: 207000 | I30: 208000 | J30: 210000 | K30: 208000 | L30: 238000 | M30: 235000 | N30: 232000 | O30: 243000 | P30: 242599 | Q30: 642052.93 | R30: 300000 | S30: 656383.1 | T30: 656383.1 | U30: 301000 | V30: 684494.31 | W30: 684494.31 | X30: 684494.31 | Y30: 452000 | Z30: 394000
A31: Depreciación acumulada | Q31: -354157.06 | R31: 0 | S31: -354947.44 | T31: -355342.63 | U31: 0 | V31: -356133.01 | W31: -356528.2 | X31: -356923.39 | Y31: 0
A32: Activo por impuestos a la utilidad diferidos, neto | B32: 505000 | C32: 449000 | D32: 520000 | E32: 521000 | F32: 366000 | G32: 346000 | H32: 268000 | I32: 346000 | J32: 346000 | K32: 346000 | L32: 346000 | M32: 346000 | N32: 346000 | O32: 1082000 | P32: 1082189 | Q32: 1082189.3 | R32: 1082000 | S32: 1082189.3 | T32: 1082189.3 | U32: 1082000 | V32: 1082189.3 | W32: 1082189.3 | X32: 1082189.3 | Y32: 1361000 | Z32: 1669000
A33: Total Activo | B33: =SUM(B25:B32) -> 7662000 | C33: =SUM(C25:C32) -> 15348000 | D33: =SUM(D25:D32) -> 17387000 | E33: =SUM(E25:E32) -> 17700000 | F33: =SUM(F25:F32) -> 16744000 | G33: =SUM(G25:G32) -> 17919000 | H33: =SUM(H25:H32) -> 16341000 | I33: =SUM(I25:I32) -> 14928000 | ... Z33: =SUM(Z25:Z32) -> 83278000
A35: Préstamos de corto plazo | B35: 1058000 | C35: 115000 | D35: 17000 | E35: 50000 | F35: 89000 | G35: 142000 | H35: 114000 | I35: 255000 | J35: 59000 | K35: 139000 | L35: 60000 | M35: 75000 | N35: 358000 | O35: 0 | P35: 86288 | Q35: 164643.18 | R35: 81000 | S35: 119104.48 | T35: 101245.29 | U35: 374000 | V35: 178760.11 | W35: 72353.39 | X35: 66838.97 | Y35: 378000 | Z35: 94000
A36: Préstamos de largo plazo | B36: 1477000 | C36: 10611000 | D36: 10405000 | E36: 9400000 | F36: 8803000 | G36: 8206000 | H36: 7609000 | I36: 7459000 | J36: 6862000 | K36: 11265000 | L36: 10465000 | M36: 10334000 | N36: 10465000 | O36: 24549000 | P36: 34468353 | Q36: 38468353 | R36: 47070000 | S36: 55574615 | T36: =55574614.97 -> 55574615 | U36: 55327000 | V36: 64675005 | W36: 59840978 | X36: 54586440 | Y36: 54268000 | Z36: 54268000
A37: Contribuciones por pagar | B37: 95000 | C37: 155000 | D37: 497000 | E37: 450000 | F37: 316000 | G37: 461000 | H37: 348000 | I37: 633000 | J37: 1021000 | K37: 1011000 | L37: 1552000 | M37: 1563000 | N37: 2074000 | O37: 2501000 | P37: 3168518 | Q37: 3433525.3 | R37: 2454000 | S37: 2876758.8 | T37: 3492117.8 | U37: 3121000 | V37: 3759750 | W37: 3441035.4 | X37: =4483008.93-X38 -> 4250057.4 | Y37: 4668000 | Z37: 5417000
A38: Acreedores diversas y otras cuentas por pagar | B38: 185000 | C38: 310000 | D38: 335000 | E38: 505000 | F38: 41000 | G38: 229000 | H38: 356000 | I38: 80000 | J38: 62000 | K38: 223000 | L38: 31000 | M38: 398000 | N38: 585000 | O38: 600000 | P38: 645113 | Q38: 669184.7 | R38: 296000 | S38: 352413.85 | T38: 463869.94 | U38: 501000 | V38: 582334.27 | W38: 673578.63 | X38: 232951.49 | Y38: 398000 | Z38: 508000
A39: Aportaciones para futuros aumentos de capital como pasivos | B39: 0 | C39: 0 | D39: 0 | E39: 0 | F39: 0 | G39: 0 | H39: 0 | I39: 0 | J39: 2250000 | K39: 0 | L39: 0 | M39: 0 | N39: 0 | O39: 0 | R39: 0 | S39: 0 | T39: 0 | U39: 0 | V39: 0 | W39: 0 | X39: 0 | Y39: 0
A40: Pasivo por impuestos a la utilidad | B40: 44000 | C40: 120000 | D40: 88000 | E40: 44000 | F40: 92000 | G40: 71000 | H40: 164000 | I40: 270000 | J40: 211000 | K40: 294000 | L40: 1094000 | M40: 1114000 | N40: 1485000 | O40: 1900000 | P40: 2355861 | Q40: 2720411.4 | R40: 2744000 | S40: 3021912.8 | T40: 3340183.9 | U40: 3268000 | V40: 3726144.4 | W40: 3808299.5 | X40: 4221362 | Y40: 4732000 | Z40: 5272000
A41: Pasivo por Beneficios a Empleados | B41: 0 | C41: 0 | D41: 0 | E41: 185000 | F41: 185000 | G41: 185000 | H41: 0 | I41: 232000 | J41: 368000 | K41: 506000 | L41: 653000 | M41: 707000 | N41: 755000 | O41: 1185000 | P41: 1038792 | Q41: 1094502.7 | R41: 1152000 | S41: 1207415.1 | T41: 1265752.7 | U41: 1158000 | V41: 1060969.9 | W41: 965640.63 | X41: 757993.75 | Y41: 792000 | Z41: 826000
A42: Total Pasivo | B42: 2859000 | C42: 11312000 | D42: 11342000 | E42: 10634000 | F42: 9525000 | G42: 9294000 | H42: 8591000 | I42: 8929000 | J42: 10833000 | K42: 13438000 | L42: =SUM(L35:L41) -> 13855000 | M42: =SUM(M35:M41) -> 14191000 | N42: =SUM(N35:N41) -> 15722000 | O42: =SUM(O35:O41) -> 30735000 | P42: =SUM(P35:P41) -> 41762925 | Q42: =SUM(Q35:Q41) -> 46550621 | R42: =SUM(R35:R41) -> 53797000 | S42: =SUM(S35:S41) -> 63152220 | ... Z42: =SUM(Z35:Z41) -> 66385000
A44: Capital Social | B44: 3564000 | C44: 3564000 | D44: 3564000 | E44: 3564000 | F44: 3564000 | G44: 3564000 | H44: 3564000 | I44: 3564000 | J44: 3564000 | K44: 3564000 | L44: 4277000 | M44: 4277000 | N44: 4277000 | O44: 4277000 | P44: 4276689 | Q44: 4276689 | R44: 4277000 | S44: 4276689 | T44: 4276689 | U44: 4277000 | V44: 51331429 | W44: 51331429 | X44: 4739996 | Y44: 4740000 | Z44: 4740000
A45: Aportaciones para futuros aumentos de capital | B45: 4568000 | C45: 4568000 | D45: 10568000 | E45: 13068000 | F45: 15568000 | G45: 18568000 | H45: 19768000 | I45: 19768000 | J45: 19768000 | K45: 22768000 | L45: 22768000 | M45: 22768000 | N45: 22768000 | O45: 22768000 | P45: 25267520 | Q45: 25267520 | R45: 27768000 | S45: 27767520 | T45: 27767520 | U45: 27768000 | V45: 0 | W45: 0 | X45: 14767520 | Y45: 14768000 | Z45: 14768000
A46: Prima en Venta de Acciones | B46: 0 | C46: 0 | D46: 0 | E46: 0 | F46: 0 | G46: 0 | H46: 0 | I46: 0 | J46: 0 | K46: 0 | L46: 19287000 | M46: 19287000 | N46: 19287000 | O46: 19287000 | P46: 19287220 | Q46: 19287220 | R46: 19287000 | S46: 19287220 | T46: 19287220 | U46: 19287000 | V46: 0 | W46: 0 | X46: 31823913 | Y46: 31824000 | Z46: 31824000
A47: Resultados acumulados | B47: -3329000 | C47: -4096000 | D47: -8087000 | E47: -9565000 | F47: -11912000 | G47: -13506000 | H47: -15582000 | I47: -17332000 | J47: -18581000 | K47: -20128000 | L47: -21507000 | M47: -22264000 | N47: -22456000 | O47: -24541000 | P47: -23034714 | Q47: -23034714 | R47: -26851000 | S47: -23034714 | T47: -23034714 | U47: -30104000 | V47: -30002799 | W47: -31584483 | X47: -32064290 | Y47: -33518000 | Z47: -34437000
A48: Utilidad o pérdida del ejercicio | Q48: -2552119.6 | S48: -4643647.2 | T48: -6134165.3 | U48: 0 | V48: 0 | W48: 0 | X48: 0 | Y48: 0
A49: Total participación no controlada | P49: -641897 | Q49: 0 | R49: 0 | S49: 0 | T49: 0 | U49: 0 | V49: 0 | W49: 0 | X49: 0 | Y49: 0
A50: Total Capital | B50: 4803000 | C50: 4036000 | D50: 6045000 | E50: 7067000 | F50: 7220000 | G50: 8626000 | H50: 7750000 | I50: 6000000 | J50: 4751000 | K50: 6204000 | L50: =SUM(L44:L47) -> 24825000 | M50: =SUM(M44:M47) -> 24068000 | N50: =SUM(N44:N47) -> 23876000 | O50: =SUM(O44:O47) -> 21791000 | P50: =SUM(P44:P49) -> 25154818 | Q50: =SUM(Q44:Q49) -> 23244595 | R50: =SUM(R44:R49) -> 24481000 | S50: =SUM(S44:S49) -> 23653068 | T50: =SUM(T44:T49) -> 22162550 | U50: =SUM(U44:U49) -> 21228000 | V50: =SUM(V44:V49) -> 21328630 | W50: =SUM(W44:W49) -> 19746946 | ... Z50: =SUM(Z44:Z49) -> 16895000
A52: Balance | B52: =B33-B42-B50 -> 0 | C52: =C33-C42-C50 -> 0 | D52: =D33-D42-D50 -> 0 | E52: =E33-E42-E50 -> -1000 | F52: =F33-F42-F50 -> -1000 | G52: =G33-G42-G50 -> -1000 | H52: =H33-H42-H50 -> 0 | I52: =I33-I42-I50 -> -1000 | ... Z52: =Z33-Z42-Z50 -> -2000
AB53: 42657563
A54: Activo Total | B54: =B33-B28 -> 7337000 | C54: =C33-C28 -> 14117000 | D54: =D33-D28 -> 10407000 | E54: =E33-E28 -> 10447000 | F54: =F33-F28 -> 9584000 | G54: =G33-G28 -> 6095000 | H54: =H33-H28 -> 4562000 | I54: =I33-I28 -> 3251000 | ... Z54: =Z33-Z28 -> 71014000 | AB54: =AB53-Y72 -> 24979964
A55: Capital Contable Ajustado | B55: =B50-B28 -> 4478000 | C55: =C50-C28 -> 2805000 | D55: =D50-D28 -> -935000 | E55: =E50-E28 -> -186000 | F55: =F50-F28 -> 60000 | G55: =G50-G28 -> -3198000 | H55: =H50-H28 -> -4029000 | I55: =I50-I28 -> -5677000 | ... Z55: =Z50-Z28 -> 4631000
A57: Índice de Apalancamiento (CNBV) | B57: =B42/B55 -> 0.63845467 | C57: =C42/C55 -> 4.0327986 | D57: =D42/D55 -> -12.130481 | E57: =E42/E55 -> -57.172043 | F57: =F42/F55 -> 158.75 | G57: =G42/G55 -> -2.9061914 | H57: =H42/H55 -> -2.1322909 | I57: =I42/I55 -> -1.5728378 | ... Z57: =Z42/Z55 -> 14.334917
A58: Índice de Apalancamiento Ajustado | B58: =B42/B26 -> 0.46046062 | C58: =C42/C26 -> 1.6939203 | D58: =D42/D26 -> 1.6425778 | E58: =E42/E26 -> 1.6538103 | F58: =F42/F26 -> 1.5395183 | G58: =G42/G26 -> 7.1602465 | H58: =H42/H26 -> 4.3041082 | I58: =I42/I26 -> 6.049458 | ... Z58: =Z42/Z26 -> 1.0810481
A59: Apalancamiento Oso | M59: =(M35+M36-M25)/(M26+M27) -> 0.4057119 | N59: =(N35+N36-N25)/(N26+N27) -> 0.44912955 | O59: =(O35+O36-O25)/(O26+O27) -> 0.66961111 | P59: =(P35+P36-P25)/(P26+P27) -> 0.70856375 | Q59: =(Q35+Q36-Q25)/(Q26+Q27) -> 0.77929945 | R59: =(R35+R36-R25)/(R26+R27) -> 0.81322721 | S59: =(S35+S36-S25)/(S26+S27) -> 0.80509102 | T59: =(T35+T36-T25)/(T26+T27) -> 0.82837264 | ... Z59: =(Z35+Z36-Z25)/(Z26+Z27) -> 0.9608304
A60: Índice de Capitalización | B60: =B55/B54 -> 0.6103312 | C60: =C55/C54 -> 0.19869661 | D60: =D55/D54 -> -0.089843375 | E60: =E55/E54 -> -0.017804154 | F60: =F55/F54 -> 0.0062604341 | G60: =G55/G54 -> -0.52469237 | H60: =H55/H54 -> -0.88316528 | I60: =I55/I54 -> -1.7462319 | ... Z60: =Z55/Z54 -> 0.065212493
A61: Índice de Rendimiento | L61: =(SUM(A2:L2)+SUM(A6:L6))/L73 -> 0.49128635 | M61: =(SUM(B2:M2)+SUM(B6:M6))/M73 -> 0.48811199 | N61: =(SUM(C2:N2)+SUM(C6:N6))/N73 -> 0.46343952 | O61: =(SUM(D2:O2)+SUM(D6:O6))/O73 -> 0.40301369 | P61: =(SUM(E2:P2)+SUM(E6:P6))/P73 -> 0.34426087 | Q61: =(SUM(F2:Q2)+SUM(F6:Q6))/Q73 -> 0.33571751 | R61: =(SUM(G2:R2)+SUM(G6:R6))/R73 -> 0.31486238 | S61: =(SUM(H2:S2)+SUM(H6:S6))/S73 -> 0.28804192 | ... Z61: =(SUM(O2:Z2)+SUM(O6:Z6))/Z73 -> 0.16607488
A62: Índice de Rentabilidad | L62: =(SUM(A13:L13))/L73 -> -0.25730637 | M62: =(SUM(B13:M13))/M73 -> -0.25621724 | N62: =(SUM(C13:N13))/N73 -> -0.25698136 | O62: =(SUM(D13:O13))/O73 -> -0.23983151 | P62: =(SUM(E13:P13))/P73 -> -0.19809747 | Q62: =(SUM(F13:Q13))/Q73 -> -0.19683796 | R62: =(SUM(G13:R13))/R73 -> -0.17527368 | S62: =(SUM(H13:S13))/S73 -> -0.14711211 | ... X62: =(SUM(M13:X13))/X73 -> -0.046250918 | Y62: > | Z62: =Z13/Z73 -> -0.013552794
A64: Tasa Activa | L64: =(((L6))/L26)+L20 -> 0.13191962 | M64: =(((M6)*12)/M26)+M20 -> 0.208939 | N64: =(((N6)*12)/N26)+N20 -> 0.28541732 | O64: =(((O6)*12)/O26)+O20 -> 0.21421457 | P64: =(((P6)*12)/P26)+P20 -> 0.25138495 | Q64: =(((Q6)*12)/Q26)+Q20 -> #DIV/0! | R64: =(((R6)*12)/R26)+R20 -> 0.22895373 | S64: =(((S6)*12)/S26)+S20 -> 0.13339326 | T64: =(((T6)*12)/T26)+T20 -> 0.14199664 | ... Z64: =(((Z6)*12)/Z26)+Z20 -> 0.41191175
A65: Tasa Pasiva | L65: =-((L8))/(L35+L36) -> 0.022612827 | M65: =-((M8)*12)/(M35+M36) -> 0 | N65: =-((N8)*12)/(N35+N36) -> 0.20844498 | O65: =-((O8)*12)/(O35+O36) -> 0.057191739 | P65: =-((P8)*12)/(P35+P36) -> 0 | Q65: =-((Q8)*12)/(Q35+Q36) -> 0.27893686 | R65: =-((R8)*12)/(R35+R36) -> 0.16898546 | S65: =-((S8)*12)/(S35+S36) -> 0.18195648 | T65: =-((T8)*12)/(T35+T36) -> 0.19784756 | U65: =-((U8)*12)/(U35+U36) -> 0.1912144 | V65: =-((V3)*12)/(V35+V36) -> 0.044327329 | W65: =-((W3)*12)/(W35+W36) -> 0.019347918 | X65: =-((X3)*12)/(X35+X36) -> 0.039851005 | Y65: =-((Y3)*12)/(Y35+Y36) -> 0.045675804 | Z65: =-((Z3)*12)/(Z35+Z36) -> 0.085648063
A67: Monto Originado 16 Meses | L67: 89555942 | N67: 93410014 | O67: 103972448 | P67: 108185067 | Q67: 115121760 | R67: 120654788 | S67: 126121513 | T67: 123607290 | U67: 119792326 | V67: 138785251 | W67: 134990514 | X67: 125321850 | Y67: 118738388 | Z67: 119489195
A68: Saldo Vencido 16 Meses | L68: 4634468.6 | N68: 3620615.2 | O68: 3950723.8 | P68: 2666354 | Q68: 8186639.6 | R68: 8930882.1 | S68: 12476128 | T68: 13829800 | U68: 15831567 | V68: 16170808 | W68: 14734138 | X68: 9542620.5 | Y68: 8046442.2 | Z68: 8046442.2
A69: IMOR 16 Meses | L69: =L68/L67 -> 0.051749426 | N69: =N68/N67 -> 0.038760461 | O69: =O68/O67 -> 0.037997795 | P69: =P68/P67 -> 0.02464623 | Q69: =Q68/Q67 -> 0.071112877 | R69: =R68/R67 -> 0.074020122 | S69: =S68/S67 -> 0.098921489 | T69: =T68/T67 -> 0.11188499 | U69: =U68/U67 -> 0.13215844 | ... Z69: =Z68/Z67 -> 0.067340333
A71: Saldo Insoluto | L71: 1.5867403e+08 | M71: 1.6282073e+08 | N71: 1.6696743e+08 | O71: 1.7969425e+08 | P71: 1.9132533e+08 | Q71: 1.9473994e+08 | R71: 2.0224946e+08 | S71: 2.0612057e+08 | T71: 2.0572996e+08 | U71: 2.0326457e+08 | V71: 2.0660767e+08 | W71: 2.0360786e+08 | X71: 1.9917319e+08 | Y71: 1.9489329e+08 | Z71: 1.9285419e+08
A72: Vencido +36 Meses | L72: 14845487 | M72: 15426273 | N72: 16007060 | O72: 15987657 | P72: 16048343 | Q72: 16145588 | R72: 16288856 | S72: 15769209 | T72: 15597865 | U72: 15751741 | V72: 14737138 | W72: 15489200 | X72: 17589326 | Y72: 17677599 | Z72: 17761137
A73: Valor del Portafolio | L73: =L71-L72 -> 1.4382854e+08 | M73: =M71-M72 -> 1.4739445e+08 | N73: =N71-N72 -> 1.5096037e+08 | O73: =O71-O72 -> 1.637066e+08 | P73: =P71-P72 -> 1.7527698e+08 | Q73: =Q71-Q72 -> 1.7859435e+08 | R73: =R71-R72 -> 1.8596061e+08 | S73: =S71-S72 -> 1.9035136e+08 | ... Z73: =Z71-Z72 -> 1.7509305e+08
A75: Vencido -36 Meses | L75: 13450834 | N75: 15244089 | O75: 18519737 | P75: 17304485 | Q75: 23097241 | R75: 24800095 | S75: 28370436 | T75: 30137089 | U75: 32207709 | V75: 32815648 | W75: 29712387 | X75: 29235458 | Y75: 29432300 | Z75: 28408233
A76: Atrasado - 36 meses | L76: 4982049.5 | N76: 18297544 | O76: 22634465 | P76: 13816953 | Q76: 8481049.2 | R76: 19066746 | S76: 17517029 | T76: 11052483 | U76: 27349983 | V76: 2776085 | W76: 18114125 | X76: 3787273.9 | Y76: 3655728.7 | Z76: 6054453.3
A78: Índice de Cartera Vencida | L78: =L75/L73 -> 0.093519918 | N78: =N75/N73 -> 0.10098074 | O78: =O75/O73 -> 0.11312762 | P78: =P75/P73 -> 0.098726512 | Q78: =Q75/Q73 -> 0.12932795 | R78: =R75/R73 -> 0.13336209 | S78: =S75/S73 -> 0.14904247 | T78: =T75/T73 -> 0.15850606 | U78: =U75/U73 -> 0.1717627 | ... Z78: =Z75/Z73 -> 0.16224649
A79: Índice de Cartera Atrasada | L79: =L76/L73 -> 0.034638809 | N79: =N76/N73 -> 0.1212076 | O79: =O76/O73 -> 0.13826239 | P79: =P76/P73 -> 0.078829252 | Q79: =Q76/Q73 -> 0.047487779 | R79: =R76/R73 -> 0.1025311 | S79: =S76/S73 -> 0.092024709 | T79: =T76/T73 -> 0.058130551 | U79: =U76/U73 -> 0.1458566 | ... Z79: =Z76/Z73 -> 0.034578491

Sheet Efs OG
B1: 42736 | C1: 42767 | D1: 42795 | E1: 42826 | F1: 42856 | G1: 42887 | H1: 42917 | I1: 42948 | J1: 42979 | K1: 43009 | L1: 43040 | M1: 43070 | N1: 43101 | O1: 43132 | P1: 43160 | Q1: 43191 | R1: 43221 | S1: 43252 | T1: 43282 | U1: 43313 | V1: 43344 | W1: 43374 | X1: 43405 | Y1: 43435 | Z1: 43466 | AA1: 43497 | AB1: 43525 | AC1: 43556 | AD1: 43586 | AE1: 43617 | AF1: 43647 | AG1: 43678 | AH1: 43709 | AI1: 43739 | AJ1: 43770 | AK1: 43800 | AL1: 43831 | AM1: 43862 | AN1: 43891 | AO1: 43922 | AP1: 43952 | AQ1: 43983 | AR1: 44013 | AS1: 44044 | AT1: 44075 | AU1: 44105 | AV1: 44136 | AW1: 44166 | AX1: 44197 | AY1: 44228 | AZ1: 44256 | BA1: 44287 | BB1: 44317 | BC1: 44348 | BD1: 44378 | BE1: 44409 | BF1: 44440 | BG1: 44470 | BH1: 44501 | BI1: 44531 | BJ1: 44562 | BK1: 44593 | BL1: 44621 | BM1: 44652 | BN1: 44682 | BO1: 44713 | BP1: 44743 | BQ1: 44774 | BR1: 44805 | BS1: 44835 | BT1: 44866 | BU1: 44896 | BV1: 44927 | BW1: 44958 | BX1: 44986 | BY1: 45017 | BZ1: 45047 | CA1: 45078 | CB1: 45108 | CC1: 45139 | CD1: 45170 | CE1: 45200 | CF1: 45231 | CG1: 45261 | CH1: 45292 | CI1: 45323 | CJ1: 45352 | CK1: 45383 | CL1: 45413 | CM1: 45444 | CN1: 45474 | CO1: 45505 | CP1: 45536 | CQ1: 45566 | CR1: 45597 | CS1: 45627 | CT1: 45658 | CU1: 45689 | CV1: 45717 | CW1: 45748 | CX1: 45778 | CY1: 45809 | CZ1: 45839 | DA1: 45870 | DB1: 45901 | DC1: 45931 | DD1: 45962 | DE1: 45992 | DF1: 46023 | DG1: 46054 | DH1: 46082 | DI1: 46113 | DJ1: 46143 | DK1: 46174 | DL1: 46204 | DM1: 46235 | DN1: 46266 | DO1: 46296 | DP1: 46327 | DQ1: 46357 | DR1: 46388 | DS1: 46419 | DT1: 46447 | DU1: 46478 | DV1: 46508 | DW1: 46539 | DX1: 46569 | DY1: 46600 | DZ1: 46631 | EA1: 46661 | EB1: 46692 | EC1: 46722 | ED1: 46753 | EE1: 46784 | EF1: 46813 | EG1: 46844 | EH1: 46874 | EI1: 46905 | EJ1: 46935 | EK1: 46966 | EL1: 46997 | EM1: 47027 | EN1: 47058 | EO1: 47088 | EP1: 47119 | EQ1: 47150 | ER1: 47178 | ES1: 47209 | ET1: 47239 | EU1: 47270 | EV1: 47300 | EW1: 47331 | EX1: 47362 | EY1: 47392 | EZ1: 47423 | FA1: 47453
A2: Ingresos por Intereses | B2: =B52*B46/12 -> #REF! | C2: =C52*C46/12 -> #REF! | D2: =D52*D46/12 -> #REF! | E2: =E52*E46/12 -> #REF! | F2: =F52*F46/12 -> #REF! | G2: =G52*G46/12 -> #REF! | H2: =H52*H46/12 -> #REF! | I2: =I52*I46/12 -> #REF! | ... CG2: =CG52*CG46/12 -> #REF! | CH2: 17680.753 | CI2: 17631.547 | CJ2: 17771.454 | CK2: 17390.616 | CL2: 17744.96 | CM2: 18224.778 | CN2: 18220.482 | CO2: 18457.067 | CP2: 92383.189 | CQ2: 97493.857 | CR2: 370452.24 | CS2: 370104.55 | CT2: 369788.25 | CU2: 653527.02 | CV2: 867596.47 | CW2: 1365097.5 | CX2: 1577717.7 | CY2: 1794483.5 | CZ2: 1797754.2 | DA2: 1802069.4 | DB2: 1800032.5 | DC2: 1803977.5 | DD2: 1808662.7 | DE2: 1813038.6 | DF2: 1815206.1 | DG2: 1820111.5 | DH2: 1824580 | DI2: 1831553.4 | DJ2: 1833679.1 | DK2: 1838117.9 | DL2: 1840940.3 | DM2: 1843972.6 | DN2: 1841067.7 | DO2: 1839090.3 | DP2: 1842276.6 | DQ2: 1845919 | DR2: 1852898 | DS2: 1855184.6 | DT2: 1859231.2 | DU2: 1858152.4 | DV2: 1856673.3 | DW2: 1861887.4 | DX2: 1865080.1 | DY2: 1869191.8 | DZ2: 1877368.9 | EA2: 1887346.9 | EB2: 1897349.1 | EC2: 1910809.5 | ED2: 1922911 | EE2: 1942155.9 | EF2: 1957542.7 | EG2: 1964199.1 | EH2: 1985114.5 | EI2: 2015466.6 | EJ2: 2028301 | EK2: 2022878.3 | EL2: 2051451.8 | EM2: 2068222.2 | EN2: 2101442.8 | EO2: 2078548.2 | EP2: 2118380.9 | EQ2: 2104254.2 | ER2: 2166687.6 | ES2: 2240644.2 | ET2: 2358818.6 | EU2: 2437515.7 | EV2: 2888535.2 | EW2: 3092187.3 | EX2: 3309111.6 | EY2: 0 | EZ2: 0 | FA2: 0
A4: Comisiones de Apertura y Preoriginación | B4: =#REF! -> #REF! | C4: =#REF! -> #REF! | D4: =#REF! -> #REF! | E4: =#REF! -> #REF! | F4: =#REF! -> #REF! | G4: =#REF! -> #REF! | H4: =#REF! -> #REF! | I4: =#REF! -> #REF! | ... CG4: =#REF! -> #REF! | CH4: 143476.08 | CI4: 112522.68 | CJ4: 41129.2 | CK4: 153075.28 | CL4: 176065.56 | CM4: 103720.42 | CN4: 121839.7 | CO4: 167684.58 | CP4: 157378.68 | CQ4: 17664.24 | CR4: 512465.9 | CS4: 509675.44 | CT4: 107007.41 | CU4: 504751.89 | CV4: 404969.95 | CW4: 405732.01 | CX4: 102572.67 | CY4: 98017.185 | CZ4: 98115.729 | DA4: 98093.801 | DB4: 98918.412 | DC4: 93347.041 | DD4: 93095.718 | DE4: 93475.457 | DF4: 92957.612 | DG4: 90887.966 | DH4: 90800.018 | DI4: 89874.54 | DJ4: 90555.282 | DK4: 87312.689 | DL4: 85900.313 | DM4: 83512.655 | DN4: 81113.591 | DO4: 75895.662 | DP4: 71991.6 | DQ4: 70567.38 | DR4: 69730.996 | DS4: 70314.591 | DT4: 68753.719 | DU4: 67867.102 | DV4: 64951.381 | DW4: 62505.595 | DX4: 62190.12 | DY4: 61266.041 | DZ4: 60442.123 | EA4: 60346.06 | EB4: 60449.285 | EC4: 60189.681 | ED4: 60402.641 | EE4: 59852.449 | EF4: 60235.171 | EG4: 59438.062 | EH4: 57056.844 | EI4: 56289.404 | EJ4: 55829.9 | EK4: 53338.117 | EL4: 49704.746 | EM4: 48560.516 | EN4: 46616.913 | EO4: 45445.52 | EP4: 42648.874 | EQ4: 41868.456 | ER4: 40099.298 | ES4: 39730.497 | ET4: 39156.57 | EU4: 38543.819 | EV4: 37456.97 | EW4: 37373.41 | EX4: 36008.875 | EY4: 35715.251 | EZ4: 35792.194 | FA4: 36060.635
A5: Comisiones de Administración | B5: =#REF! -> #REF! | C5: =#REF! -> #REF! | D5: =#REF! -> #REF! | E5: =#REF! -> #REF! | F5: =#REF! -> #REF! | G5: =#REF! -> #REF! | H5: =#REF! -> #REF! | I5: =#REF! -> #REF! | ... CG5: =#REF! -> #REF! | CH5: 619810.34 | CI5: 657343.22 | CJ5: 687399.6 | CK5: 685065.91 | CL5: 728561.52 | CM5: 786023.94 | CN5: 805613.79 | CO5: 839588.74 | CP5: 894218.17 | CQ5: 950629.83 | CR5: 1251720.6 | CS5: 1279712.2 | CT5: 1307559.7 | CU5: 1535597.7 | CV5: 1713039.1 | CW5: 2088174.3 | CX5: 2262214.9 | CY5: 2438594 | CZ5: 2464445.3 | DA5: 2489734.3 | DB5: 2511899.7 | DC5: 2536695.7 | DD5: 2560939.4 | DE5: 2584726.9 | DF5: 2606460.8 | DG5: 2628595.5 | DH5: 2649185.3 | DI5: 2670682.5 | DJ5: 2690285.6 | DK5: 2710977.4 | DL5: 2730208 | DM5: 2749958.2 | DN5: 2766892.8 | DO5: 2784344.4 | DP5: 2803323.9 | DQ5: 2821486.4 | DR5: 2839905.6 | DS5: 2857738.3 | DT5: 2875901.9 | DU5: 2891815.6 | DV5: 2908971.6 | DW5: 2925582.8 | DX5: 2941848.8 | DY5: 2958283.3 | DZ5: 2974665.3 | EA5: 2991134.6 | EB5: 3007849.2 | EC5: 3023829.6 | ED5: 3039436.8 | EE5: 3055347 | EF5: 3070113.2 | EG5: 3084229.3 | EH5: 3099258 | EI5: 3114557.6 | EJ5: 3128991.5 | EK5: 3143002.3 | EL5: 3158360.3 | EM5: 3173456.8 | EN5: 3189060.6 | EO5: 3204004.8 | EP5: 3220065.3 | EQ5: 3235774.9 | ER5: 3252299 | ES5: 3268852.2 | ET5: 3285516.7 | EU5: 3302082.6 | EV5: 3319270.8 | EW5: 3335967.7 | EX5: 3353323.6 | EY5: 3370993.5 | EZ5: 3388889.6 | FA5: 3406919.9
A6: Comisiones de Éxito | B6: =IF(B1>Supuestos!$D$22,Supuestos!$B$22*B41,Supuestos!$B$21*B44) -> #REF! | C6: =IF(C1>Supuestos!$D$22,Supuestos!$B$22*C41,Supuestos!$B$21*C44) -> #REF! | D6: =IF(D1>Supuestos!$D$22,Supuestos!$B$22*D41,Supuestos!$B$21*D44) -> #REF! | E6: =IF(E1>Supuestos!$D$22,Supuestos!$B$22*E41,Supuestos!$B$21*E44) -> #REF! | F6: =IF(F1>Supuestos!$D$22,Supuestos!$B$22*F41,Supuestos!$B$21*F44) -> #REF! | G6: =IF(G1>Supuestos!$D$22,Supuestos!$B$22*G41,Supuestos!$B$21*G44) -> #REF! | H6: =IF(H1>Supuestos!$D$22,Supuestos!$B$22*H41,Supuestos!$B$21*H44) -> #REF! | I6: =IF(I1>Supuestos!$D$22,Supuestos!$B$22*I41,Supuestos!$B$21*I44) -> #REF! | ... CG6: =IF(CG1>Supuestos!$D$22,Supuestos!$B$22*CG41,Supuestos!$B$21*CG44) -> #REF! | CH6: 124346.62 | CI6: 125886.47 | CJ6: 122884.67 | CK6: 122582.87 | CL6: 128007.74 | CM6: 129375.4 | CN6: 126787.78 | CO6: 125012.58 | CP6: 120596.59 | CQ6: 196094.06 | CR6: 199463.91 | CS6: 201416.1 | CT6: 203391.15 | CU6: 205627.27 | CV6: 207949.64 | CW6: 209926.23 | CX6: 211801.08 | CY6: 214183.93 | CZ6: 216562.55 | DA6: 219090.86 | DB6: 220865.75 | DC6: 223387.58 | DD6: 226026.39 | DE6: 228653.2 | DF6: 231024.64 | DG6: 233767.06 | DH6: 236480.59 | DI6: 239547.9 | DJ6: 242009.29 | DK6: 244797.5 | DL6: 247394.74 | DM6: 250041.99 | DN6: 251899.06 | DO6: 253889.01 | DP6: 256606.61 | DQ6: 259412.08 | DR6: 262716.34 | DS6: 265385.2 | DT6: 268330.03 | DU6: 270555.91 | DV6: 272735.12 | DW6: 275917.81 | DX6: 278829.8 | DY6: 281906.17 | DZ6: 285629.55 | EA6: 289669.79 | EB6: 293759.66 | EC6: 298435.64 | ED6: 302953.96 | EE6: 308659.88 | EF6: 313821.09 | EG6: 317632.79 | EH6: 323806.62 | EI6: 331612.11 | EJ6: 336617.45 | EK6: 338621.66 | EL6: 346366.95 | EM6: 352205.58 | EN6: 360938.22 | EO6: 360068.76 | EP6: 370109.65 | EQ6: 370783.2 | ER6: 385040.55 | ES6: 401575 | ET6: 426350.58 | EU6: 444317.28 | EV6: 530995.74 | EW6: 573248.14 | EX6: 618650.62 | EY6: 0 | EZ6: 0 | FA6: 0
A7: Total Comisiones | B7: =SUM(B4:B6) -> #REF! | C7: =SUM(C4:C6) -> #REF! | D7: =SUM(D4:D6) -> #REF! | E7: =SUM(E4:E6) -> #REF! | F7: =SUM(F4:F6) -> #REF! | G7: =SUM(G4:G6) -> #REF! | H7: =SUM(H4:H6) -> #REF! | I7: =SUM(I4:I6) -> #REF! | ... CQ7: =SUM(CQ4:CQ6) -> 1164388.1 | CR7: =SUM(CR4:CR6)*Supuestos!$B$4 -> 1767285.3 | CS7: =SUM(CS4:CS6)*Supuestos!$B$4 -> 1791723.4 | CT7: =SUM(CT4:CT6)*Supuestos!$B$4 -> 1456162.4 | CU7: =SUM(CU4:CU6)*Supuestos!$B$4 -> 2021379.1 | CV7: =SUM(CV4:CV6)*Supuestos!$B$4 -> 2093362.8 | CW7: =SUM(CW4:CW6)*Supuestos!$B$4 -> 2433449.3 | CX7: =SUM(CX4:CX6)*Supuestos!$B$4 -> 2318929.8 | CY7: =SUM(CY4:CY6)*Supuestos!$B$4 -> 2475715.6 | ... FA7: =SUM(FA4:FA6)*Supuestos!$B$4 -> 3098682.5
CR9: =#REF!+CR41*0.1 -> #REF! | CS9: =#REF!+CS41*0.1 -> #REF! | CT9: =#REF!+CT41*0.1 -> #REF! | CU9: =#REF!+CU41*0.1 -> #REF! | CV9: =#REF!+CV41*0.1 -> #REF! | CW9: =#REF!+CW41*0.1 -> #REF! | CX9: =#REF!+CX41*0.1 -> #REF! | CY9: =#REF!+CY41*0.1 -> #REF! | ... FA9: =#REF!+FA41*0.1 -> #REF!
CQ10: 0.205 | CR10: =CR9/POWER((1+($CQ$10/12)),CR11) -> #REF! | CS10: =CS9/POWER((1+($CQ$10/12)),CS11) -> #REF! | CT10: =CT9/POWER((1+($CQ$10/12)),CT11) -> #REF! | CU10: =CU9/POWER((1+($CQ$10/12)),CU11) -> #REF! | CV10: =CV9/POWER((1+($CQ$10/12)),CV11) -> #REF! | CW10: =CW9/POWER((1+($CQ$10/12)),CW11) -> #REF! | CX10: =CX9/POWER((1+($CQ$10/12)),CX11) -> #REF! | CY10: =CY9/POWER((1+($CQ$10/12)),CY11) -> #REF! | ... FA10: =FA9/POWER((1+($CQ$10/12)),FA11) -> #REF!
CR11: 0 | CS11: 1 | CT11: 2 | CU11: 3 | CV11: 4 | CW11: 5 | CX11: 6 | CY11: 7 | CZ11: 8 | DA11: 9 | DB11: 10 | DC11: 11 | DD11: 12 | DE11: 13 | DF11: 14 | DG11: 15 | DH11: 16 | DI11: 17 | DJ11: 18 | DK11: 19 | DL11: 20 | DM11: 21 | DN11: 22 | DO11: 23 | DP11: 24 | DQ11: 25 | DR11: 26 | DS11: 27 | DT11: 28 | DU11: 29 | DV11: 30 | DW11: 31 | DX11: 32 | DY11: 33 | DZ11: 34 | EA11: 35 | EB11: 36 | EC11: 37 | ED11: 38 | EE11: 39 | EF11: 40 | EG11: 41 | EH11: 42 | EI11: 43 | EJ11: 44 | EK11: 45 | EL11: 46 | EM11: 47 | EN11: 48 | EO11: 49 | EP11: 50 | EQ11: 51 | ER11: 52 | ES11: 53 | ET11: 54 | EU11: 55 | EV11: 56 | EW11: 57 | EX11: 58 | EY11: 59 | EZ11: 60 | FA11: 61
CR12: {=NPV(CQ10/12,CR9:EC9)} -> #REF! | CS12: =SUM(CR10:EC10) -> #REF!
A14: Gastos por Intereses Fondeador 2 | CH14: 0 | CI14: 0 | CJ14: 0 | CK14: 0 | CL14: 0 | CM14: 0 | CN14: 0 | CO14: 0 | CP14: 0 | CQ14: 0 | CR14: 0 | CW14: -350000 | CX14: -612500 | CY14: -875000 | CZ14: -875000 | DA14: -875000 | DB14: -875000 | DC14: -875000 | DD14: -852573.96 | DE14: -829755.47 | DF14: -806537.66 | DG14: -782913.53 | DH14: -758875.98 | DI14: -734417.78 | DJ14: -709531.55 | DK14: -684209.82 | DL14: -658444.96 | DM14: -632229.21 | DN14: -605554.68 | DO14: -578413.35 | DP14: -550797.05 | DQ14: -522697.46 | DR14: -494106.13 | DS14: -465014.46 | DT14: -435413.67 | DU14: -405294.88 | DV14: -374649 | DW14: -343466.82 | DX14: -311738.96 | DY14: -279455.85 | DZ14: -246607.8 | EA14: -213184.9 | EB14: -179177.1 | EC14: -144574.16 | ED14: -109365.67 | EE14: -73541.037 | EF14: -37089.47
A15: Gastos por Comisiones Fondeador 2 | CH15: 0 | CI15: 0 | CJ15: 0 | CK15: 0 | CL15: 0 | CM15: 0 | CN15: 0 | CO15: 0 | CP15: 0 | CQ15: 0 | CR15: 0 | CW15: -420833.33 | CX15: -320833.33 | CY15: -320833.33 | CZ15: -20833.333 | DA15: -20833.333 | DB15: -20833.333 | DC15: -20833.333 | DD15: -20833.333 | DE15: -20833.333 | DF15: -20833.333 | DG15: -20833.333 | DH15: -20833.333 | DI15: -20833.333 | DJ15: -20833.333 | DK15: -20833.333 | DL15: -20833.333 | DM15: -20833.333 | DN15: -20833.333 | DO15: -20833.333 | DP15: -20833.333 | DQ15: -20833.333 | DR15: -20833.333 | DS15: -20833.333 | DT15: -20833.333 | DU15: -20833.333 | DV15: -20833.333 | DW15: -20833.333 | DX15: -20833.333 | DY15: -20833.333 | DZ15: -20833.333 | EA15: -20833.333 | EB15: -20833.333 | EC15: -20833.333 | ED15: -20833.333 | EE15: -20833.333 | EF15: -20833.333
A16: Gastos por Intereses | CH16: 0 | CI16: 0 | CJ16: 0 | CK16: 0 | CL16: 0 | CM16: 0 | CN16: 0 | CO16: 0 | CP16: 0 | CQ16: 0 | CR16: 0 | CU16: -350000 | CV16: -612500 | CW16: -875000 | CX16: -875000 | CY16: -875000 | CZ16: -875000 | DA16: -875000 | DB16: -852573.96 | DC16: -829755.47 | DD16: -806537.66 | DE16: -782913.53 | DF16: -758875.98 | DG16: -734417.78 | DH16: -709531.55 | DI16: -684209.82 | DJ16: -658444.96 | DK16: -632229.21 | DL16: -605554.68 | DM16: -578413.35 | DN16: -550797.05 | DO16: -522697.46 | DP16: -494106.13 | DQ16: -465014.46 | DR16: -435413.67 | DS16: -405294.88 | DT16: -374649 | DU16: -343466.82 | DV16: -311738.96 | DW16: -279455.85 | DX16: -246607.8 | DY16: -213184.9 | DZ16: -179177.1 | EA16: -144574.16 | EB16: -109365.67 | EC16: -73541.037 | ED16: -37089.47
A17: Gastos por Comisiones Syscap | CH17: 0 | CI17: 0 | CJ17: 0 | CK17: 0 | CL17: 0 | CM17: 0 | CN17: 0 | CO17: 0 | CP17: 0 | CQ17: 0 | CR17: 0 | CU17: -420833.33 | CV17: -320833.33 | CW17: -320833.33 | CX17: -20833.333 | CY17: -20833.333 | CZ17: -20833.333 | DA17: -20833.333 | DB17: -20833.333 | DC17: -20833.333 | DD17: -20833.333 | DE17: -20833.333 | DF17: -20833.333 | DG17: -20833.333 | DH17: -20833.333 | DI17: -20833.333 | DJ17: -20833.333 | DK17: -20833.333 | DL17: -20833.333 | DM17: -20833.333 | DN17: -20833.333 | DO17: -20833.333 | DP17: -20833.333 | DQ17: -20833.333 | DR17: -20833.333 | DS17: -20833.333 | DT17: -20833.333 | DU17: -20833.333 | DV17: -20833.333 | DW17: -20833.333 | DX17: -20833.333 | DY17: -20833.333 | DZ17: -20833.333 | EA17: -20833.333 | EB17: -20833.333 | EC17: -20833.333 | ED17: -20833.333
A18: Comisiones Pagadas | CH18: -500000 | CI18: -500000 | CJ18: -500000 | CK18: -500000 | CL18: -500000 | CM18: -500000 | CN18: -500000 | CO18: -500000 | CP18: -500000 | CQ18: -500000 | CR18: -500000 | CS18: -500000 | CT18: -500000 | CU18: -500000 | CV18: -500000 | CW18: -500000 | CX18: -500000 | CY18: -500000 | CZ18: -500000 | DA18: -500000 | DB18: -500000 | DC18: -500000 | DD18: -500000 | DE18: -500000 | DF18: -500000 | DG18: -500000 | DH18: -500000 | DI18: -500000 | DJ18: -500000 | DK18: -500000 | DL18: -500000 | DM18: -500000 | DN18: -500000 | DO18: -500000 | DP18: -500000 | DQ18: -500000 | DR18: -500000 | DS18: -500000 | DT18: -500000 | DU18: -500000 | DV18: -500000 | DW18: -500000 | DX18: -500000 | DY18: -500000 | DZ18: -500000 | EA18: -500000 | EB18: -500000 | EC18: -500000 | ED18: -500000 | EE18: -500000 | EF18: -500000 | EG18: -500000 | EH18: -500000 | EI18: -500000 | EJ18: -500000 | EK18: -500000 | EL18: -500000 | EM18: -500000 | EN18: -500000 | EO18: -500000 | EP18: -500000 | EQ18: -500000 | ER18: -500000 | ES18: -500000 | ET18: -500000 | EU18: -500000 | EV18: -500000 | EW18: -500000 | EX18: -500000 | EY18: -500000 | EZ18: -500000 | FA18: -500000
A19: Total Gastos por Intereses | CH19: =SUM(CH16:CH18) -> -500000 | CI19: =SUM(CI16:CI18) -> -500000 | CJ19: =SUM(CJ16:CJ18) -> -500000 | CK19: =SUM(CK16:CK18) -> -500000 | CL19: =SUM(CL16:CL18) -> -500000 | CM19: =SUM(CM16:CM18) -> -500000 | CN19: =SUM(CN16:CN18) -> -500000 | CO19: =SUM(CO16:CO18) -> -500000 | ... FA19: =SUM(FA16:FA18) -> -500000
A21: Margen Financiero | CH21: =CH2+CH7+CH19 -> 405313.79 | CI21: =CI2+CI7+CI19 -> 413383.91 | CJ21: =CJ2+CJ7+CJ19 -> 369184.92 | CK21: =CK2+CK7+CK19 -> 478114.67 | CL21: =CL2+CL7+CL19 -> 550379.78 | CM21: =CM2+CM7+CM19 -> 537344.54 | CN21: =CN2+CN7+CN19 -> 572461.76 | CO21: =CO2+CO7+CO19 -> 650742.96 | ... FA21: =FA2+FA7+FA19 -> 2598682.5
CH22: =CH21/(CH2+CH7) -> 0.44770531 | CI22: =CI21/(CI2+CI7) -> 0.45258506 | CJ22: =CJ21/(CJ2+CJ7) -> 0.42474842 | CK22: =CK21/(CK2+CK7) -> 0.48881249 | CL22: =CL21/(CL2+CL7) -> 0.5239817 | CM22: =CM21/(CM2+CM7) -> 0.51800006 | CN22: =CN21/(CN2+CN7) -> 0.53378291 | CO22: =CO21/(CO2+CO7) -> 0.5654981 | ... FA22: =FA21/(FA2+FA7) -> 0.8386411
A24: Beneficios directos a corto plazo | CH24: =CI24*(1-Supuestos!$B$6/12) -> -566606.14 | CI24: =CJ24*(1-Supuestos!$B$6/12) -> -569453.4 | CJ24: =CK24*(1-Supuestos!$B$6/12) -> -572314.98 | CK24: =CL24*(1-Supuestos!$B$6/12) -> -575190.93 | CL24: =CM24*(1-Supuestos!$B$6/12) -> -578081.34 | CM24: =CN24*(1-Supuestos!$B$6/12) -> -580986.27 | CN24: =CO24*(1-Supuestos!$B$6/12) -> -583905.8 | CO24: -586840 | CP24: =CO24*(1+Supuestos!$B$6/12) -> -589774.2 | CQ24: =CP24*(1+Supuestos!$B$6/12) -> -592723.07 | CR24: =CQ24*(1+Supuestos!$B$6/12) -> -595686.69 | CS24: =CR24*(1+Supuestos!$B$6/12) -> -598665.12 | CT24: =CS24*(1+Supuestos!$B$6/12) -> -601658.45 | CU24: =CT24*(1+Supuestos!$B$6/12) -> -604666.74 | CV24: =CU24*(1+Supuestos!$B$6/12) -> -607690.07 | CW24: =CV24*(1+Supuestos!$B$6/12) -> -610728.52 | ... FA24: =EZ24*(1+Supuestos!$B$6/12) -> -807509.54
A25: Honorarios | CH25: =CI25*(1-Supuestos!$B$6/12) -> -367823.78 | CI25: =CJ25*(1-Supuestos!$B$6/12) -> -369672.14 | CJ25: =CK25*(1-Supuestos!$B$6/12) -> -371529.79 | CK25: =CL25*(1-Supuestos!$B$6/12) -> -373396.77 | CL25: =CM25*(1-Supuestos!$B$6/12) -> -375273.14 | CM25: =CN25*(1-Supuestos!$B$6/12) -> -377158.93 | CN25: =CO25*(1-Supuestos!$B$6/12) -> -379054.21 | CO25: -380959 | CP25: =CO25*(1+Supuestos!$B$6/12) -> -382863.79 | CQ25: =CP25*(1+Supuestos!$B$6/12) -> -384778.11 | CR25: =CQ25*(1+Supuestos!$B$6/12) -> -386702 | CS25: =CR25*(1+Supuestos!$B$6/12) -> -388635.51 | CT25: =CS25*(1+Supuestos!$B$6/12) -> -390578.69 | CU25: =CT25*(1+Supuestos!$B$6/12) -> -392531.59 | CV25: =CU25*(1+Supuestos!$B$6/12) -> -394494.24 | CW25: =CV25*(1+Supuestos!$B$6/12) -> -396466.71 | ... FA25: =EZ25*(1+Supuestos!$B$6/12) -> -524211.07
A26: Impuestos y derechos diversos | CH26: =CI26*(1-Supuestos!$B$6/12) -> -183231.68 | CI26: =CJ26*(1-Supuestos!$B$6/12) -> -184152.44 | CJ26: =CK26*(1-Supuestos!$B$6/12) -> -185077.83 | CK26: =CL26*(1-Supuestos!$B$6/12) -> -186007.87 | CL26: =CM26*(1-Supuestos!$B$6/12) -> -186942.58 | CM26: =CN26*(1-Supuestos!$B$6/12) -> -187881.99 | CN26: =CO26*(1-Supuestos!$B$6/12) -> -188826.12 | CO26: -189775 | CP26: =CO26*(1+Supuestos!$B$6/12) -> -190723.87 | CQ26: =CP26*(1+Supuestos!$B$6/12) -> -191677.49 | CR26: =CQ26*(1+Supuestos!$B$6/12) -> -192635.88 | CS26: =CR26*(1+Supuestos!$B$6/12) -> -193599.06 | CT26: =CS26*(1+Supuestos!$B$6/12) -> -194567.06 | CU26: =CT26*(1+Supuestos!$B$6/12) -> -195539.89 | CV26: =CU26*(1+Supuestos!$B$6/12) -> -196517.59 | CW26: =CV26*(1+Supuestos!$B$6/12) -> -197500.18 | ... FA26: =EZ26*(1+Supuestos!$B$6/12) -> -261136.12
A27: Gastos en tecnología | CH27: =CI27*(1-Supuestos!$B$6/12) -> -84767.885 | CI27: =CJ27*(1-Supuestos!$B$6/12) -> -85193.854 | CJ27: =CK27*(1-Supuestos!$B$6/12) -> -85621.964 | CK27: =CL27*(1-Supuestos!$B$6/12) -> -86052.225 | CL27: =CM27*(1-Supuestos!$B$6/12) -> -86484.649 | CM27: =CN27*(1-Supuestos!$B$6/12) -> -86919.245 | CN27: =CO27*(1-Supuestos!$B$6/12) -> -87356.025 | CO27: -87795 | CP27: =CO27*(1+Supuestos!$B$6/12) -> -88233.975 | CQ27: =CP27*(1+Supuestos!$B$6/12) -> -88675.145 | CR27: =CQ27*(1+Supuestos!$B$6/12) -> -89118.521 | CS27: =CR27*(1+Supuestos!$B$6/12) -> -89564.113 | CT27: =CS27*(1+Supuestos!$B$6/12) -> -90011.934 | CU27: =CT27*(1+Supuestos!$B$6/12) -> -90461.993 | CV27: =CU27*(1+Supuestos!$B$6/12) -> -90914.303 | CW27: =CV27*(1+Supuestos!$B$6/12) -> -91368.875 | ... FA27: =EZ27*(1+Supuestos!$B$6/12) -> -120808.57
A28: Otros gastos | CH28: =CI28*(1-Supuestos!$B$6/12) -> -100059.8 | CI28: =CJ28*(1-Supuestos!$B$6/12) -> -100562.61 | CJ28: =CK28*(1-Supuestos!$B$6/12) -> -101067.95 | CK28: =CL28*(1-Supuestos!$B$6/12) -> -101575.83 | CL28: =CM28*(1-Supuestos!$B$6/12) -> -102086.26 | CM28: =CN28*(1-Supuestos!$B$6/12) -> -102599.26 | CN28: =CO28*(1-Supuestos!$B$6/12) -> -103114.84 | CO28: -103633 | CP28: =CO28*(1+Supuestos!$B$6/12) -> -104151.16 | CQ28: =CP28*(1+Supuestos!$B$6/12) -> -104671.92 | CR28: =CQ28*(1+Supuestos!$B$6/12) -> -105195.28 | CS28: =CR28*(1+Supuestos!$B$6/12) -> -105721.26 | CT28: =CS28*(1+Supuestos!$B$6/12) -> -106249.86 | CU28: =CT28*(1+Supuestos!$B$6/12) -> -106781.11 | CV28: =CU28*(1+Supuestos!$B$6/12) -> -107315.02 | CW28: =CV28*(1+Supuestos!$B$6/12) -> -107851.59 | ... FA28: =EZ28*(1+Supuestos!$B$6/12) -> -142602.13
A29: Total Gastos | CH29: =SUM(CH24:CH28) -> -1302489.3 | CI29: =SUM(CI24:CI28) -> -1309034.5 | CJ29: =SUM(CJ24:CJ28) -> -1315612.5 | CK29: =SUM(CK24:CK28) -> -1322223.6 | CL29: =SUM(CL24:CL28) -> -1328868 | CM29: =SUM(CM24:CM28) -> -1335545.7 | CN29: =SUM(CN24:CN28) -> -1342257 | CO29: =SUM(CO24:CO28) -> -1349002 | ... FA29: =SUM(FA24:FA28) -> -1856267.4
A31: Margen Neto | CH31: =CH29+CH21 -> -897175.5 | CI31: =CI29+CI21 -> -895650.54 | CJ31: =CJ29+CJ21 -> -946427.6 | CK31: =CK29+CK21 -> -844108.97 | CL31: =CL29+CL21 -> -778488.2 | CM31: =CM29+CM21 -> -798201.17 | CN31: =CN29+CN21 -> -769795.23 | CO31: =CO29+CO21 -> -698259.04 | ... FA31: =FA29+FA21 -> 742415.02
A34: CUENTAS BAJO ADMINISTRACIÓN
A36: Saldo Vigente Portafolio AUM | B36: =#REF! -> #REF! | C36: =#REF! -> #REF! | D36: =#REF! -> #REF! | E36: =#REF! -> #REF! | F36: =#REF! -> #REF! | G36: =#REF! -> #REF! | H36: =#REF! -> #REF! | I36: =#REF! -> #REF! | ... CG36: =#REF! -> #REF! | CH36: 1.2128955e+08 | CI36: 1.1927845e+08 | CJ36: 1.163798e+08 | CK36: 1.1919881e+08 | CL36: 1.2228258e+08 | CM36: 1.2173847e+08 | CN36: 1.2261893e+08 | CO36: 1.2627676e+08 | CP36: 1.295254e+08 | CQ36: 1.2588781e+08 | CR36: 1.2140754e+08 | CS36: 1.1707536e+08 | CT36: 1.1288522e+08 | CU36: 1.0881656e+08 | CV36: 1.0474577e+08 | CW36: 1.006457e+08 | CX36: 96712502 | CY36: 93016042 | CZ36: 89323687 | DA36: 85641530 | DB36: 81927311 | DC36: 78500899 | DD36: 75096360 | DE36: 71682210 | DF36: 68303400 | DG36: 65037591 | DH36: 61785768 | DI36: 58589880 | DJ36: 55369689 | DK36: 52321435 | DL36: 49353680 | DM36: 46515262 | DN36: 43806826 | DO36: 41369391 | DP36: 39137340 | DQ36: 36986756 | DR36: 34888324 | DS36: 32771124 | DT36: 30742456 | DU36: 28768686 | DV36: 26951350 | DW36: 25267030 | DX36: 23609290 | DY36: 22008643 | DZ36: 20460161 | EA36: 18927535 | EB36: 17400883 | EC36: 15898430 | ED36: 14396631 | EE36: 12933729 | EF36: 11463164 | EG36: 10044014 | EH36: 8755570 | EI36: 7517231.1 | EJ36: 6313688.4 | EK36: 5246644.4 | EL36: 4373268 | EM36: 3569192.1 | EN36: 2874475.9 | EO36: 2250600.3 | EP36: 1778920 | EQ36: 1358716.4 | ER36: 1039519.8 | ES36: 751406.53 | ET36: 504727.71 | EU36: 301520.05 | EV36: 165584.72 | EW36: 46854.223 | EX36: 9475.0157 | EY36: 0 | EZ36: 0 | FA36: 0
A37: Saldo Vencido Portafolio AUM | B37: =#REF! -> #REF! | C37: =#REF! -> #REF! | D37: =#REF! -> #REF! | E37: =#REF! -> #REF! | F37: =#REF! -> #REF! | G37: =#REF! -> #REF! | H37: =#REF! -> #REF! | I37: =#REF! -> #REF! | ... CG37: =#REF! -> #REF! | CH37: 20882184 | CI37: 23945660 | CJ37: 24217653 | CK37: 24591728 | CL37: 25629327 | CM37: 26271008 | CN37: 26271008 | CO37: 26368010 | CP37: 26515280 | CQ37: 26515280 | CR37: 26515280 | CS37: 26515280 | CT37: 26515280 | CU37: 26515280 | CV37: 26515280 | CW37: 26515280 | CX37: 26515280 | CY37: 26515280 | CZ37: 26515280 | DA37: 26515280 | DB37: 26515280 | DC37: 26515280 | DD37: 26515280 | DE37: 26515280 | DF37: 26515280 | DG37: 26515280 | DH37: 26515280 | DI37: 26515280 | DJ37: 26515280 | DK37: 26515280 | DL37: 26515280 | DM37: 26515280 | DN37: 26515280 | DO37: 26515280 | DP37: 26515280 | DQ37: 26515280 | DR37: 26515280 | DS37: 26515280 | DT37: 26515280 | DU37: 26515280 | DV37: 26515280 | DW37: 26515280 | DX37: 26515280 | DY37: 26515280 | DZ37: 26515280 | EA37: 26515280 | EB37: 26515280 | EC37: 26515280 | ED37: 26515280 | EE37: 26515280 | EF37: 26515280 | EG37: 26515280 | EH37: 26515280 | EI37: 26515280 | EJ37: 26515280 | EK37: 26515280 | EL37: 26515280 | EM37: 26515280 | EN37: 26515280 | EO37: 26515280 | EP37: 26515280 | EQ37: 26515280 | ER37: 26515280 | ES37: 26515280 | ET37: 26515280 | EU37: 26515280 | EV37: 26515280 | EW37: 26515280 | EX37: 26515280 | EY37: 26515280 | EZ37: 26515280 | FA37: 26515280
A38: Nuevo Saldo Portafolio AUM | CR38: 5623295 | CS38: 11107067 | CT38: 16457438 | CU38: 21695032 | CV38: 26943530 | CW38: 32230130 | CX38: 37358764 | CY38: 42259623 | CZ38: 47165409 | DA38: 52070099 | DB38: 57016020 | DC38: 61683372 | DD38: 66338158 | DE38: 71011931 | DF38: 75659811 | DG38: 80204210 | DH38: 84744210 | DI38: 89237937 | DJ38: 93765702 | DK38: 98131336 | DL38: 1.0242635e+08 | DM38: 1.0660198e+08 | DN38: 1.1065766e+08 | DO38: 1.1445245e+08 | DP38: 1.1805203e+08 | DQ38: 1.215804e+08 | DR38: 1.2506695e+08 | DS38: 1.2858268e+08 | DT38: 1.3202036e+08 | DU38: 1.3541372e+08 | DV38: 1.3866129e+08 | DW38: 1.4178657e+08 | DX38: 1.4489607e+08 | DY38: 1.4795937e+08 | DZ38: 1.5098148e+08 | EA38: 1.5399878e+08 | EB38: 1.5702125e+08 | EC38: 1.6003073e+08 | ED38: 1.6305086e+08 | EE38: 1.6604349e+08 | EF38: 1.6905524e+08 | EG38: 1.7202715e+08 | EH38: 1.7487999e+08 | EI38: 1.7769446e+08 | EJ38: 1.8048595e+08 | EK38: 1.8315286e+08 | EL38: 1.856381e+08 | EM38: 1.8806612e+08 | EN38: 1.9039697e+08 | EO38: 1.9266925e+08 | EP38: 1.9480169e+08 | EQ38: 1.9689511e+08 | ER38: 1.9890008e+08 | ES38: 2.008866e+08 | ET38: 2.0284443e+08 | EU38: 2.0477162e+08 | EV38: 2.0664447e+08 | EW38: 2.0851314e+08 | EX38: 2.1031358e+08 | EY38: 2.1209935e+08 | EZ38: 2.1388896e+08 | FA38: 2.1569199e+08
A39: Saldo Total Portafolio AUM | B39: =SUM(B36:B37) -> #REF! | C39: =SUM(C36:C37) -> #REF! | D39: =SUM(D36:D37) -> #REF! | E39: =SUM(E36:E37) -> #REF! | F39: =SUM(F36:F37) -> #REF! | G39: =SUM(G36:G37) -> #REF! | H39: =SUM(H36:H37) -> #REF! | I39: =SUM(I36:I37) -> #REF! | ... CQ39: =SUM(CQ36:CQ37) -> 1.5240309e+08 | CR39: =CQ39*(1+Supuestos!$B$5) -> 1.5354611e+08 | CS39: =CR39*(1+Supuestos!$B$5) -> 1.5469771e+08 | CT39: =CS39*(1+Supuestos!$B$5) -> 1.5585794e+08 | CU39: =CT39*(1+Supuestos!$B$5) -> 1.5702688e+08 | CV39: =CU39*(1+Supuestos!$B$5) -> 1.5820458e+08 | CW39: =CV39*(1+Supuestos!$B$5) -> 1.5939111e+08 | CX39: =CW39*(1+Supuestos!$B$5) -> 1.6058655e+08 | CY39: =CX39*(1+Supuestos!$B$5) -> 1.6179094e+08 | ... FA39: =EZ39*(1+Supuestos!$B$5) -> 2.4220727e+08
A41: Intereses Portafolio AUM | B41: =#REF! -> #REF! | C41: =#REF! -> #REF! | D41: =#REF! -> #REF! | E41: =#REF! -> #REF! | F41: =#REF! -> #REF! | G41: =#REF! -> #REF! | H41: =#REF! -> #REF! | I41: =#REF! -> #REF! | ... CG41: =#REF! -> #REF! | CH41: 1768075.3 | CI41: 1763154.7 | CJ41: 1777145.4 | CK41: 1739061.6 | CL41: 1774496 | CM41: 1822477.8 | CN41: 1822048.2 | CO41: 1845706.7 | CP41: 1900792.1 | CQ41: 1960940.6 | CR41: 1906342 | CS41: 1839633 | CT41: 1775118.5 | CU41: 1714457.1 | CV41: 1654033 | CW41: 1590068.9 | CX41: 1527830.2 | CY41: 1472736.6 | CZ41: 1417268.2 | DA41: 1362504.8 | DB41: 1302325 | DC41: 1250933.9 | DD41: 1200114.3 | DE41: 1148636.3 | DF41: 1096097.3 | DG41: 1046781.7 | DH41: 997143.05 | DI41: 949420.95 | DJ41: 898511.01 | DK41: 851307.46 | DL41: 804443.17 | DM41: 759598.87 | DN41: 714397.1 | DO41: 674054.04 | DP41: 638904.54 | DQ41: 605094.51 | DR41: 573018.49 | DS41: 539000.09 | DT41: 506818.7 | DU41: 474078.71 | DV41: 443841.72 | DW41: 417328.55 | DX41: 390668.5 | DY41: 365031.74 | DZ41: 340875.57 | EA41: 317056.14 | EB41: 293063.59 | EC41: 269691.39 | ED41: 245791.94 | EE41: 223052.04 | EF41: 199280.66 | EG41: 175223.15 | EH41: 154387.94 | EI41: 134592.2 | EJ41: 113774.18 | EK41: 94301.068 | EL41: 79719.206 | EM41: 65598 | EN41: 53681.402 | EO41: 41574.569 | EP41: 33492.392 | EQ41: 25411.324 | ER41: 20018.91 | ES41: 14964.742 | ET41: 10582.338 | EU41: 6532.8187 | EV41: 4251.4751 | EW41: 1287.8355 | EX41: 278.70099 | EY41: 0 | EZ41: 0 | FA41: 0
A42: Intereses Nuevo Portafolio AUM | CR42: 88297.018 | CS42: 174527.99 | CT42: 258792.98 | CU42: 341815.62 | CV42: 425463.37 | CW42: 509193.4 | CX42: 590180.64 | CY42: 669102.77 | CZ42: 748357.31 | DA42: 828403.72 | DB42: 906332.54 | DC42: 982941.88 | DD42: 1060149.6 | DE42: 1137895.7 | DF42: 1214149.1 | DG42: 1290888.8 | DH42: 1367662.9 | DI42: 1446058 | DJ42: 1521581.9 | DK42: 1596667.6 | DL42: 1669504.3 | DM42: 1740821.1 | DN42: 1804593.5 | DO42: 1864836.1 | DP42: 1927161.5 | DQ42: 1989026.3 | DR42: 2054144.9 | DS42: 2114851.9 | DT42: 2176481.6 | DU42: 2231480.4 | DV42: 2283509.5 | DW42: 2341849.6 | DX42: 2397629.5 | DY42: 2454029.9 | DZ42: 2515419.9 | EA42: 2579641.7 | EB42: 2644533 | EC42: 2714665 | ED42: 2783747.7 | EE42: 2863546.8 | EF42: 2938930.3 | EG42: 3001104.8 | EH42: 3083678.2 | EI42: 3181528.9 | EJ42: 3252400.3 | EK42: 3291915.6 | EL42: 3383950.3 | EM42: 3456457.8 | EN42: 3555700.8 | EO42: 3559113 | EP42: 3667604.2 | EQ42: 3682420.7 | ER42: 3830386.6 | ES42: 4000785.3 | ET42: 4252923.5 | EU42: 4436639.9 | EV42: 5305705.9 | EW42: 5731193.5 | EX42: 6186227.5 | EY42: 0 | EZ42: 0 | FA42: 0
A43: Amortizaciones Portafolio AUM | B43: =#REF! -> #REF! | C43: =#REF! -> #REF! | D43: =#REF! -> #REF! | E43: =#REF! -> #REF! | F43: =#REF! -> #REF! | G43: =#REF! -> #REF! | H43: =#REF! -> #REF! | I43: =#REF! -> #REF! | ... CG43: =#REF! -> #REF! | CH43: 4449255.7 | CI43: 4531168.7 | CJ43: 4367087.9 | CK43: 4390081.9 | CL43: 4625890.7 | CM43: 4646292.1 | CN43: 4517340.9 | CO43: 4404922.1 | CP43: 4129037.2 | CQ43: 4363473.6 | CR43: 4229969.5 | CS43: 4091089.3 | CT43: 3972099.5 | CU43: 3973286.9 | CV43: 4001159.4 | CW43: 3838666.6 | CX43: 3608253.3 | CY43: 3603362 | CZ43: 3592663.2 | DA43: 3623515.6 | DB43: 3343630.7 | DC43: 3321386.7 | DD43: 3330063 | DE43: 3294329.1 | DF43: 3183823 | DG43: 3169494.8 | DH43: 3114970.4 | DI43: 3138325.8 | DJ43: 2970748.8 | DK43: 2891663.2 | DL43: 2765671.5 | DM43: 2638157.1 | DN43: 2374448.9 | DO43: 2174626.7 | DP43: 2094404 | DQ43: 2043337.8 | DR43: 2061517.6 | DS43: 1975058.9 | DT43: 1920952.6 | DU43: 1768862.9 | DV43: 1638640.5 | DW43: 1612618.9 | DX43: 1557049.2 | DY43: 1506060 | DZ43: 1490458.2 | EA43: 1484449.7 | EB43: 1460153.9 | EC43: 1459272.8 | ED43: 1421079.9 | EE43: 1428152.8 | EF43: 1378277.9 | EG43: 1251327.5 | EH43: 1202683.6 | EI43: 1168894 | EJ43: 1036366 | EK43: 848260.41 | EL43: 780926.89 | EM43: 674671.72 | EN43: 605870.59 | EO43: 458129.48 | EP43: 408127.8 | EQ43: 310073.21 | ER43: 279905.65 | ES43: 239694.05 | ET43: 197469.29 | EU43: 132104.56 | EV43: 115375.01 | EW43: 36302.851 | EX43: 9208.8493 | EY43: 0 | EZ43: 0 | FA43: 0
A44: Total Cobranza Portafolio AUM | B44: =SUM(B41:B43) -> #REF! | C44: =SUM(C41:C43) -> #REF! | D44: =SUM(D41:D43) -> #REF! | E44: =SUM(E41:E43) -> #REF! | F44: =SUM(F41:F43) -> #REF! | G44: =SUM(G41:G43) -> #REF! | H44: =SUM(H41:H43) -> #REF! | I44: =SUM(I41:I43) -> #REF! | ... FA44: =SUM(FA41:FA43) -> 0
A46: Tasa Activa Promedio Portafolio AUM | B46: 0 | C46: =C41/B36*12 -> #REF! | D46: =D41/C36*12 -> #REF! | E46: =E41/D36*12 -> #REF! | F46: =F41/E36*12 -> #REF! | G46: =G41/F36*12 -> #REF! | H46: =H41/G36*12 -> #REF! | I46: =I41/H36*12 -> #REF! | J46: =J41/I36*12 -> #REF! | ... N46: =N41/M36*12 -> #REF! | O46: =O41/O36*12 -> #REF! | P46: =P41/P36*12 -> #REF! | Q46: =Q41/Q36*12 -> #REF! | R46: =R41/R36*12 -> #REF! | S46: =S41/S36*12 -> #REF! | T46: =T41/T36*12 -> #REF! | U46: =U41/U36*12 -> #REF! | V46: =V41/V36*12 -> #REF! | ... EX46: =EX41/EX36*12 -> 0.35297164
A48: BALANCE
A50: Efectivo y equivalentes de efectivo | BY50: 500000 | BZ50: 500000 | CA50: 500000 | CB50: 500000 | CC50: 500000 | CD50: 500000 | CE50: 500000 | CF50: 500000 | CG50: 500000 | CH50: 500000 | CI50: 500000 | CJ50: 500000 | CK50: 500000 | CL50: 500000 | CM50: 500000 | CN50: 500000 | CO50: 500000 | CP50: 500000 | CQ50: 500000 | CR50: 500000 | CS50: 500000 | CT50: 500000 | CU50: 500000 | CV50: 500000 | CW50: 500000 | CX50: 500000 | CY50: 500000 | CZ50: 500000 | DA50: 500000 | DB50: 500000 | DC50: 500000 | DD50: 500000 | DE50: 500000 | DF50: 500000 | DG50: 500000 | DH50: 500000 | DI50: 500000 | DJ50: 500000 | DK50: 500000 | DL50: 500000 | DM50: 500000 | DN50: 500000 | DO50: 500000 | DP50: 500000 | DQ50: 500000 | DR50: 500000 | DS50: 500000 | DT50: 500000 | DU50: 500000 | DV50: 500000 | DW50: 500000 | DX50: 500000 | DY50: 500000 | DZ50: 500000 | EA50: 500000 | EB50: 500000 | EC50: 500000 | ED50: 500000 | EE50: 500000 | EF50: 500000 | EG50: 500000 | EH50: 500000 | EI50: 500000 | EJ50: 500000 | EK50: 500000 | EL50: 500000 | EM50: 500000 | EN50: 500000 | EO50: 500000 | EP50: 500000 | EQ50: 500000 | ER50: 500000 | ES50: 500000 | ET50: 500000 | EU50: 500000 | EV50: 500000 | EW50: 500000 | EX50: 500000 | EY50: 500000 | EZ50: 500000 | FA50: 500000
A52: Inversiones en instrumentos financieros (1% Cartera) | B52: =B36*Supuestos!$D$10 -> #REF! | C52: =C36*Supuestos!$D$10 -> #REF! | D52: =D36*Supuestos!$D$10 -> #REF! | E52: =E36*Supuestos!$D$10 -> #REF! | F52: =F36*Supuestos!$D$10 -> #REF! | G52: =G36*Supuestos!$D$10 -> #REF! | H52: =H36*Supuestos!$D$10 -> #REF! | I52: =I36*Supuestos!$D$10 -> #REF! | ... FA52: =FA36*Supuestos!$D$10 -> 0
A53: Colocaciones Propias | CH53: 0 | CI53: 0 | CJ53: 0 | CK53: 0 | CL53: 0 | CM53: 0 | CN53: 0 | CO53: 0 | CQ53: 0 | CW53: {=TRANSPOSE('Crédito Syscap'!C2:C10)} -> 20000000 | CX53: 15000000 | CY53: 15000000 | CZ53: 0 | DA53: 0 | DB53: 0 | DC53: 0 | DD53: 0 | DE53: 0
A54: Colocaciones Propias | CH54: 0 | CI54: 0 | CJ54: 0 | CK54: 0 | CL54: 0 | CM54: 0 | CN54: 0 | CO54: 0 | CP54: =Supuestos!$B$3 -> 5000000 | CQ54: 0 | CR54: =Supuestos!D5 -> 20000000 | CU54: {=TRANSPOSE('Crédito Syscap'!C2:C10)} -> 20000000 | CV54: 15000000 | CW54: 15000000 | CX54: 0 | CY54: 0 | CZ54: 0 | DA54: 0 | DB54: 0 | DC54: 0
A55: Cartera Propia Originada | CC55: 0 | CD55: 0 | CE55: 0 | CF55: 0 | CG55: 0 | CH55: 0 | CI55: 0 | CJ55: 0 | CK55: 0 | CL55: 0 | CM55: 0 | CN55: 0 | CO55: 0 | CP55: =CO55+CP54 -> 5000000 | CQ55: =CP55+CQ54 -> 5000000 | CR55: =CQ55+CR54 -> 25000000 | CS55: =CR55+CS54+CS53 -> 25000000 | CT55: =CS55+CT54+CT53 -> 25000000 | CU55: =CT55+CU54+CU53 -> 45000000 | CV55: =CU55+CV54+CV53 -> 60000000 | CW55: =CV55+CW54+CW53 -> 95000000 | CX55: =CW55+CX54+CX53 -> 110000000 | CY55: =CX55+CY54+CY53 -> 125000000 | CZ55: =CY55+CZ54+CZ53 -> 125000000 | DA55: =CZ55+DA54 -> 125000000 | DB55: =DA55+DB54 -> 125000000 | DC55: =DB55+DC54 -> 125000000 | DD55: =DC55+DD54 -> 125000000 | DE55: =DD55+DE54 -> 125000000 | DF55: =DE55+DF54 -> 125000000 | DG55: =DF55+DG54 -> 125000000 | DH55: =DG55+DH54 -> 125000000 | ... FA55: =EZ55+FA54 -> 125000000
A56: Cartera Total | CH56: =CH55+CH52 -> 1212895.5 | CI56: =CI55+CI52 -> 1192784.5 | CJ56: =CJ55+CJ52 -> 1163798 | CK56: =CK55+CK52 -> 1191988.1 | CL56: =CL55+CL52 -> 1222825.8 | CM56: =CM55+CM52 -> 1217384.7 | CN56: =CN55+CN52 -> 1226189.3 | CO56: =CO55+CO52 -> 1262767.6 | ... FA56: =FA55+FA52 -> 125000000
CR57: =CR56/(CR39+CR56) -> 0.14582804 | CS57: =CS56/(CS39+CS56) -> 0.14469495 | CT57: =CT56/(CT39+CT56) -> 0.14357554 | CU57: =CU56/(CU39+CU56) -> 0.22690671 | CV57: =CV56/(CV39+CV56) -> 0.27843508 | CW57: =CW56/(CW39+CW56) -> 0.37590983 | CX57: =CX56/(CX39+CX56) -> 0.40863791 | CY57: =CY56/(CY39+CY56) -> 0.43768135 | ... DP57: =DP56/(DP39+DP56) -> 0.40567126
A58: Estimación de pérdidas crediticias | BY58: =-BY52/BY39*BY37 -> #REF! | BZ58: =-BZ52/BZ39*BZ37 -> #REF! | CA58: =-CA52/CA39*CA37 -> #REF! | CB58: =-CB52/CB39*CB37 -> #REF! | CC58: =-CC52/CC39*CC37 -> #REF! | CD58: =-CD52/CD39*CD37 -> #REF! | CE58: =-CE52/CE39*CE37 -> #REF! | CF58: =-CF52/CF39*CF37 -> #REF! | ... CQ58: =-CQ52/CQ39*CQ37 -> -219021.19 | CR58: 0 | CS58: 0 | CT58: 0 | CU58: 0 | CV58: 0 | CW58: 0 | CX58: 0 | CY58: 0 | CZ58: 0 | DA58: 0 | DB58: 0 | DC58: 0 | DD58: 0 | DE58: 0 | DF58: 0 | DG58: 0 | DH58: 0 | DI58: 0 | DJ58: 0 | DK58: 0 | DL58: 0 | DM58: 0 | DN58: 0 | DO58: 0 | DP58: 0 | DQ58: 0 | DR58: 0 | DS58: 0 | DT58: 0 | DU58: 0 | DV58: 0 | DW58: 0 | DX58: 0 | DY58: 0 | DZ58: 0 | EA58: 0 | EB58: 0 | EC58: 0 | ED58: 0 | EE58: 0 | EF58: 0 | EG58: 0 | EH58: 0 | EI58: 0 | EJ58: 0 | EK58: 0 | EL58: 0 | EM58: 0 | EN58: 0 | EO58: 0 | EP58: 0 | EQ58: 0 | ER58: 0 | ES58: 0 | ET58: 0 | EU58: 0 | EV58: 0 | EW58: 0 | EX58: 0 | EY58: 0 | EZ58: 0 | FA58: 0
A59: Cuentas por cobrar, neto | BY59: =Supuestos!$D2 -> 0 | BZ59: =Supuestos!$D2 -> 0 | CA59: =Supuestos!$D2 -> 0 | CB59: =Supuestos!$D2 -> 0 | CC59: =Supuestos!$D2 -> 0 | CD59: =Supuestos!$D2 -> 0 | CE59: =Supuestos!$D2 -> 0 | CF59: =Supuestos!$D2 -> 0 | ... FA59: =Supuestos!$D2 -> 0
A60: Pagos anticipados y otros activos, neto | BY60: =Supuestos!$D3 -> 1500000 | BZ60: =Supuestos!$D3 -> 1500000 | CA60: =Supuestos!$D3 -> 1500000 | CB60: =Supuestos!$D3 -> 1500000 | CC60: =Supuestos!$D3 -> 1500000 | CD60: =Supuestos!$D3 -> 1500000 | CE60: =Supuestos!$D3 -> 1500000 | CF60: =Supuestos!$D3 -> 1500000 | ... FA60: =Supuestos!$D3 -> 1500000
A61: Propiedades, mobiliario y equipo, neto | BY61: =Supuestos!$D4 -> 200000 | BZ61: =Supuestos!$D4 -> 200000 | CA61: =Supuestos!$D4 -> 200000 | CB61: =Supuestos!$D4 -> 200000 | CC61: =Supuestos!$D4 -> 200000 | CD61: =Supuestos!$D4 -> 200000 | CE61: =Supuestos!$D4 -> 200000 | CF61: =Supuestos!$D4 -> 200000 | ... FA61: =Supuestos!$D4 -> 200000
A62: Activo por impuestos a la utilidad diferidos, neto | BY62: =Supuestos!$D5 -> 20000000 | BZ62: =Supuestos!$D5 -> 20000000 | CA62: =Supuestos!$D5 -> 20000000 | CB62: =Supuestos!$D5 -> 20000000 | CC62: =Supuestos!$D5 -> 20000000 | CD62: =Supuestos!$D5 -> 20000000 | CE62: =Supuestos!$D5 -> 20000000 | CF62: =Supuestos!$D5 -> 20000000 | CG62: =Supuestos!$D5 -> 20000000 | CH62: 325000 | CI62: 325000 | CJ62: 325000 | CK62: 325000 | CL62: 325000 | CM62: 325000 | CN62: 325000 | CO62: 325000 | CP62: 325000 | CQ62: 325000 | CR62: 325000 | CS62: 325000 | CT62: 325000 | CU62: 325000 | CV62: 325000 | CW62: 325000 | CX62: 325000 | CY62: 325000 | CZ62: 325000 | DA62: =Supuestos!$D5 -> 20000000 | DB62: =Supuestos!$D5 -> 20000000 | DC62: =Supuestos!$D5 -> 20000000 | DD62: =Supuestos!$D5 -> 20000000 | DE62: =Supuestos!$D5 -> 20000000 | DF62: =Supuestos!$D5 -> 20000000 | DG62: =Supuestos!$D5 -> 20000000 | DH62: =Supuestos!$D5 -> 20000000 | ... FA62: =Supuestos!$D5 -> 20000000
A63: Total Activo | BY63: =SUM(BY50:BY62) -> #REF! | BZ63: =SUM(BZ50:BZ62) -> #REF! | CA63: =SUM(CA50:CA62) -> #REF! | CB63: =SUM(CB50:CB62) -> #REF! | CC63: =SUM(CC50:CC62) -> #REF! | CD63: =SUM(CD50:CD62) -> #REF! | CE63: =SUM(CE50:CE62) -> #REF! | CF63: =SUM(CF50:CF62) -> #REF! | CG63: =SUM(CG50:CG62) -> #REF! | CH63: =SUM(CH58:CH62)+CH55+CH50 -> 2346849.9 | CI63: =SUM(CI58:CI62)+CI55+CI50 -> 2325578.2 | CJ63: =SUM(CJ58:CJ62)+CJ55+CJ50 -> 2324537.9 | CK63: =SUM(CK58:CK62)+CK55+CK50 -> 2321140.6 | CL63: =SUM(CL58:CL62)+CL55+CL50 -> 2313115.8 | CM63: =SUM(CM58:CM62)+CM55+CM50 -> 2308919.8 | CN63: =SUM(CN58:CN62)+CN55+CN50 -> 2308644 | CO63: =SUM(CO58:CO62)+CO55+CO50 -> 2306868.3 | ... FA63: =SUM(FA58:FA62)+FA55+FA50 -> 147200000
A65: Préstamos de corto plazo | BY65: 150000 | BZ65: 150000 | CA65: 150000 | CB65: 150000 | CC65: 150000 | CD65: 150000 | CE65: 150000 | CF65: 150000 | CG65: 150000 | CH65: 150000 | CI65: 150000 | CJ65: 150000 | CK65: 150000 | CL65: 150000 | CM65: 150000 | CN65: 150000 | CO65: 150000 | CP65: 150000 | CQ65: 150000 | CR65: 150000 | CS65: 150000 | CT65: 150000 | CU65: 150000 | CV65: 150000 | CW65: 150000 | CX65: 150000 | CY65: 150000 | CZ65: 150000 | DA65: 150000 | DB65: 150000 | DC65: 150000 | DD65: 150000 | DE65: 150000 | DF65: 150000 | DG65: 150000 | DH65: 150000 | DI65: 150000 | DJ65: 150000 | DK65: 150000 | DL65: 150000 | DM65: 150000 | DN65: 150000 | DO65: 150000 | DP65: 150000 | DQ65: 150000 | DR65: 150000 | DS65: 150000 | DT65: 150000 | DU65: 150000 | DV65: 150000 | DW65: 150000 | DX65: 150000 | DY65: 150000 | DZ65: 150000 | EA65: 150000 | EB65: 150000 | EC65: 150000 | ED65: 150000 | EE65: 150000 | EF65: 150000 | EG65: 150000 | EH65: 150000 | EI65: 150000 | EJ65: 150000 | EK65: 150000 | EL65: 150000 | EM65: 150000 | EN65: 150000 | EO65: 150000 | EP65: 150000 | EQ65: 150000 | ER65: 150000 | ES65: 150000 | ET65: 150000 | EU65: 150000 | EV65: 150000 | EW65: 150000 | EX65: 150000 | EY65: 150000 | EZ65: 150000 | FA65: 150000
A66: Préstamos de largo plazo | BY66: 7500000 | BZ66: 7500000 | CA66: 7500000 | CB66: 7500000 | CC66: 7500000 | CD66: 7500000 | CE66: 7500000 | CF66: 7500000 | CG66: 7500000 | CH66: 7500000 | CI66: 7500000 | CJ66: 7500000 | CK66: 7500000 | CL66: 7500000 | CM66: 7500000 | CN66: 7500000 | CO66: 7500000 | CP66: 11265000 | CQ66: 11100000 | CR66: =CQ66/CP66*CQ66 -> 10937417 | CS66: =CR66/CQ66*CR66 -> 10777215 | CT66: =CS66/CR66*CS66 -> 10619360 | CU66: =CT66/CS66*CT66 -> 10463816 | CV66: =CU66/CT66*CU66 -> 10310551 | CW66: =CV66/CU66*CV66 -> 10159531 | CX66: =CW66/CV66*CW66 -> 10010723 | CY66: =CX66/CW66*CX66 -> 9864094.9 | ... FA66: =EZ66/EY66*EZ66 -> 4446451
A67: Crédito Fondeador 2 | CH67: 0 | CI67: 0 | CJ67: 0 | CK67: 0 | CL67: 0 | CM67: 0 | CN67: 0 | CO67: 0 | CP67: 0 | CQ67: 0 | CR67: 0 | CW67: {=TRANSPOSE('Crédito Syscap'!B3:B38)} -> 20000000 | CX67: 35000000 | CY67: 50000000 | CZ67: 50000000 | DA67: 50000000 | DB67: 50000000 | DC67: 50000000 | DD67: 48718512 | DE67: 47414598 | DF67: 46087866 | DG67: 44737916 | DH67: 43364342 | DI67: 41966730 | DJ67: 40544660 | DK67: 39097704 | DL67: 37625426 | DM67: 36127383 | DN67: 34603125 | DO67: 33052192 | DP67: 31474117 | DQ67: 29868427 | DR67: 28234636 | DS67: 26572255 | DT67: 24880781 | DU67: 23159707 | DV67: 21408514 | DW67: 19626676 | DX67: 17813655 | DY67: 15968906 | DZ67: 14091874 | EA67: 12181994 | EB67: 10238691 | EC67: 8261380.6 | ED67: 6249467.1 | EE67: 4202345 | EF67: 2119398.3
A68: Crédito Syscap | CH68: 0 | CI68: 0 | CJ68: 0 | CK68: 0 | CL68: 0 | CM68: 0 | CN68: 0 | CO68: 0 | CP68: 0 | CQ68: 0 | CR68: 0 | CU68: {=TRANSPOSE('Crédito Syscap'!B3:B38)} -> 20000000 | CV68: 35000000 | CW68: 50000000 | CX68: 50000000 | CY68: 50000000 | CZ68: 50000000 | DA68: 50000000 | DB68: 48718512 | DC68: 47414598 | DD68: 46087866 | DE68: 44737916 | DF68: 43364342 | DG68: 41966730 | DH68: 40544660 | DI68: 39097704 | DJ68: 37625426 | DK68: 36127383 | DL68: 34603125 | DM68: 33052192 | DN68: 31474117 | DO68: 29868427 | DP68: 28234636 | DQ68: 26572255 | DR68: 24880781 | DS68: 23159707 | DT68: 21408514 | DU68: 19626676 | DV68: 17813655 | DW68: 15968906 | DX68: 14091874 | DY68: 12181994 | DZ68: 10238691 | EA68: 8261380.6 | EB68: 6249467.1 | EC68: 4202345 | ED68: 2119398.3
A69: Contribuciones por pagar | BY69: 750000 | BZ69: 750000 | CA69: 750000 | CB69: 750000 | CC69: 750000 | CD69: 750000 | CE69: 750000 | CF69: 750000 | CG69: 750000 | CH69: 750000 | CI69: 750000 | CJ69: 750000 | CK69: 750000 | CL69: 750000 | CM69: 750000 | CN69: 750000 | CO69: 750000 | CP69: 750000 | CQ69: 750000 | CR69: 750000 | CS69: 750000 | CT69: 750000 | CU69: 750000 | CV69: 750000 | CW69: 750000 | CX69: 750000 | CY69: 750000 | CZ69: 750000 | DA69: 750000 | DB69: 750000 | DC69: 750000 | DD69: 750000 | DE69: 750000 | DF69: 750000 | DG69: 750000 | DH69: 750000 | DI69: 750000 | DJ69: 750000 | DK69: 750000 | DL69: 750000 | DM69: 750000 | DN69: 750000 | DO69: 750000 | DP69: 750000 | DQ69: 750000 | DR69: 750000 | DS69: 750000 | DT69: 750000 | DU69: 750000 | DV69: 750000 | DW69: 750000 | DX69: 750000 | DY69: 750000 | DZ69: 750000 | EA69: 750000 | EB69: 750000 | EC69: 750000 | ED69: 750000 | EE69: 750000 | EF69: 750000 | EG69: 750000 | EH69: 750000 | EI69: 750000 | EJ69: 750000 | EK69: 750000 | EL69: 750000 | EM69: 750000 | EN69: 750000 | EO69: 750000 | EP69: 750000 | EQ69: 750000 | ER69: 750000 | ES69: 750000 | ET69: 750000 | EU69: 750000 | EV69: 750000 | EW69: 750000 | EX69: 750000 | EY69: 750000 | EZ69: 750000 | FA69: 750000
A70: Acreedores diversas y otras cuentas por pagar | BY70: 200000 | BZ70: 200000 | CA70: 200000 | CB70: 200000 | CC70: 200000 | CD70: 200000 | CE70: 200000 | CF70: 200000 | CG70: 200000 | CH70: 200000 | CI70: 200000 | CJ70: 200000 | CK70: 200000 | CL70: 200000 | CM70: 200000 | CN70: 200000 | CO70: 200000 | CP70: 200000 | CQ70: 200000 | CR70: 200000 | CS70: 200000 | CT70: 200000 | CU70: 200000 | CV70: 200000 | CW70: 200000 | CX70: 200000 | CY70: 200000 | CZ70: 200000 | DA70: 200000 | DB70: 200000 | DC70: 200000 | DD70: 200000 | DE70: 200000 | DF70: 200000 | DG70: 200000 | DH70: 200000 | DI70: 200000 | DJ70: 200000 | DK70: 200000 | DL70: 200000 | DM70: 200000 | DN70: 200000 | DO70: 200000 | DP70: 200000 | DQ70: 200000 | DR70: 200000 | DS70: 200000 | DT70: 200000 | DU70: 200000 | DV70: 200000 | DW70: 200000 | DX70: 200000 | DY70: 200000 | DZ70: 200000 | EA70: 200000 | EB70: 200000 | EC70: 200000 | ED70: 200000 | EE70: 200000 | EF70: 200000 | EG70: 200000 | EH70: 200000 | EI70: 200000 | EJ70: 200000 | EK70: 200000 | EL70: 200000 | EM70: 200000 | EN70: 200000 | EO70: 200000 | EP70: 200000 | EQ70: 200000 | ER70: 200000 | ES70: 200000 | ET70: 200000 | EU70: 200000 | EV70: 200000 | EW70: 200000 | EX70: 200000 | EY70: 200000 | EZ70: 200000 | FA70: 200000
A71: Pasivo por impuestos a la utilidad | BY71: 230000 | BZ71: 230000 | CA71: 230000 | CB71: 230000 | CC71: 230000 | CD71: 230000 | CE71: 230000 | CF71: 230000 | CG71: 230000 | CH71: 230000 | CI71: 230000 | CJ71: 230000 | CK71: 230000 | CL71: 230000 | CM71: 230000 | CN71: 230000 | CO71: 230000 | CP71: 230000 | CQ71: 230000 | CR71: 230000 | CS71: 230000 | CT71: 230000 | CU71: 230000 | CV71: 230000 | CW71: 230000 | CX71: 230000 | CY71: 230000 | CZ71: 230000 | DA71: 230000 | DB71: 230000 | DC71: 230000 | DD71: 230000 | DE71: 230000 | DF71: 230000 | DG71: 230000 | DH71: 230000 | DI71: 230000 | DJ71: 230000 | DK71: 230000 | DL71: 230000 | DM71: 230000 | DN71: 230000 | DO71: 230000 | DP71: 230000 | DQ71: 230000 | DR71: 230000 | DS71: 230000 | DT71: 230000 | DU71: 230000 | DV71: 230000 | DW71: 230000 | DX71: 230000 | DY71: 230000 | DZ71: 230000 | EA71: 230000 | EB71: 230000 | EC71: 230000 | ED71: 230000 | EE71: 230000 | EF71: 230000 | EG71: 230000 | EH71: 230000 | EI71: 230000 | EJ71: 230000 | EK71: 230000 | EL71: 230000 | EM71: 230000 | EN71: 230000 | EO71: 230000 | EP71: 230000 | EQ71: 230000 | ER71: 230000 | ES71: 230000 | ET71: 230000 | EU71: 230000 | EV71: 230000 | EW71: 230000 | EX71: 230000 | EY71: 230000 | EZ71: 230000 | FA71: 230000
A72: Pasivo por Beneficios a Empleados | BY72: 400000 | BZ72: 400000 | CA72: 400000 | CB72: 400000 | CC72: 400000 | CD72: 400000 | CE72: 400000 | CF72: 400000 | CG72: 400000 | CH72: 400000 | CI72: 400000 | CJ72: 400000 | CK72: 400000 | CL72: 400000 | CM72: 400000 | CN72: 400000 | CO72: 400000 | CP72: 400000 | CQ72: 400000 | CR72: 400000 | CS72: 400000 | CT72: 400000 | CU72: 400000 | CV72: 400000 | CW72: 400000 | CX72: 400000 | CY72: 400000 | CZ72: 400000 | DA72: 400000 | DB72: 400000 | DC72: 400000 | DD72: 400000 | DE72: 400000 | DF72: 400000 | DG72: 400000 | DH72: 400000 | DI72: 400000 | DJ72: 400000 | DK72: 400000 | DL72: 400000 | DM72: 400000 | DN72: 400000 | DO72: 400000 | DP72: 400000 | DQ72: 400000 | DR72: 400000 | DS72: 400000 | DT72: 400000 | DU72: 400000 | DV72: 400000 | DW72: 400000 | DX72: 400000 | DY72: 400000 | DZ72: 400000 | EA72: 400000 | EB72: 400000 | EC72: 400000 | ED72: 400000 | EE72: 400000 | EF72: 400000 | EG72: 400000 | EH72: 400000 | EI72: 400000 | EJ72: 400000 | EK72: 400000 | EL72: 400000 | EM72: 400000 | EN72: 400000 | EO72: 400000 | EP72: 400000 | EQ72: 400000 | ER72: 400000 | ES72: 400000 | ET72: 400000 | EU72: 400000 | EV72: 400000 | EW72: 400000 | EX72: 400000 | EY72: 400000 | EZ72: 400000 | FA72: 400000
A73: Total Pasivo | BY73: =SUM(BY65:BY72) -> 9230000 | BZ73: =SUM(BZ65:BZ72) -> 9230000 | CA73: =SUM(CA65:CA72) -> 9230000 | CB73: =SUM(CB65:CB72) -> 9230000 | CC73: =SUM(CC65:CC72) -> 9230000 | CD73: =SUM(CD65:CD72) -> 9230000 | CE73: =SUM(CE65:CE72) -> 9230000 | CF73: =SUM(CF65:CF72) -> 9230000 | ... FA73: =SUM(FA65:FA72) -> 6176451
A75: Capital Social | BY75: 3564000 | BZ75: 3564000 | CA75: 3564000 | CB75: 3564000 | CC75: 3564000 | CD75: 3564000 | CE75: 3564000 | CF75: 3564000 | CG75: 3564000 | CH75: 3564000 | CI75: 3564000 | CJ75: 3564000 | CK75: 3564000 | CL75: 3564000 | CM75: 3564000 | CN75: 3564000 | CO75: 3564000 | CP75: 3564000 | CQ75: 3564000 | CR75: 3564000 | CS75: 3564000 | CT75: 3564000 | CU75: 3564000 | CV75: 3564000 | CW75: 3564000 | CX75: 3564000 | CY75: 3564000 | CZ75: 3564000 | DA75: 3564000 | DB75: 3564000 | DC75: 3564000 | DD75: 3564000 | DE75: 3564000 | DF75: 3564000 | DG75: 3564000 | DH75: 3564000 | DI75: 3564000 | DJ75: 3564000 | DK75: 3564000 | DL75: 3564000 | DM75: 3564000 | DN75: 3564000 | DO75: 3564000 | DP75: 3564000 | DQ75: 3564000 | DR75: 3564000 | DS75: 3564000 | DT75: 3564000 | DU75: 3564000 | DV75: 3564000 | DW75: 3564000 | DX75: 3564000 | DY75: 3564000 | DZ75: 3564000 | EA75: 3564000 | EB75: 3564000 | EC75: 3564000 | ED75: 3564000 | EE75: 3564000 | EF75: 3564000 | EG75: 3564000 | EH75: 3564000 | EI75: 3564000 | EJ75: 3564000 | EK75: 3564000 | EL75: 3564000 | EM75: 3564000 | EN75: 3564000 | EO75: 3564000 | EP75: 3564000 | EQ75: 3564000 | ER75: 3564000 | ES75: 3564000 | ET75: 3564000 | EU75: 3564000 | EV75: 3564000 | EW75: 3564000 | EX75: 3564000 | EY75: 3564000 | EZ75: 3564000 | FA75: 3564000
A76: Aportaciones para futuros aumentos de capital | CH76: 22768000 | CI76: 22768000 | CJ76: 22768000 | CK76: 22768000 | CL76: 22768000 | CM76: 22768000 | CN76: 22768000 | CO76: 22768000 | CP76: 22768000 | CQ76: 22768000 | CR76: 22768000 | CS76: 22768000 | CT76: 22768000 | CU76: 22768000 | CV76: 22768000 | CW76: 22768000 | CX76: 22768000 | CY76: 22768000 | CZ76: 22768000 | DA76: 22768000 | DB76: 22768000 | DC76: 22768000 | DD76: 22768000 | DE76: 22768000 | DF76: 22768000 | DG76: 22768000 | DH76: 22768000 | DI76: 22768000 | DJ76: 22768000 | DK76: 22768000 | DL76: 22768000 | DM76: 22768000 | DN76: 22768000 | DO76: 22768000 | DP76: 22768000 | DQ76: 22768000 | DR76: 22768000 | DS76: 22768000 | DT76: 22768000 | DU76: 22768000 | DV76: 22768000 | DW76: 22768000 | DX76: 22768000 | DY76: 22768000 | DZ76: 22768000 | EA76: 22768000 | EB76: 22768000 | EC76: 22768000 | ED76: 22768000 | EE76: 22768000 | EF76: 22768000 | EG76: 22768000 | EH76: 22768000 | EI76: 22768000 | EJ76: 22768000 | EK76: 22768000 | EL76: 22768000 | EM76: 22768000 | EN76: 22768000 | EO76: 22768000 | EP76: 22768000 | EQ76: 22768000 | ER76: 22768000 | ES76: 22768000 | ET76: 22768000 | EU76: 22768000 | EV76: 22768000 | EW76: 22768000 | EX76: 22768000 | EY76: 22768000 | EZ76: 22768000 | FA76: 22768000
A77: Resultados acumulados | CH77: -17000000 | CI77: -17500000 | CJ77: -18000000 | CK77: -18500000 | CL77: -19000000 | CM77: -19500000 | CN77: -20000000 | CO77: -20500000 | CP77: -20000000 | CQ77: -20500000 | CR77: -21000000 | CS77: =CR77+CR78 -> -20731601 | CT77: =CS77+CS78 -> -20445958 | CU77: =CT77+CT78 -> -20503073 | CV77: =CU77+CU78 -> -20488982 | CW77: =CV77+CV78 -> -20358287 | CX77: =CW77+CW78 -> -19659489 | CY77: =CX77+CX78 -> -18569611 | CZ77: =CY77+CY78 -> -17113235 | ... FA77: =EZ77+EZ78 -> 1.1441258e+08
A78: Resultado del Ejercicio | CP78: =CP31 -> -591170.39 | CR78: =CR31 -> 268399.2 | CS78: =CS31 -> 285642.89 | CT78: =CT31 -> -57115.333 | CU78: =CU31 -> 14091.496 | CV78: =CV31 -> 130694.74 | CW78: =CW31 -> 698797.53 | CX78: =CX31 -> 1089878.7 | CY78: =CY31 -> 1456375.7 | ... FA78: =FA31 -> 742415.02
A79: Capitalización Adicional | CP79: 0 | CR79: =Supuestos!$D$5 -> 20000000 | CS79: =Supuestos!$D$5 -> 20000000 | CT79: =Supuestos!$D$5 -> 20000000 | CU79: =Supuestos!$D$5 -> 20000000 | CV79: =Supuestos!$D$5 -> 20000000 | CW79: =Supuestos!$D$5 -> 20000000 | CX79: =Supuestos!$D$5 -> 20000000 | CY79: =Supuestos!$D$5 -> 20000000 | ... FA79: =Supuestos!$D$5 -> 20000000
A80: Castigo por Vesting | CP80: -10200000 | CR80: -10200000 | CS80: -10200000 | CT80: -10200000 | CU80: -10200000 | CV80: -10200000 | CW80: -10200000 | CX80: -10200000 | CY80: -10200000 | CZ80: -10200000 | DA80: -10200000 | DB80: -10200000 | DC80: -10200000 | DD80: -10200000 | DE80: -10200000 | DF80: -10200000 | DG80: -10200000 | DH80: -10200000 | DI80: -10200000 | DJ80: -10200000 | DK80: -10200000 | DL80: -10200000 | DM80: -10200000 | DN80: -10200000 | DO80: -10200000 | DP80: -10200000 | DQ80: -10200000 | DR80: -10200000 | DS80: -10200000 | DT80: -10200000 | DU80: -10200000 | DV80: -10200000 | DW80: -10200000 | DX80: -10200000 | DY80: -10200000 | DZ80: -10200000 | EA80: -10200000 | EB80: -10200000 | EC80: -10200000 | ED80: -10200000 | EE80: -10200000 | EF80: -10200000 | EG80: -10200000 | EH80: -10200000 | EI80: -10200000 | EJ80: -10200000 | EK80: -10200000 | EL80: -10200000 | EM80: -10200000 | EN80: -10200000 | EO80: -10200000 | EP80: -10200000 | EQ80: -10200000 | ER80: -10200000 | ES80: -10200000 | ET80: -10200000 | EU80: -10200000 | EV80: -10200000 | EW80: -10200000 | EX80: -10200000 | EY80: -10200000 | EZ80: -10200000 | FA80: -10200000
A81: Total Capital | CP81: =SUM(CP75:CP80) -> -4459170.4 | CR81: =SUM(CR75:CR80)+CR82 -> 15400399 | CS81: =SUM(CS75:CS80)+CS82 -> 15686042 | CT81: =SUM(CT75:CT80)+CT82 -> 15628927 | CU81: =SUM(CU75:CU80)+CU82 -> 15643018 | CV81: =SUM(CV75:CV80)+CV82 -> 15773713 | CW81: =SUM(CW75:CW80)+CW82 -> 16472511 | CX81: =SUM(CX75:CX80)+CX82 -> 17562389 | CY81: =SUM(CY75:CY80)+CY82 -> 19018765 | ... FA81: =SUM(FA75:FA80)+FA82 -> 1.51287e+08
A83: Índice de Capitalización vs. Activos | CP83: =CP81/CP63 -> -0.61043523 | CR83: =CR81/CR63 -> 0.55950587 | CS83: =CS81/CS63 -> 0.56988345 | CT83: =CT81/CT63 -> 0.56780842 | CU83: =CU81/CU63 -> 0.32915346 | CV83: =CV81/CV63 -> 0.2522785 | CW83: =CW81/CW63 -> 0.16890552 | CX83: =CX81/CX63 -> 0.15607544 | CY83: =CY81/CY63 -> 0.14913754 | ... FA83: =FA81/FA63 -> 1.0277649
A84: Índice de Apalancamiento vs. Capital | CP84: =CP73/CP81 -> -2.9142192 | CR84: =CR73/CR81 -> 0.82253821 | CS84: =CS73/CS81 -> 0.79734677 | CT84: =CT73/CT81 -> 0.79016044 | CU84: =CU73/CU81 -> 2.058031 | CV84: =CV73/CV81 -> 2.9822117 | CW84: =CW73/CW81 -> 4.9712842 | CX84: =CX73/CX81 -> 5.5084033 | CY84: =CY73/CY81 -> 5.8675784 | ... FA84: =FA73/FA81 -> 0.040826053
A85: Apalancamiento vs. Cartera | CP85: =CP73/CP56 -> 2.0642535 | CR85: =CR73/CR56 -> 0.48322959 | CS85: =CS73/CS56 -> 0.47790809 | CT85: =CT73/CT56 -> 0.47263307 | CU85: =CU73/CU56 -> 0.69852675 | CV85: =CV73/CV56 -> 0.77055709 | CW85: =CW73/CW56 -> 0.85295858 | CX85: =CX73/CX56 -> 0.87179625 | CY85: =CY73/CY56 -> 0.8861586 | ... FA85: =FA73/FA56 -> 0.049411608
A86: Rendimiento Total Cartera y Portafolio | CP86: =(CP2+CP7+CP41+CP42)/(CP39-CP37+CP56)*12 -> 0.27966605 | CR86: =(CR2+CR7+CR41+CR42)/(CR39-CR37+CR56)*12 -> 0.32359 | CS86: =(CS2+CS7+CS41+CS42)/(CS39-CS37+CS56)*12 -> 0.32465717 | CT86: =(CT2+CT7+CT41+CT42)/(CT39-CT37+CT56)*12 -> 0.29792175 | CU86: =(CU2+CU7+CU41+CU42)/(CU39-CU37+CU56)*12 -> 0.32148484 | CV86: =(CV2+CV7+CV41+CV42)/(CV39-CV37+CV56)*12 -> 0.31382425 | CW86: =(CW2+CW7+CW41+CW42)/(CW39-CW37+CW56)*12 -> 0.30921444 | CX86: =(CX2+CX7+CX41+CX42)/(CX39-CX37+CX56)*12 -> 0.29454936 | CY86: =(CY2+CY7+CY41+CY42)/(CY39-CY37+CY56)*12 -> 0.29457407 | ... FA86: =(FA2+FA7+FA41+FA42)/(FA39-FA37+FA56)*12 -> 0.10914313
A87: Rentabilidad sobre Cartera y Portafolio | CP87: =(CP78)/(CP39-CP37+CP56)*12 -> -0.052230972 | CR87: =(CR78)/(CR39-CR37+CR56)*12 -> 0.021017275 | CS87: =(CS78)/(CS39-CS37+CS56)*12 -> 0.022206958 | CT87: =(CT78)/(CT39-CT37+CT56)*12 -> -0.0044084217 | CU87: =(CU78)/(CU39-CU37+CU56)*12 -> 0.00095752086 | CV87: =(CV78)/(CV39-CV37+CV56)*12 -> 0.0081371964 | CW87: =(CW78)/(CW39-CW37+CW56)*12 -> 0.036637043 | CX87: =(CX78)/(CX39-CX37+CX56)*12 -> 0.053373452 | CY87: =(CY78)/(CY39-CY37+CY56)*12 -> 0.06690704 | ... FA87: =(FA78)/(FA39-FA37+FA56)*12 -> 0.026149662
A88: Cartera Vencida | CQ88: =CQ37/CQ39 -> 0.17398125

Sheet EFs KDP
A1: Estado de resultados | B1: 44713 | C1: 44805 | D1: 44896 | E1: 44986 | F1: 45078 | G1: 45170 | H1: 45261 | I1: 45352 | J1: 45444 | K1: 45536
A2: Comisiones cobradas | B2: 3031 | C2: 5147 | D2: 7230 | E2: 2199 | F2: 2974 | G2: 4870 | H2: 7076 | I2: 2519 | J2: 5696 | K2: 8874
A3: Comisiones pagadas | B3: -112 | C3: -247 | D3: -322 | E3: -111 | F3: -194 | G3: -346 | H3: -515 | I3: -612 | J3: -1574 | K3: -2635
A4: Resultado por Servicios | B4: =SUM(B2:B3) -> 2919 | C4: =SUM(C2:C3) -> 4900 | D4: =SUM(D2:D3) -> 6908 | E4: =SUM(E2:E3) -> 2088 | F4: =SUM(F2:F3) -> 2780 | G4: =SUM(G2:G3) -> 4524 | H4: =SUM(H2:H3) -> 6561 | I4: =SUM(I2:I3) -> 1907 | ... K4: =SUM(K2:K3) -> 6239
A5: Ingresos por intereses | B5: 357 | C5: 656 | D5: 880 | E5: 262 | F5: 699 | G5: 874 | H5: 1256 | I5: 386 | J5: 761 | K5: 1093
A6: Resultado por valuación a valor razonable | B6: 1 | C6: 231 | D6: 263 | E6: 19 | F6: 538 | G6: 1252 | H6: 1282 | I6: 1 | J6: 1 | K6: 1
A7: Gastos por Intereses | B7: -144 | C7: -245 | D7: -245 | E7: 0 | F7: 0 | G7: 0 | H7: 0 | I7: 0 | J7: 0 | K7: 0
A8: Margen Financiero por Intermediación | B8: =SUM(B5:B7)+B4 -> 3133 | C8: =SUM(C5:C7)+C4 -> 5542 | D8: =SUM(D5:D7)+D4 -> 7806 | E8: =SUM(E5:E7)+E4 -> 2369 | F8: =SUM(F5:F7)+F4 -> 4017 | G8: =SUM(G5:G7)+G4 -> 6650 | H8: =SUM(H5:H7)+H4 -> 9099 | I8: =SUM(I5:I7)+I4 -> 2294 | ... K8: =SUM(K5:K7)+K4 -> 7333
A9: Otros ingresos (egresos) de la operación | B9: 1886 | C9: 1882 | D9: 1597 | E9: -401 | F9: -512 | G9: -565 | H9: -602 | I9: 67 | J9: 65 | K9: 171
A10: Gastos de Administración y Promoción | B10: -4616 | C10: -7689 | D10: -13731 | E10: -3446 | F10: -7176 | G10: -11329 | H10: -15660 | I10: -4272 | J10: -8109 | K10: -12211
A11: Impuestos a la utilidad y diferido | B11: 434 | C11: 378 | D11: 449 | E11: 0 | F11: -154 | G11: -174 | H11: -332 | I11: 0 | J11: 0 | K11: 0
A12: Resultado Neto | B12: =SUM(B9:B11)+B8 -> 837 | C12: =SUM(C9:C11)+C8 -> 113 | D12: =SUM(D9:D11)+D8 -> -3879 | E12: =SUM(E9:E11)+E8 -> -1478 | F12: =SUM(F9:F11)+F8 -> -3825 | G12: =SUM(G9:G11)+G8 -> -5418 | H12: =SUM(H9:H11)+H8 -> -7495 | I12: =SUM(I9:I11)+I8 -> -1911 | ... K12: =SUM(K9:K11)+K8 -> -4707
A14: Cuentas Bajo Administración | B14: 44713 | C14: 44805 | D14: 44896 | E14: 44986 | F14: 45078 | G14: 45170 | H14: 45261 | I14: 45352 | J14: 45444 | K14: 45536
A15: Deuda cuentas corrientes | B15: 2339 | C15: 3307 | D15: 5406 | E15: 4330 | F15: 4512 | G15: 4995 | H15: 6718 | I15: 5575 | J15: 5215 | K15: 6889
A16: Depósitos de inversionistas | B16: 4458 | C16: 5356 | D16: 4906 | E16: 7587 | F16: 7267 | G16: 6142 | H16: 6825 | I16: 8451 | J16: 9034 | K16: 8643
A17: Otras cuentas corrientes | B17: 6524 | C17: 8079 | D17: 10063 | E17: 11779 | F17: 11608 | G17: 10980 | H17: 13791 | I17: 13851 | J17: 13566 | K17: 15240
A18: Instrumentos financieros de clientes en administración | B18: 97373 | C18: 100058 | D18: 111072 | E18: 116535 | F18: 119344 | G18: 130759 | H18: 136571 | I18: 152097 | J18: 152920 | K18: 160492
A19: Colaterales recibidos en garanía por cuenta de solicitantes | B19: 117285 | C19: 125400 | D19: 134270 | E19: 151502 | F19: 166160 | G19: 186115 | H19: 203482 | I19: 198647 | J19: 208366 | K19: 216152
A20: Total Operaciones de Administración | B20: =SUM(B15:B19) -> 227979 | C20: =SUM(C15:C19) -> 242200 | D20: =SUM(D15:D19) -> 265717 | E20: =SUM(E15:E19) -> 291733 | F20: =SUM(F15:F19) -> 308891 | G20: =SUM(G15:G19) -> 338991 | H20: =SUM(H15:H19) -> 367387 | I20: =SUM(I15:I19) -> 378621 | ... K20: =SUM(K15:K19) -> 407416
A22: Balance General | B22: 44713 | C22: 44805 | D22: 44896 | E22: 44986 | F22: 45078 | G22: 45170 | H22: 45261 | I22: 45352 | J22: 45444 | K22: 45536
A23: Efectivo y equivalentes de efectivo | B23: 544 | C23: 6371 | D23: 1962 | E23: 3241 | F23: 2397 | G23: 3151 | H23: 945 | I23: 113 | J23: 634 | K23: 458
A24: Inversiones en instrumentos financieros | B24: 6209 | C24: 6678 | D24: 6905 | E24: 6430 | F24: 6187 | G24: 1298 | H24: 1996 | I24: 1476 | J24: 1516 | K24: 6208
A25: Estimación de pérdidas crediticias | B25: -1683 | C25: -1495 | D25: -1548 | E25: -1550 | F25: -1221 | G25: -403 | H25: -403 | I25: -403 | J25: -403 | K25: -403
A26: Cuentas por cobrar, neto | B26: 325 | C26: 1231 | D26: 6980 | E26: 7253 | F26: 7160 | G26: 11824 | H26: 11779 | I26: 11677 | J26: 11821 | K26: 11405
A27: Pagos anticipados y otros activos, neto | B27: 1630 | C27: 2000 | D27: 2472 | E27: 1696 | F27: 1675 | G27: 1529 | H27: 1549 | I27: 1511 | J27: 1460 | K27: 1419
A28: Propiedades, mobiliario y equipo, neto | B28: 132 | C28: 114 | D28: 96 | E28: 109 | F28: 180 | G28: 174 | H28: 207 | I28: 208 | J28: 210 | K28: 208
A29: Activo por impuestos a la utilidad diferidos, neto | B29: 505 | C29: 449 | D29: 520 | E29: 521 | F29: 366 | G29: 346 | H29: 268 | I29: 346 | J29: 346 | K29: 346
A30: Total Activo | B30: =SUM(B23:B29) -> 7662 | C30: =SUM(C23:C29) -> 15348 | D30: =SUM(D23:D29) -> 17387 | E30: =SUM(E23:E29)+1 -> 17701 | F30: =SUM(F23:F29)+1 -> 16745 | G30: =SUM(G23:G29)+1 -> 17920 | H30: =SUM(H23:H29) -> 16341 | I30: =SUM(I23:I29)+1 -> 14929 | J30: =SUM(J23:J29) -> 15584 | K30: =SUM(K23:K29)+1 -> 19642
A32: Préstamos de corto plazo | B32: 1058 | C32: 115 | D32: 17 | E32: 50 | F32: 89 | G32: 142 | H32: 114 | I32: 255 | J32: 59 | K32: 139
A33: Préstamos de largo plazo | B33: 1477 | C33: 10611 | D33: 10405 | E33: 9400 | F33: 8803 | G33: 8206 | H33: 7609 | I33: 7459 | J33: 6862 | K33: 11265
A34: Contribuciones por pagar | B34: 95 | C34: 155 | D34: 497 | E34: 450 | F34: 316 | G34: 461 | H34: 348 | I34: 633 | J34: 1021 | K34: 1011
A35: Acreedores diversas y otras cuentas por pagar | B35: 185 | C35: 310 | D35: 335 | E35: 505 | F35: 41 | G35: 229 | H35: 356 | I35: 80 | J35: 62 | K35: 223
A36: Aportaciones para futuros aumentos de capital como pasivos | B36: 0 | C36: 0 | D36: 0 | E36: 0 | F36: 0 | G36: 0 | H36: 0 | I36: 0 | J36: 2250 | K36: 0
A37: Pasivo por impuestos a la utilidad | B37: 44 | C37: 120 | D37: 88 | E37: 44 | F37: 92 | G37: 71 | H37: 164 | I37: 270 | J37: 211 | K37: 294
A38: Pasivo por Beneficios a Empleados | B38: 0 | C38: 0 | D38: 0 | E38: 185 | F38: 185 | G38: 185 | H38: 0 | I38: 232 | J38: 368 | K38: 506
A39: Total Pasivo | B39: =SUM(B32:B38) -> 2859 | C39: =SUM(C32:C38)+1 -> 11312 | D39: =SUM(D32:D38) -> 11342 | E39: =SUM(E32:E38) -> 10634 | F39: =SUM(F32:F38)-1 -> 9525 | G39: =SUM(G32:G38) -> 9294 | H39: =SUM(H32:H38) -> 8591 | I39: =SUM(I32:I38) -> 8929 | J39: =SUM(J32:J38) -> 10833 | K39: =SUM(K32:K38) -> 13438
A41: Capital Social | B41: 3564 | C41: 3564 | D41: 3564 | E41: 3564 | F41: 3564 | G41: 3564 | H41: 3564 | I41: 3564 | J41: 3564 | K41: 3564
A42: Aportaciones para futuros aumentos de capital | B42: 4568 | C42: 4568 | D42: 10568 | E42: 13068 | F42: 15568 | G42: 18568 | H42: 19768 | I42: 19768 | J42: 19768 | K42: 22768
A43: Resultados acumulados | B43: -3329 | C43: -4096 | D43: -8087 | E43: -9565 | F43: -11912 | G43: -13506 | H43: -15582 | I43: -17332 | J43: -18581 | K43: -20128
A44: Total Capital | B44: =SUM(B41:B43) -> 4803 | C44: =SUM(C41:C43) -> 4036 | D44: =SUM(D41:D43) -> 6045 | E44: =SUM(E41:E43) -> 7067 | F44: =SUM(F41:F43) -> 7220 | G44: =SUM(G41:G43) -> 8626 | H44: =SUM(H41:H43) -> 7750 | I44: =SUM(I41:I43) -> 6000 | ... K44: =SUM(K41:K43) -> 6204
A46: Balance | B46: =B39+B44-B30 -> 0 | C46: =C39+C44-C30 -> 0 | D46: =D39+D44-D30 -> 0 | E46: =E39+E44-E30 -> 0 | F46: =F39+F44-F30 -> 0 | G46: =G39+G44-G30 -> 0 | H46: =H39+H44-H30 -> 0 | I46: =I39+I44-I30 -> 0 | ... K46: =K39+K44-K30 -> 0

Sheet Notas
B2: Notas check Septiembre-25
B3: Insights | C3: Referencia | D3: Next Steps | E3: Avances
B4: Se esta viendo la opción de hacer un aumento de la linea de $10MDP. Se hablo con Mau para ver si esta opcion es viable dependiendo de como mejora tanto su cobranza como sus covenants. Nos comento que uno de los clientes con mayor concentración que esta atrasado "Materiales Franco" va a liquidar la linea y "Birsa" ya se recupero pero pedimos info para validar esto. Ahorita se encuentran en incumplimiento de todos los covenants porque en contrato se tiene que a partir del mes de agosto los covenants se iban a apretar.
B5: Birsa cliente con mayor concentracion paso a atraso con 38 dias y cuenta con un saldo de $13MDP llevando a un incumplimiento de cartera atrasada pasando de 6% a 15%. | C5: Loan Tape Septiembre 2025 | D5: Preguntar sobre la cobranza de este caso en particular y si se ve recuperación o no | E5: Nos comentaron que al día de hoy Oct ya se recuperó y no debería atrasarse nuevamente
B6: 9 créditos desaparecidos que contaban con días de atraso, afectando la confiabilidad de los datos que nos pasan e indicadores. Estos créditos representan un saldo insoluto total de $445,170 | C6: Loan Tape Septiembre 2025 | D6: Estos créditos realmente se liquidaron o porque no se registraron en la cartera de septiembre?
B7: 6 créditos con cambio en fecha de finalizacion, dos de ellos que debieron de terminar este mes con un saldo de $820,979 y se les aumento otro mes por lo que podrían ser créditos que no pagaron y solamente se les cambio la fecha de finalización para no tomarlos como atrasados. | C7: Loan Tape Septiembre 2025 | D7: Preguntar sobre el cambio de estas fechas, fueron acuerdos con los clientes?
B8: 1 crédito vencido sin movimiento en días de atraso y sin cambio en monto histórico pagado. Este crédito comoquiera ya se considera vencido pero el que no cambien los días de atraso desmuestra inconsistencias y errores dentro de su LT | C8: Loan Tape Septiembre 2025 | D8: Pedir que se registre este cambio en los días de atraso del cliente
B9: Recuperación de un crédito vencido: un crédito paso de 196 días a 0 días por lo que parece que se recupero porque si se ve aumento en el monto pagado histórico solo validar que se haya recuperado y ese monto pagado no solo represente lo que estaba vencido si no también lo que le tocaba pagar este mes | C9: Loan Tape Septiembre 2025 | D9: Platicar con ellos para comprobar que efectivamente el pago de este cliente se hizo incluyendo lo que le tocaba en el mes de septiembre y ya se encuentra al corriente
B10: 5 créditos que debieron de haber terminado este mes y pero siguen apareciendo con saldo insoluto y sin días de atraso. Estos 5 créditos representan un saldo total de $1,059,577 | C10: Loan Tape Septiembre 2025 | D10: Preguntar porque no se hicieron las liquidaciones de estos créditos, deben de ser atrasados?, fue error en el reporte?, se les dio chance?
B11: Hubo una baja en el capital contable ajustado que viene directamente de el aumento en pérdidas por resultado del ejercicio, por otro lado la cartera se quedo igual y dentro de sus pasivos aumentaron las contribuciones por pagar; llevando a un incumplimiento de capitalización que se encuentre en 13% y de apalancamiento ajustado en un 89%. | C11: Balance General Agosto 2025 | D11: Tomar en cuenta estos cambios para ver el aumento de la línea que se les quiere dar
B12: Aumento de estimación preventiva por aumento en cartera vencida llevando a mayores pérdidas en el mes y a un incumplimiento en la rentabilidad dejando el indicador en -0.8% | C12: Estado de Resultados Agosto 2025
B14: Notas check Agosto-25
B15: Insights | C15: Referencia | D15: Next Steps | E15: Avances
B16: Se sigue avanzando con la compra de cartera de CiBanco y con Fincitri. Mauricio quiere dar una propiedad suya como garantia.Si se completa esta compra de cartera es es bueno tanto para RG como para nosotros porque van a tener una cartera mas sana y más grande por lo que nuestros indicadores como el IMOR16 van a bajar y esta cartera se debe compartar de mejor manera (es menos riesgosa).
B17: Aumento IMOR16 de 9.89% a 11.19%: algunos créditos pasaron a 90 días afectando el indicador y demostrando que no han podido manejar la cobranza. | C17: Loan Tape Agosto 2025 | D17: Seguir monitoreando la cobranza, preguntando sobre updates de alguna recuperación, y presionar para mejorar el indicador
B18: Aumento cartera vencida de 14.9% a 15.85%: ligado a lo mismo del IMOR16. | C18: Loan Tape Agosto 2025
B19: Tendencia de baja en rendimiento: por temas de menor cobranza se refleja en menores ingresos proporcionale al valor de su portafolio. | C19: Monitoreo Julio 2025
B20: Sin aumento de estimacion preventiva: No se ve un aumento en la estimación preventiva aun teniendo aumento en cartera vencida | C20: Estado de Resultados Julio 2025 | D20: Preguntar porque no se ve este aumento y pedir que se haga
B21: Clientes sin movimientos en días de atraso: Se ven algunos clientes como Birsa, acciones ecologicas, materiales franco, que tienen alta concentración en la cartera sin movimiento en los días de atraso y ya se válido que se debe a que si han estado haciendo sus pagos correspondientes mes con mes solo no han pagado los meses atrasados. Esto demuestra que han podido estar en contacto con estos clientes y cobrando lo actual sin dejar que pasen a ser vencidos. | C21: Loan Tape Agosto 2025 | D21: Seguir monitoreando estos clientes que tienen mayor concentración
B22: Cliente "desplasificate" con baja en días de atraso: Este cliente sigue pagando y también pago un mes de los que estaba atrasado por lo que se ve esa baja en dís de atraso y demuestra igual comunicación en cobranza y recuperación. | C22: Loan Tape Agosto 2025
D23: Seguir monitoreando el proceso con CiBanco y Fincitri
B25: Notas check Julio-25
B26: Insights | C26: Referencia | D26: Next Steps | E26: Avances
B27: Contexto: Incumplimientos de covenants cartera vencida e IMOR16. El IMOR16 ya subio de 7.5% por lo que el aforo debe subir a 1.5. Acutalmente estamos desaforados con 4.75, se esta viendo el proceso para esa nueva cesión pero Mau de mucha igual esta buscando bajar ese indicador del IMOR16 porque si le afecta en otros financiamientos el tenernos cedido 1.5 de aforo.
B28: Atraso de 8 dias del cliente más grande (Birsa) representa un 7%. No se habia visto con atrasos anteriormente | C28: Loan Tape Julio 2025 | D28: Montirorear que el proximo mes haya pagado y en caso de que no hablar con RG notificarles esto y presionar en que se mejore la cobranza
B29: Materiales franco sigue atrasado y en algunos de sus créditos a un mes de pasar a vencido. Es el crédito que comentaron que es un primo de el y si va a pagar pero seguirlo monitoreando porque representa un 4%. | C29: Loan Tape Julio 2025 | D29: Preguntar porque no se ha recuperado este cliente que es primo y cuando debe verse recuperado
B30: Aportaciones para futuros aumentos de capital: sigue aumentando las aportaciones desde 2024 pero no se ve un aumento en capital social. De mayo a junio aumento 2.5MDP | C30: Estado de Resultados Junio 2025
B31: Acciones ecologicas: Cliente atrasado con 30 días que representa 1% de la cartera total | C31: Loan Tape Julio 2025
B32: Comentaron sobre una oportunidad que tienen de comprar cartera de créditos solares de CI Banco, con tasa de 15% esos créditos.
B39: Notas check Junio-25
B40: Insights | C40: Referencia | D40: Next Steps | E40: Avances
B41: Contexto: Se hizo nueva cesión e hicieron una disposición el lunes de $3MDP. Se planea hacer la última disposición de $6MDP la próxima semana pero hubo unos errores con OPAM entonces se debe resolver y checar 100% que el aforo este bien para ver si se puede hacer esa siguiente disposición o si nos deben ceder más.
B42: En abril no se reportaron gastos por intereses y en mayo se vio un monto más grande. Validamos los intereses que nos pagaron a nosotros esos meses y coincide lo que pusieron en mayo con la sujma de sus pagos de abril y mayo. | C42: Estado de Resultados Mayo 25 | D42: Platicar sobre los desfases en los gastos, que fue lo que paso con no llevaron ese registro en abril? | E42: Nosotros les facturamos esos gastos hasta despues
B43: Reportaron mayores gastos en Mayo dejandolos con muy pooco margen financiero positivo. La cuenta de "resultado por valuación a valor razonable" no sabemos que es y paso de $0MXN a -$725 mil MXN de abril a mayo. Asi como mayores gastos en admin y menores ingresos. | C43: Estado de Resultados Mayo 25 | D43: Preguntar y entender que es esqa cuenta de "Resultado por valuación a valor razonable" y que cambios hubo que hicieron que haya menos ingresos y mayores gastos | E43: La cuenta de resutaldo por valuacion razonable es la estimacion preventiva
B44: La cartera se mantuvo practicamente igual de abril a mayo | C44: Balance general Mayo 25 | D44: Preguntar si no hubo muchas colocaciones? Se amortizo la misma cantidad que se coloco? | E44: Lo iban a checar porque dijeron que no deberia ser igual
B45: IMOR16 sigue aumentando. Paso de 7.11% en mayo a 7.40% en junio. Si llegan a 7.5% es cuando aumenta el aforo requerido | C45: Loan Tape Junio 25 | D45: Tenerlos al tanto de la situación y estar pendiente de como se mueve el IMOR16 en julio para ver si brinca a ese nuevo aforo de 1.5
B46: Cartera atrasada aumento de 5% a 10% dejandolos muy cerca del incumplimiento del covenant. Y lo mismo con la cartera vencido aumento de 12.9% a 13.3% lo que los acerca al incumplimiento del convenant de cartera vencida con diferencia de 0.7% | C46: Loan Tape Junio 25 | D46: Hablar con ellos sobre la cobranza, qué esta ocasionando estos aumentos y que planes tienen para recuperarlos?
B47: Incumplimiento de covenant: apalancamiento ajustado con 91%. En las proyecciones de originación si se esperaba que el apalancamiento este más alto estos meses, esperando que baje cuando empiece a amortizar. Al igual sacamos el apalancamiento restandole el efectivo a los pasivos (que es lo correcto) y asi se encuentran en 88.5% | C47: Estado de Resultados Mayo 25 | D47: Seguir monitoreando
B48: Caso Herguin: Cliente de puebla que representa un 3% de la cartera total de RG atrasado ya con 148 días no se ha recuperado ninguno de sus créditos. Desde abril paso a cartera vencida. | C48: Loan Tape Junio 25 | D48: Preguntar contexto y actualización del caso
B49: Caso Materiales Franco: cliente que representa un 4% con 8 créditos en su cartera de los cuales 6 ya pasaron a cartera atrasada y las otras dos tienen 28 dias de atraso pero se consideran vigentes. | C49: Loan Tape Junio 25 | D49: Preguntar contexto y actualización del caso | E49: Nos comenta que es un primo y si debe de pagar
B50: Nuevo cliento con mayor concentración: Ebony que representa un 4% | C50: Loan Tape Junio 25
B52: Notas check Mayo-25
B53: Insights | C53: Referencia | D53: Next Steps | E53: Avances
B54: Contexto: se hizo una cesión de cartera para las nuevas disposiciones. Dos disposiciones una de $4MDP y otra de $9MDP. Se espera hacer otra disposición de $9MDP
B55: 1.- Aumento de IMOR16, se encuentra en 7.11% y si llega a 7.5% el aforo debe de subir | C55: Loan Tape Mayo 25
B56: 2.- Aumento de cartera vencida a 13% con incumplimiento en 14% | C56: Loan tape Mayo 25
B57: 3.- Nuevo cliente con mayor concentración
B64: Notas check Abr-25
B65: Insights | C65: Referencia | D65: Next Steps | E65: Avances
B66: Contexto: Se dispusieron $14MDP de los que se pensaba que con la cesión pasada para el aforo se podia disponer, hubo errores de comunicación entre OPAM, nosotros, y Red Girasol. OPAM nos dijo que si tenian el aforo para disponer $4MDP despues de los $10MDP que dispusieron pero realmente no se tenia el aforo suficiente. Se esta buscando tener otra cesión pero RG esta esperando saber si si vamos a poder darles el saldo faltante del crédito para que ya nos cedan todo o solamente lo de los $4MDP.
B67: 1.- No existe registro de estimación preventiva en el ER, solamente en el BG | C67: Estado de Resultados Abr 25 | D67: Preguntarles porque no se lleva ese registro e incitar a que es importante que lo agreguen
B68: 2.- No estan incluyendo gastos por intereses, la cuenta sale como $0 cuando si nos pagaron a nosotros | C68: Estado de Resultados Abr25 | D68: Preguntar porque no incluyen los gastos por intereses? Hay algun tema en la contabilidad?
B69: 3.- Aportaciones para futuros aumentos: tienen esta cuenta la cual va aumentando desde el 2023 y ahorita cuentan con $25MDP a diferencia de $22MDPO del mes pasado. | C69: Balance General Abr25 | D69: Preguntarles si planean protocalizar esto y pasarlo a su capital, porque esta ahí parado, de donde vienen estos aumentos? Cuales es su plan con esta cuenta? Saber donde esta en activos
B70: 4.- Nueva cuenta en capital reportada como "Total participación no controlada" de $-642 mil pesos | C70: Balance General Abr25 | D70: Preguntarles sobre esta nueva cuenta, qué es?
B71: 5.- Vemos que OPAM no esta restando unas cuentas que deben ser como inelegibles | C71: OPAM Abr25 | D71: Platicar con ellos para no dejar pasar esas pequeñas diferencias
B72: 6.- Aumento su cartera $12MDP al igual que su deuda, demostrando que si están utilizando su fondeo para colocar y crecer su cartera
B73: 7.- Hacer nuevo check y análisis de atrasos y vencido por cliente, no solo por crédito. Ver esa diferencia para ver si es importante tomarlo en cuenta en los covenants. | C73: Análisis LT Abr25
B77: Notas check Mar-25
B78: Insights | C78: Referencia | D78: Next Steps | E78: Avances
B79: 1.- No existe registro de estimación preventiva en el ER | C79: Estado de resultados | D79: Checar con ellos, porque no ponen ese registro? | E79: Prioridades: creemos que el aforo es más importante y salieron temas acerca de eso entonces decidimos buscar reslover antes de hacer estas preguntas, vamos a esperar a cuando manden la info de mayo para hacer esa pregunta
B80: 2.- Aumento de cartera vencida y atrasada | C80: Loan Tape | D80: Platicar con ellos sobre porque esta pasando con la cobranza, y si esperan recuperar algo | E80: Si vimos recuperación tanto de cartera atrasada como de cartera vencida, nos comentaron que si tenian tema con un cliente de $4MDP que no estaba contestando y ya lo estaban demandando. Creemos que recuperaron ese cliente
B81: 3.- El LT no se esta compartiendo en el formato solicitado | C81: Loan Tape | D81: Pedir que no se cambie el formato y regrese al formato solicitado
B82: 4.- Agregar el check de moffin/syntage | E82: Ya se agregó, hace falta la declaración anual
B83: 5.- No se ve la declaración anual en syntage | C83: Syntage | D83: Preguntar que pasó, porque no se ve el registro | E83: Volvimos a correr la declaración anual de syntage y siguen sin tenerla, junto con la opinión de cumplimiento negativa
